Workbook

Sheet StudentData
A1: Mason
A2: Stephens
A3: 80679969
A4: 45716.947

Sheet DivData
A1: Ticker | B1: Monthly Calendar Date | C1: Shares Outstanding | D1: Distribution Ordinary Dividend Flag | E1: Dividend Amount | F1: Factor To Adjust Shares
A2: UVV | B2: 38016 | C2: 24992 | D2: Y | E2: 0.39 | F2: 0
A3: UVV | B3: 38044 | C3: 25141
A4: UVV | B4: 38077 | C4: 25141
A5: UVV | B5: 38107 | C5: 25141 | D5: Y | E5: 0.39 | F5: 0
A6: UVV | B6: 38135 | C6: 25141
A7: UVV | B7: 38168 | C7: 25466
A8: UVV | B8: 38198 | C8: 25515 | D8: Y | E8: 0.39 | F8: 0
A9: UVV | B9: 38230 | C9: 25532
A10: UVV | B10: 38260 | C10: 25532
A11: UVV | B11: 38289 | C11: 25532 | D11: Y | E11: 0.39 | F11: 0
A12: UVV | B12: 38321 | C12: 25535
A13: UVV | B13: 38352 | C13: 25535
A14: UVV | B14: 38383 | C14: 25535 | D14: Y | E14: 0.42 | F14: 0
A15: UVV | B15: 38411 | C15: 25622
A16: UVV | B16: 38442 | C16: 25622
A17: UVV | B17: 38471 | C17: 25622 | D17: Y | E17: 0.42 | F17: 0
A18: UVV | B18: 38503 | C18: 25669
A19: UVV | B19: 38533 | C19: 25669
A20: UVV | B20: 38562 | C20: 25683 | D20: Y | E20: 0.42 | F20: 0
A21: UVV | B21: 38595 | C21: 25705
A22: UVV | B22: 38625 | C22: 25705
A23: UVV | B23: 38656 | C23: 25705 | D23: Y | E23: 0.42 | F23: 0
A24: UVV | B24: 38686 | C24: 25715
A25: UVV | B25: 38716 | C25: 25715
A26: UVV | B26: 38748 | C26: 25715 | D26: Y | E26: 0.43 | F26: 0
A27: UVV | B27: 38776 | C27: 25723
A28: UVV | B28: 38807 | C28: 25723
A29: UVV | B29: 38835 | C29: 25723 | D29: Y | E29: 0.43 | F29: 0
A30: UVV | B30: 38868 | C30: 25723
A31: UVV | B31: 38898 | C31: 25748
A32: UVV | B32: 38929 | C32: 25748 | D32: Y | E32: 0.43 | F32: 0
A33: UVV | B33: 38960 | C33: 25748
A34: UVV | B34: 38989 | C34: 25748
A35: UVV | B35: 39021 | C35: 25748 | D35: Y | E35: 0.43 | F35: 0
A36: UVV | B36: 39051 | C36: 25775
A37: UVV | B37: 39080 | C37: 25775
A38: UVV | B38: 39113 | C38: 25775 | D38: Y | E38: 0.44 | F38: 0
A39: UVV | B39: 39141 | C39: 25969
A40: UVV | B40: 39171 | C40: 25969
A41: UVV | B41: 39202 | C41: 25969 | D41: Y | E41: 0.44 | F41: 0
A42: UVV | B42: 39233 | C42: 27027
A43: UVV | B43: 39262 | C43: 27350
A44: UVV | B44: 39294 | C44: 27350 | D44: Y | E44: 0.44 | F44: 0
A45: UVV | B45: 39325 | C45: 27363
A46: UVV | B46: 39353 | C46: 27363
A47: UVV | B47: 39386 | C47: 27363 | D47: Y | E47: 0.44 | F47: 0
A48: UVV | B48: 39416 | C48: 27375
A49: UVV | B49: 39447 | C49: 27375
A50: UVV | B50: 39478 | C50: 27375 | D50: Y | E50: 0.45 | F50: 0
A51: UVV | B51: 39507 | C51: 27189
A52: UVV | B52: 39538 | C52: 27189
A53: UVV | B53: 39568 | C53: 27189 | D53: Y | E53: 0.45 | F53: 0
A54: UVV | B54: 39598 | C54: 26983
A55: UVV | B55: 39629 | C55: 26576
A56: UVV | B56: 39660 | C56: 26576 | D56: Y | E56: 0.45 | F56: 0
A57: UVV | B57: 39689 | C57: 25411
A58: UVV | B58: 39721 | C58: 25411
A59: UVV | B59: 39752 | C59: 25411 | D59: Y | E59: 0.45 | F59: 0
A60: UVV | B60: 39780 | C60: 24987
A61: UVV | B61: 39813 | C61: 24987
A62: UVV | B62: 39843 | C62: 24987 | D62: Y | E62: 0.46 | F62: 0
A63: UVV | B63: 39871 | C63: 24987
A64: UVV | B64: 39903 | C64: 24987
A65: UVV | B65: 39933 | C65: 24987 | D65: Y | E65: 0.46 | F65: 0
A66: UVV | B66: 39962 | C66: 24999
A67: UVV | B67: 39994 | C67: 24958
A68: UVV | B68: 40025 | C68: 24958 | D68: Y | E68: 0.46 | F68: 0
A69: UVV | B69: 40056 | C69: 24819
A70: UVV | B70: 40086 | C70: 24819
A71: UVV | B71: 40116 | C71: 24819 | D71: Y | E71: 0.46 | F71: 0
A72: UVV | B72: 40147 | C72: 24684
A73: UVV | B73: 40178 | C73: 24684
A74: UVV | B74: 40207 | C74: 24684 | D74: Y | E74: 0.47 | F74: 0
A75: UVV | B75: 40235 | C75: 24495
A76: UVV | B76: 40268 | C76: 24495
A77: UVV | B77: 40298 | C77: 24495 | D77: Y | E77: 0.47 | F77: 0
A78: UVV | B78: 40326 | C78: 24165
A79: UVV | B79: 40359 | C79: 24153
A80: UVV | B80: 40389 | C80: 24153 | D80: Y | E80: 0.47 | F80: 0
A81: UVV | B81: 40421 | C81: 24155
A82: UVV | B82: 40451 | C82: 24155
A83: UVV | B83: 40480 | C83: 24155 | D83: Y | E83: 0.47 | F83: 0
A84: UVV | B84: 40512 | C84: 23793
A85: UVV | B85: 40543 | C85: 23793
A86: UVV | B86: 40574 | C86: 23793 | D86: Y | E86: 0.48 | F86: 0
A87: UVV | B87: 40602 | C87: 23456
A88: UVV | B88: 40633 | C88: 23456
A89: UVV | B89: 40662 | C89: 23456 | D89: Y | E89: 0.48 | F89: 0
A90: UVV | B90: 40694 | C90: 23160
A91: UVV | B91: 40724 | C91: 23230
A92: UVV | B92: 40753 | C92: 23230 | D92: Y | E92: 0.48 | F92: 0
A93: UVV | B93: 40786 | C93: 23227
A94: UVV | B94: 40816 | C94: 23227
A95: UVV | B95: 40847 | C95: 23227 | D95: Y | E95: 0.48 | F95: 0
A96: UVV | B96: 40877 | C96: 23230
A97: UVV | B97: 40907 | C97: 23230
A98: UVV | B98: 40939 | C98: 23230 | D98: Y | E98: 0.49 | F98: 0
A99: UVV | B99: 40968 | C99: 23245
A100: UVV | B100: 40998 | C100: 23245
...

Sheet RtrnData
A1: Ticker | B1: Monthly Calendar Date | C1: Monthly Total Return | D1: Value-weighted return including dividends
A2: UVV | B2: 43861 | C2: -0.055898687 | D2: -0.0017278557
A3: UVV | B3: 43889 | C3: -0.071495767 | D3: -0.077917925
A4: UVV | B4: 43921 | C4: -0.104154 | D4: -0.14173291
A5: UVV | B5: 43951 | C5: 0.11191323 | D5: 0.12967378
A6: UVV | B6: 43980 | C6: -0.089104817 | D6: 0.053738803 | G6: Lin Est | J6: Mkt Rtrn
A7: UVV | B7: 44012 | C7: -0.035179301 | D7: 0.025299125 | G7: {=LINEST(C2:C61,D2:D61,1,1)} -> 0.79677005 | H7: -0.0011540326 | J7: 0.1
A8: UVV | B8: 44043 | C8: 0.01029759 | D8: 0.055531515 | G8: 0.18175516 | H8: 0.0098974883
A9: UVV | B9: 44074 | C9: 0.029648956 | D9: 0.068442205 | G9: 0.24887304 | H9: 0.074951274
A10: UVV | B10: 44104 | C10: -0.035245335 | D10: -0.035055977 | G10: 19.217306 | H10: 58
A11: UVV | B11: 44134 | C11: -0.031624809 | D11: -0.020178318 | G11: 0.10795693 | H11: 0.32582622
A12: UVV | B12: 44165 | C12: 0.14203262 | D12: 0.123707
A13: UVV | B13: 44196 | C13: 0.068116897 | D13: 0.045048306
A14: UVV | B14: 44225 | C14: -0.042460832 | D14: -0.00063112875 | G14: Dicount Rate | H14: =H7+G7*J7 -> 0.078522973
A15: UVV | B15: 44253 | C15: 0.10791367 | D15: 0.029196292
A16: UVV | B16: 44286 | C16: 0.16076348 | D16: 0.030573271
A17: UVV | B17: 44316 | C17: -0.034053838 | D17: 0.048190158
A18: UVV | B18: 44344 | C18: -0.0033789792 | D18: 0.0070918504
A19: UVV | B19: 44377 | C19: 0.016595289 | D19: 0.02342178
A20: UVV | B20: 44407 | C20: -0.071358019 | D20: 0.01182778
A21: UVV | B21: 44439 | C21: -0.029907975 | D21: 0.027146419
A22: UVV | B22: 44469 | C22: -0.04486166 | D22: -0.042243373
A23: UVV | B23: 44498 | C23: -0.012133032 | D23: 0.0646505
A24: UVV | B24: 44530 | C24: -0.0091489362 | D24: -0.018350523
A25: UVV | B25: 44561 | C25: 0.17929998 | D25: 0.033341265
A26: UVV | B26: 44592 | C26: 0.0048184361 | D26: -0.059822418
... A61: UVV | B61: 45657 | C61: -0.039915966 | D61: -0.031582433

Sheet DivGrth
A1: =DivData!A1 -> Ticker | B1: =DivData!B1 -> Monthly Calendar Date | C1: =DivData!C1 -> Shares Outstanding | D1: =DivData!D1 -> Distribution Ordinary Dividend Flag | E1: =DivData!E1 -> Dividend Amount | F1: =DivData!F1 -> Factor To Adjust Shares | G1: Year | H1: OrdDiv | I1: SpltFac | J1: SplitAdj | L1: Year | M1: Ann Div | N1: Growth
A2: =DivData!A2 -> UVV | B2: =DivData!B2 -> 38016 | C2: =DivData!C2 -> 24992 | D2: =DivData!D2 -> Y | E2: =DivData!E2 -> 0.39 | F2: =DivData!F2 -> 0 | G2: =YEAR(B2) -> 2004 | H2: =IF(D2="Y",E2,) -> 0.39 | I2: =SUM($F$2:F2) -> 0 | J2: =H2*2^I2 -> 0.39 | L2: 2004 | M2: =SUMIF(G2:G253,L2,J2:J253) -> 1.56
A3: =DivData!A3 -> UVV | B3: =DivData!B3 -> 38044 | C3: =DivData!C3 -> 25141 | D3: =DivData!D3 | E3: =DivData!E3 -> 0 | F3: =DivData!F3 -> 0 | G3: =YEAR(B3) -> 2004 | H3: =IF(D3="Y",E3,) -> 0 | I3: =SUM($F$2:F3) -> 0 | J3: =H3*2^I3 -> 0 | L3: 2005 | M3: =SUMIF(G3:G254,L3,J3:J254) -> 1.68 | N3: =(M3-M2)/M2 -> 0.076923077
A4: =DivData!A4 -> UVV | B4: =DivData!B4 -> 38077 | C4: =DivData!C4 -> 25141 | D4: =DivData!D4 | E4: =DivData!E4 -> 0 | F4: =DivData!F4 -> 0 | G4: =YEAR(B4) -> 2004 | H4: =IF(D4="Y",E4,) -> 0 | I4: =SUM($F$2:F4) -> 0 | J4: =H4*2^I4 -> 0 | L4: 2006 | M4: =SUMIF(G4:G255,L4,J4:J255) -> 1.72 | N4: =(M4-M3)/M3 -> 0.023809524 | P4: Median | Q4: =MEDIAN(N3:N22) -> 0.020620748
A5: =DivData!A5 -> UVV | B5: =DivData!B5 -> 38107 | C5: =DivData!C5 -> 25141 | D5: =DivData!D5 -> Y | E5: =DivData!E5 -> 0.39 | F5: =DivData!F5 -> 0 | G5: =YEAR(B5) -> 2004 | H5: =IF(D5="Y",E5,) -> 0.39 | I5: =SUM($F$2:F5) -> 0 | J5: =H5*2^I5 -> 0.39 | L5: 2007 | M5: =SUMIF(G5:G256,L5,J5:J256) -> 1.76 | N5: =(M5-M4)/M4 -> 0.023255814 | P5: Average | Q5: =AVERAGE(N3:N22) -> 0.038034073
A6: =DivData!A6 -> UVV | B6: =DivData!B6 -> 38135 | C6: =DivData!C6 -> 25141 | D6: =DivData!D6 | E6: =DivData!E6 -> 0 | F6: =DivData!F6 -> 0 | G6: =YEAR(B6) -> 2004 | H6: =IF(D6="Y",E6,) -> 0 | I6: =SUM($F$2:F6) -> 0 | J6: =H6*2^I6 -> 0 | L6: 2008 | M6: =SUMIF(G6:G257,L6,J6:J257) -> 1.8 | N6: =(M6-M5)/M5 -> 0.022727273 | P6: Std | Q6: =_xlfn.STDEV.S(N3:N22) -> 0.05171414
A7: =DivData!A7 -> UVV | B7: =DivData!B7 -> 38168 | C7: =DivData!C7 -> 25466 | D7: =DivData!D7 | E7: =DivData!E7 -> 0 | F7: =DivData!F7 -> 0 | G7: =YEAR(B7) -> 2004 | H7: =IF(D7="Y",E7,) -> 0 | I7: =SUM($F$2:F7) -> 0 | J7: =H7*2^I7 -> 0 | L7: 2009 | M7: =SUMIF(G7:G258,L7,J7:J258) -> 1.84 | N7: =(M7-M6)/M6 -> 0.022222222
A8: =DivData!A8 -> UVV | B8: =DivData!B8 -> 38198 | C8: =DivData!C8 -> 25515 | D8: =DivData!D8 -> Y | E8: =DivData!E8 -> 0.39 | F8: =DivData!F8 -> 0 | G8: =YEAR(B8) -> 2004 | H8: =IF(D8="Y",E8,) -> 0.39 | I8: =SUM($F$2:F8) -> 0 | J8: =H8*2^I8 -> 0.39 | L8: 2010 | M8: =SUMIF(G8:G259,L8,J8:J259) -> 1.88 | N8: =(M8-M7)/M7 -> 0.02173913
A9: =DivData!A9 -> UVV | B9: =DivData!B9 -> 38230 | C9: =DivData!C9 -> 25532 | D9: =DivData!D9 | E9: =DivData!E9 -> 0 | F9: =DivData!F9 -> 0 | G9: =YEAR(B9) -> 2004 | H9: =IF(D9="Y",E9,) -> 0 | I9: =SUM($F$2:F9) -> 0 | J9: =H9*2^I9 -> 0 | L9: 2011 | M9: =SUMIF(G9:G260,L9,J9:J260) -> 1.92 | N9: =(M9-M8)/M8 -> 0.021276596 | P9: Sub Sample
A10: =DivData!A10 -> UVV | B10: =DivData!B10 -> 38260 | C10: =DivData!C10 -> 25532 | D10: =DivData!D10 | E10: =DivData!E10 -> 0 | F10: =DivData!F10 -> 0 | G10: =YEAR(B10) -> 2004 | H10: =IF(D10="Y",E10,) -> 0 | I10: =SUM($F$2:F10) -> 0 | J10: =H10*2^I10 -> 0 | L10: 2012 | M10: =SUMIF(G10:G261,L10,J10:J261) -> 1.96 | N10: =(M10-M9)/M9 -> 0.020833333 | P10: Median | Q10: =MEDIAN(N3:N15) -> 0.021276596
A11: =DivData!A11 -> UVV | B11: =DivData!B11 -> 38289 | C11: =DivData!C11 -> 25532 | D11: =DivData!D11 -> Y | E11: =DivData!E11 -> 0.39 | F11: =DivData!F11 -> 0 | G11: =YEAR(B11) -> 2004 | H11: =IF(D11="Y",E11,) -> 0.39 | I11: =SUM($F$2:F11) -> 0 | J11: =H11*2^I11 -> 0.39 | L11: 2013 | M11: =SUMIF(G11:G262,L11,J11:J262) -> 2 | N11: =(M11-M10)/M10 -> 0.020408163 | P11: Average | Q11: =AVERAGE(N3:N15) -> 0.025453975
A12: =DivData!A12 -> UVV | B12: =DivData!B12 -> 38321 | C12: =DivData!C12 -> 25535 | D12: =DivData!D12 | E12: =DivData!E12 -> 0 | F12: =DivData!F12 -> 0 | G12: =YEAR(B12) -> 2004 | H12: =IF(D12="Y",E12,) -> 0 | I12: =SUM($F$2:F12) -> 0 | J12: =H12*2^I12 -> 0 | L12: 2014 | M12: =SUMIF(G12:G263,L12,J12:J263) -> 2.04 | N12: =(M12-M11)/M11 -> 0.02 | P12: Std | Q12: =_xlfn.STDEV.S(N3:N15) -> 0.015541805
A13: =DivData!A13 -> UVV | B13: =DivData!B13 -> 38352 | C13: =DivData!C13 -> 25535 | D13: =DivData!D13 | E13: =DivData!E13 -> 0 | F13: =DivData!F13 -> 0 | G13: =YEAR(B13) -> 2004 | H13: =IF(D13="Y",E13,) -> 0 | I13: =SUM($F$2:F13) -> 0 | J13: =H13*2^I13 -> 0 | L13: 2015 | M13: =SUMIF(G13:G264,L13,J13:J264) -> 2.08 | N13: =(M13-M12)/M12 -> 0.019607843
A14: =DivData!A14 -> UVV | B14: =DivData!B14 -> 38383 | C14: =DivData!C14 -> 25535 | D14: =DivData!D14 -> Y | E14: =DivData!E14 -> 0.42 | F14: =DivData!F14 -> 0 | G14: =YEAR(B14) -> 2005 | H14: =IF(D14="Y",E14,) -> 0.42 | I14: =SUM($F$2:F14) -> 0 | J14: =H14*2^I14 -> 0.42 | L14: 2016 | M14: =SUMIF(G14:G265,L14,J14:J265) -> 2.12 | N14: =(M14-M13)/M13 -> 0.019230769
A15: =DivData!A15 -> UVV | B15: =DivData!B15 -> 38411 | C15: =DivData!C15 -> 25622 | D15: =DivData!D15 | E15: =DivData!E15 -> 0 | F15: =DivData!F15 -> 0 | G15: =YEAR(B15) -> 2005 | H15: =IF(D15="Y",E15,) -> 0 | I15: =SUM($F$2:F15) -> 0 | J15: =H15*2^I15 -> 0 | L15: 2017 | M15: =SUMIF(G15:G266,L15,J15:J266) -> 2.16 | N15: =(M15-M14)/M14 -> 0.018867925
A16: =DivData!A16 -> UVV | B16: =DivData!B16 -> 38442 | C16: =DivData!C16 -> 25622 | D16: =DivData!D16 | E16: =DivData!E16 -> 0 | F16: =DivData!F16 -> 0 | G16: =YEAR(B16) -> 2005 | H16: =IF(D16="Y",E16,) -> 0 | I16: =SUM($F$2:F16) -> 0 | J16: =H16*2^I16 -> 0 | L16: 2018 | M16: =SUMIF(G16:G267,L16,J16:J267) -> 2.6 | N16: =(M16-M15)/M15 -> 0.2037037
A17: =DivData!A17 -> UVV | B17: =DivData!B17 -> 38471 | C17: =DivData!C17 -> 25622 | D17: =DivData!D17 -> Y | E17: =DivData!E17 -> 0.42 | F17: =DivData!F17 -> 0 | G17: =YEAR(B17) -> 2005 | H17: =IF(D17="Y",E17,) -> 0.42 | I17: =SUM($F$2:F17) -> 0 | J17: =H17*2^I17 -> 0.42 | L17: 2019 | M17: =SUMIF(G17:G268,L17,J17:J268) -> 3.02 | N17: =(M17-M16)/M16 -> 0.16153846
A18: =DivData!A18 -> UVV | B18: =DivData!B18 -> 38503 | C18: =DivData!C18 -> 25669 | D18: =DivData!D18 | E18: =DivData!E18 -> 0 | F18: =DivData!F18 -> 0 | G18: =YEAR(B18) -> 2005 | H18: =IF(D18="Y",E18,) -> 0 | I18: =SUM($F$2:F18) -> 0 | J18: =H18*2^I18 -> 0 | L18: 2020 | M18: =SUMIF(G18:G269,L18,J18:J269) -> 3.06 | N18: =(M18-M17)/M17 -> 0.013245033
A19: =DivData!A19 -> UVV | B19: =DivData!B19 -> 38533 | C19: =DivData!C19 -> 25669 | D19: =DivData!D19 | E19: =DivData!E19 -> 0 | F19: =DivData!F19 -> 0 | G19: =YEAR(B19) -> 2005 | H19: =IF(D19="Y",E19,) -> 0 | I19: =SUM($F$2:F19) -> 0 | J19: =H19*2^I19 -> 0 | L19: 2021 | M19: =SUMIF(G19:G270,L19,J19:J270) -> 3.1 | N19: =(M19-M18)/M18 -> 0.013071895
A20: =DivData!A20 -> UVV | B20: =DivData!B20 -> 38562 | C20: =DivData!C20 -> 25683 | D20: =DivData!D20 -> Y | E20: =DivData!E20 -> 0.42 | F20: =DivData!F20 -> 0 | G20: =YEAR(B20) -> 2005 | H20: =IF(D20="Y",E20,) -> 0.42 | I20: =SUM($F$2:F20) -> 0 | J20: =H20*2^I20 -> 0.42 | L20: 2022 | M20: =SUMIF(G20:G271,L20,J20:J271) -> 3.14 | N20: =(M20-M19)/M19 -> 0.012903226
A21: =DivData!A21 -> UVV | B21: =DivData!B21 -> 38595 | C21: =DivData!C21 -> 25705 | D21: =DivData!D21 | E21: =DivData!E21 -> 0 | F21: =DivData!F21 -> 0 | G21: =YEAR(B21) -> 2005 | H21: =IF(D21="Y",E21,) -> 0 | I21: =SUM($F$2:F21) -> 0 | J21: =H21*2^I21 -> 0 | L21: 2023 | M21: =SUMIF(G21:G272,L21,J21:J272) -> 3.18 | N21: =(M21-M20)/M20 -> 0.012738854
A22: =DivData!A22 -> UVV | B22: =DivData!B22 -> 38625 | C22: =DivData!C22 -> 25705 | D22: =DivData!D22 | E22: =DivData!E22 -> 0 | F22: =DivData!F22 -> 0 | G22: =YEAR(B22) -> 2005 | H22: =IF(D22="Y",E22,) -> 0 | I22: =SUM($F$2:F22) -> 0 | J22: =H22*2^I22 -> 0 | L22: 2024 | M22: =SUMIF(G22:G273,L22,J22:J273) -> 3.22 | N22: =(M22-M21)/M21 -> 0.012578616
A23: =DivData!A23 -> UVV | B23: =DivData!B23 -> 38656 | C23: =DivData!C23 -> 25705 | D23: =DivData!D23 -> Y | E23: =DivData!E23 -> 0.42 | F23: =DivData!F23 -> 0 | G23: =YEAR(B23) -> 2005 | H23: =IF(D23="Y",E23,) -> 0.42 | I23: =SUM($F$2:F23) -> 0 | J23: =H23*2^I23 -> 0.42
A24: =DivData!A24 -> UVV | B24: =DivData!B24 -> 38686 | C24: =DivData!C24 -> 25715 | D24: =DivData!D24 | E24: =DivData!E24 -> 0 | F24: =DivData!F24 -> 0 | G24: =YEAR(B24) -> 2005 | H24: =IF(D24="Y",E24,) -> 0 | I24: =SUM($F$2:F24) -> 0 | J24: =H24*2^I24 -> 0
A25: =DivData!A25 -> UVV | B25: =DivData!B25 -> 38716 | C25: =DivData!C25 -> 25715 | D25: =DivData!D25 | E25: =DivData!E25 -> 0 | F25: =DivData!F25 -> 0 | G25: =YEAR(B25) -> 2005 | H25: =IF(D25="Y",E25,) -> 0 | I25: =SUM($F$2:F25) -> 0 | J25: =H25*2^I25 -> 0
A26: =DivData!A26 -> UVV | B26: =DivData!B26 -> 38748 | C26: =DivData!C26 -> 25715 | D26: =DivData!D26 -> Y | E26: =DivData!E26 -> 0.43 | F26: =DivData!F26 -> 0 | G26: =YEAR(B26) -> 2006 | H26: =IF(D26="Y",E26,) -> 0.43 | I26: =SUM($F$2:F26) -> 0 | J26: =H26*2^I26 -> 0.43
A27: =DivData!A27 -> UVV | B27: =DivData!B27 -> 38776 | C27: =DivData!C27 -> 25723 | D27: =DivData!D27 | E27: =DivData!E27 -> 0 | F27: =DivData!F27 -> 0 | G27: =YEAR(B27) -> 2006 | H27: =IF(D27="Y",E27,) -> 0 | I27: =SUM($F$2:F27) -> 0 | J27: =H27*2^I27 -> 0
A28: =DivData!A28 -> UVV | B28: =DivData!B28 -> 38807 | C28: =DivData!C28 -> 25723 | D28: =DivData!D28 | E28: =DivData!E28 -> 0 | F28: =DivData!F28 -> 0 | G28: =YEAR(B28) -> 2006 | H28: =IF(D28="Y",E28,) -> 0 | I28: =SUM($F$2:F28) -> 0 | J28: =H28*2^I28 -> 0
A29: =DivData!A29 -> UVV | B29: =DivData!B29 -> 38835 | C29: =DivData!C29 -> 25723 | D29: =DivData!D29 -> Y | E29: =DivData!E29 -> 0.43 | F29: =DivData!F29 -> 0 | G29: =YEAR(B29) -> 2006 | H29: =IF(D29="Y",E29,) -> 0.43 | I29: =SUM($F$2:F29) -> 0 | J29: =H29*2^I29 -> 0.43
A30: =DivData!A30 -> UVV | B30: =DivData!B30 -> 38868 | C30: =DivData!C30 -> 25723 | D30: =DivData!D30 | E30: =DivData!E30 -> 0 | F30: =DivData!F30 -> 0 | G30: =YEAR(B30) -> 2006 | H30: =IF(D30="Y",E30,) -> 0 | I30: =SUM($F$2:F30) -> 0 | J30: =H30*2^I30 -> 0
A31: =DivData!A31 -> UVV | B31: =DivData!B31 -> 38898 | C31: =DivData!C31 -> 25748 | D31: =DivData!D31 | E31: =DivData!E31 -> 0 | F31: =DivData!F31 -> 0 | G31: =YEAR(B31) -> 2006 | H31: =IF(D31="Y",E31,) -> 0 | I31: =SUM($F$2:F31) -> 0 | J31: =H31*2^I31 -> 0
A32: =DivData!A32 -> UVV | B32: =DivData!B32 -> 38929 | C32: =DivData!C32 -> 25748 | D32: =DivData!D32 -> Y | E32: =DivData!E32 -> 0.43 | F32: =DivData!F32 -> 0 | G32: =YEAR(B32) -> 2006 | H32: =IF(D32="Y",E32,) -> 0.43 | I32: =SUM($F$2:F32) -> 0 | J32: =H32*2^I32 -> 0.43
A33: =DivData!A33 -> UVV | B33: =DivData!B33 -> 38960 | C33: =DivData!C33 -> 25748 | D33: =DivData!D33 | E33: =DivData!E33 -> 0 | F33: =DivData!F33 -> 0 | G33: =YEAR(B33) -> 2006 | H33: =IF(D33="Y",E33,) -> 0 | I33: =SUM($F$2:F33) -> 0 | J33: =H33*2^I33 -> 0
A34: =DivData!A34 -> UVV | B34: =DivData!B34 -> 38989 | C34: =DivData!C34 -> 25748 | D34: =DivData!D34 | E34: =DivData!E34 -> 0 | F34: =DivData!F34 -> 0 | G34: =YEAR(B34) -> 2006 | H34: =IF(D34="Y",E34,) -> 0 | I34: =SUM($F$2:F34) -> 0 | J34: =H34*2^I34 -> 0
... A253: =DivData!A253 -> UVV | B253: =DivData!B253 -> 45657 | C253: =DivData!C253 -> 24693 | D253: =DivData!D253 | E253: =DivData!E253 -> 0 | F253: =DivData!F253 -> 0 | G253: =YEAR(B253) -> 2024 | H253: =IF(D253="Y",E253,) -> 0 | I253: =SUM($F$2:F253) -> 0 | J253: =H253*2^I253 -> 0

Sheet RndGrth
B1: 1 | C1: 2 | D1: 3 | E1: 4 | F1: 5 | G1: 6 | H1: 7 | I1: 8 | J1: 9 | K1: 10 | L1: 11 | M1: 12 | N1: 13 | O1: 14 | P1: 15 | Q1: 16 | R1: 17 | S1: 18 | T1: 19 | U1: 20 | V1: 21 | W1: 22 | X1: 23 | Y1: 24 | Z1: 25 | AA1: 26 | AB1: 27 | AC1: 28 | AD1: 29 | AE1: 30 | AF1: 31 | AG1: 32 | AH1: 33 | AI1: 34 | AJ1: 35 | AK1: 36 | AL1: 37 | AM1: 38 | AN1: 39 | AO1: 40 | AP1: 41 | AQ1: 42 | AR1: 43 | AS1: 44 | AT1: 45 | AU1: 46 | AV1: 47 | AW1: 48 | AX1: 49 | AY1: 50 | AZ1: 51 | BA1: 52 | BB1: 53 | BC1: 54 | BD1: 55 | BE1: 56 | BF1: 57 | BG1: 58 | BH1: 59 | BI1: 60 | BJ1: 61 | BK1: 62 | BL1: 63 | BM1: 64 | BN1: 65 | BO1: 66 | BP1: 67 | BQ1: 68 | BR1: 69 | BS1: 70 | BT1: 71 | BU1: 72 | BV1: 73 | BW1: 74 | BX1: 75 | BY1: 76 | BZ1: 77 | CA1: 78 | CB1: 79 | CC1: 80 | CD1: 81 | CE1: 82 | CF1: 83 | CG1: 84 | CH1: 85 | CI1: 86 | CJ1: 87 | CK1: 88 | CL1: 89 | CM1: 90 | CN1: 91 | CO1: 92 | CP1: 93 | CQ1: 94 | CR1: 95 | CS1: 96 | CT1: 97 | CU1: 98 | CV1: 99 | CW1: 100 | CX1: 101 | CY1: 102 | CZ1: 103 | DA1: 104 | DB1: 105 | DC1: 106 | DD1: 107 | DE1: 108 | DF1: 109 | DG1: 110 | DH1: 111 | DI1: 112 | DJ1: 113 | DK1: 114 | DL1: 115 | DM1: 116 | DN1: 117 | DO1: 118 | DP1: 119 | DQ1: 120 | DR1: 121 | DS1: 122 | DT1: 123 | DU1: 124 | DV1: 125 | DW1: 126 | DX1: 127 | DY1: 128 | DZ1: 129 | EA1: 130 | EB1: 131 | EC1: 132 | ED1: 133 | EE1: 134 | EF1: 135 | EG1: 136 | EH1: 137 | EI1: 138 | EJ1: 139 | EK1: 140 | EL1: 141 | EM1: 142 | EN1: 143 | EO1: 144 | EP1: 145 | EQ1: 146 | ER1: 147 | ES1: 148 | ET1: 149 | EU1: 150 | EV1: 151 | EW1: 152 | EX1: 153 | EY1: 154 | EZ1: 155 | FA1: 156 | FB1: 157 | FC1: 158 | FD1: 159 | FE1: 160 | FF1: 161 | FG1: 162 | FH1: 163 | FI1: 164 | FJ1: 165 | FK1: 166 | FL1: 167 | FM1: 168 | FN1: 169 | FO1: 170 | FP1: 171 | FQ1: 172 | FR1: 173 | FS1: 174 | FT1: 175 | FU1: 176 | FV1: 177 | FW1: 178 | FX1: 179 | FY1: 180 | FZ1: 181 | GA1: 182 | GB1: 183 | GC1: 184 | GD1: 185 | GE1: 186 | GF1: 187 | GG1: 188 | GH1: 189 | GI1: 190 | GJ1: 191 | GK1: 192 | GL1: 193 | GM1: 194 | GN1: 195 | GO1: 196 | GP1: 197 | GQ1: 198 | GR1: 199 | GS1: 200 | GT1: 201 | GU1: 202 | GV1: 203 | GW1: 204 | GX1: 205 | GY1: 206 | GZ1: 207 | HA1: 208 | HB1: 209 | HC1: 210 | HD1: 211 | HE1: 212 | HF1: 213 | HG1: 214 | HH1: 215 | HI1: 216 | HJ1: 217 | HK1: 218 | HL1: 219 | HM1: 220 | HN1: 221 | HO1: 222 | HP1: 223 | HQ1: 224 | HR1: 225 | HS1: 226 | HT1: 227 | HU1: 228 | HV1: 229 | HW1: 230 | HX1: 231 | HY1: 232 | HZ1: 233 | IA1: 234 | IB1: 235 | IC1: 236 | ID1: 237 | IE1: 238 | IF1: 239 | IG1: 240 | IH1: 241 | II1: 242 | IJ1: 243 | IK1: 244 | IL1: 245 | IM1: 246 | IN1: 247 | IO1: 248 | IP1: 249 | IQ1: 250 | IR1: 251 | IS1: 252 | IT1: 253 | IU1: 254 | IV1: 255 | IW1: 256 | IX1: 257 | IY1: 258 | IZ1: 259 | JA1: 260 | JB1: 261 | JC1: 262 | JD1: 263 | JE1: 264 | JF1: 265 | JG1: 266 | JH1: 267 | JI1: 268 | JJ1: 269 | JK1: 270 | JL1: 271 | JM1: 272 | JN1: 273 | JO1: 274 | JP1: 275 | JQ1: 276 | JR1: 277 | JS1: 278 | JT1: 279 | JU1: 280 | JV1: 281 | JW1: 282 | JX1: 283 | JY1: 284 | JZ1: 285 | KA1: 286 | KB1: 287 | KC1: 288 | KD1: 289 | KE1: 290 | KF1: 291 | KG1: 292 | KH1: 293 | KI1: 294 | KJ1: 295 | KK1: 296 | KL1: 297 | KM1: 298 | KN1: 299 | KO1: 300 | KP1: 301 | KQ1: 302 | KR1: 303 | KS1: 304 | KT1: 305 | KU1: 306 | KV1: 307 | KW1: 308 | KX1: 309 | KY1: 310 | KZ1: 311 | LA1: 312 | LB1: 313 | LC1: 314 | LD1: 315 | LE1: 316 | LF1: 317 | LG1: 318 | LH1: 319 | LI1: 320 | LJ1: 321 | LK1: 322 | LL1: 323 | LM1: 324 | LN1: 325 | LO1: 326 | LP1: 327 | LQ1: 328 | LR1: 329 | LS1: 330 | LT1: 331 | LU1: 332 | LV1: 333 | LW1: 334 | LX1: 335 | LY1: 336 | LZ1: 337 | MA1: 338 | MB1: 339 | MC1: 340 | MD1: 341 | ME1: 342 | MF1: 343 | MG1: 344 | MH1: 345 | MI1: 346 | MJ1: 347 | MK1: 348 | ML1: 349 | MM1: 350 | MN1: 351 | MO1: 352 | MP1: 353 | MQ1: 354 | MR1: 355 | MS1: 356 | MT1: 357 | MU1: 358 | MV1: 359 | MW1: 360 | MX1: 361 | MY1: 362 | MZ1: 363 | NA1: 364 | NB1: 365 | NC1: 366 | ND1: 367 | NE1: 368 | NF1: 369 | NG1: 370 | NH1: 371 | NI1: 372 | NJ1: 373 | NK1: 374 | NL1: 375 | NM1: 376 | NN1: 377 | NO1: 378 | NP1: 379 | NQ1: 380 | NR1: 381 | NS1: 382 | NT1: 383 | NU1: 384 | NV1: 385 | NW1: 386 | NX1: 387 | NY1: 388 | NZ1: 389 | OA1: 390 | OB1: 391 | OC1: 392 | OD1: 393 | OE1: 394 | OF1: 395 | OG1: 396 | OH1: 397 | OI1: 398 | OJ1: 399 | OK1: 400 | OL1: 401 | OM1: 402 | ON1: 403 | OO1: 404 | OP1: 405 | OQ1: 406 | OR1: 407 | OS1: 408 | OT1: 409 | OU1: 410 | OV1: 411 | OW1: 412 | OX1: 413 | OY1: 414 | OZ1: 415 | PA1: 416 | PB1: 417 | PC1: 418 | PD1: 419 | PE1: 420 | PF1: 421 | PG1: 422 | PH1: 423 | PI1: 424 | PJ1: 425 | PK1: 426 | PL1: 427 | PM1: 428 | PN1: 429 | PO1: 430 | PP1: 431 | PQ1: 432 | PR1: 433 | PS1: 434 | PT1: 435 | PU1: 436 | PV1: 437 | PW1: 438 | PX1: 439 | PY1: 440 | PZ1: 441 | QA1: 442 | QB1: 443 | QC1: 444 | QD1: 445 | QE1: 446 | QF1: 447 | QG1: 448 | QH1: 449 | QI1: 450 | QJ1: 451 | QK1: 452 | QL1: 453 | QM1: 454 | QN1: 455 | QO1: 456 | QP1: 457 | QQ1: 458 | QR1: 459 | QS1: 460 | QT1: 461 | QU1: 462 | QV1: 463 | QW1: 464 | QX1: 465 | QY1: 466 | QZ1: 467 | RA1: 468 | RB1: 469 | RC1: 470 | RD1: 471 | RE1: 472 | RF1: 473 | RG1: 474 | RH1: 475 | RI1: 476 | RJ1: 477 | RK1: 478 | RL1: 479 | RM1: 480 | RN1: 481 | RO1: 482 | RP1: 483 | RQ1: 484 | RR1: 485 | RS1: 486 | RT1: 487 | RU1: 488 | RV1: 489 | RW1: 490 | RX1: 491 | RY1: 492 | RZ1: 493 | SA1: 494 | SB1: 495 | SC1: 496 | SD1: 497 | SE1: 498 | SF1: 499 | SG1: 500
A2: 1 | B2: 0.05132696 | C2: 0.074328536 | D2: 0.083943827 | E2: 0.058984631 | F2: 0.052273011 | G2: 0.036361883 | H2: 0.087267407 | I2: 0.11662664 | J2: 0.073894502 | K2: 0.054488616 | L2: 0.018788077 | M2: 0.03834205 | N2: 0.059382939 | O2: 0.09789954 | P2: 0.050790019 | Q2: 0.095572834 | R2: 0.067542485 | S2: 0.061157234 | T2: 0.10035385 | U2: 0.10663465 | V2: 0.06001362 | W2: 0.049502472 | X2: 0.038464038 | Y2: 0.081718825 | Z2: 0.066654736 | AA2: 0.036726184 | AB2: 0.08019412 | AC2: 0.070673113 | AD2: 0.019067806 | AE2: 0.020018498 | AF2: 0.075204596 | AG2: 0.096044799 | AH2: 0.022617084 | AI2: 0.11149617 | AJ2: 0.041849615 | AK2: 0.085484231 | AL2: 0.093299815 | AM2: 0.026318316 | AN2: 0.055181179 | AO2: 0.034200481 | AP2: 0.070319326 | AQ2: 0.049752063 | AR2: 0.046483145 | AS2: 0.063353273 | AT2: 0.058064766 | AU2: 0.032989714 | AV2: 0.09237594 | AW2: 0.11398268 | AX2: 0.043642589 | AY2: 0.046839425 | AZ2: 0.038279251 | BA2: 0.11064128 | BB2: 0.079686917 | BC2: 0.02362748 | BD2: 0.0023846432 | BE2: 0.068457307 | BF2: 0.081969733 | BG2: 0.057399621 | BH2: 0.066298971 | BI2: 0.06182387 | BJ2: 0.071745821 | BK2: 0.091913601 | BL2: 0.10457856 | BM2: 0.031586711 | BN2: 0.072962949 | BO2: 0.11087024 | BP2: 0.073768074 | BQ2: 0.066835798 | BR2: 0.075438344 | BS2: 0.040732816 | BT2: 0.065889519 | BU2: 0.089851898 | BV2: 0.058681323 | BW2: 0.077301537 | BX2: 0.078717604 | BY2: 0.097869688 | BZ2: 0.069377143 | CA2: 0.061466559 | CB2: 0.07736021 | CC2: 0.0043524914 | CD2: 0.076690166 | CE2: 0.060242784 | CF2: 0.06028742 | CG2: 0.111889 | CH2: 0.065976784 | CI2: 0.091341765 | CJ2: 0.013567412 | CK2: 0.1076667 | CL2: 0.022889594 | CM2: 0.041510954 | CN2: 0.07058857 | CO2: 0.01332378 | CP2: 0.077459623 | CQ2: 0.070429739 | CR2: 0.053710793 | CS2: 0.049080414 | CT2: 0.034200481 | CU2: 0.091715235 | CV2: 0.086373097 | CW2: 0.010567509 | CX2: 0.10376183 | CY2: 0.033397046 | CZ2: 0.075614335 | DA2: 0.053675612 | DB2: 0.086995069 | DC2: 0.078654719 | DD2: 0.054380065 | DE2: 0.11292656 | DF2: 0.063143132 | DG2: 0.073436403 | DH2: 0.024000147 | DI2: 0.064925735 | DJ2: 0.074894556 | DK2: 0.052579269 | DL2: 0.042642277 | DM2: 0.010481791 | DN2: 0.10408912 | DO2: 0.075118305 | DP2: 0.068618974 | DQ2: 0.018306314 | DR2: 0.046552763 | DS2: 0.042121609 | DT2: 0.031822493 | DU2: 0.016281282 | DV2: 0.042146247 | DW2: 0.081167645 | DX2: 0.072836291 | DY2: 0.059191735 | DZ2: 0.082010472 | EA2: 0.017531528 | EB2: 0.088199476 | EC2: 0.10440139 | ED2: 0.072975411 | EE2: 0.037671604 | EF2: 0.042189908 | EG2: 0.076756975 | EH2: 0.084281084 | EI2: 0.071332443 | EJ2: 0.067848027 | EK2: 0.073854422 | EL2: 0.059008095 | EM2: 0.13272605 | EN2: 0.040915769 | EO2: 0.10999908 | EP2: 0.02785746 | EQ2: 0.053355946 | ER2: 0.053642437 | ES2: 0.067137988 | ET2: 0.087545704 | EU2: 0.033009482 | EV2: 0.029940535 | EW2: 0.089394258 | EX2: 0.063370605 | EY2: 0.048733989 | EZ2: 0.07724974 | FA2: 0.075284584 | FB2: 0.083849285 | FC2: 0.061607569 | FD2: 0.071097234 | FE2: 0.059599269 | FF2: 0.039181182 | FG2: 0.11510366 | FH2: 0.05772579 | FI2: 0.063800542 | FJ2: 0.067601187 | FK2: 0.045487475 | FL2: 0.063310843 | FM2: 0.095963894 | FN2: 0.070556368 | FO2: 0.087564154 | FP2: 0.051087311 | FQ2: 0.054609229 | FR2: 0.06259559 | FS2: 0.06151678 | FT2: 0.056816039 | FU2: 0.074765893 | FV2: 0.034434659 | FW2: 0.028335556 | FX2: 0.053557464 | FY2: 0.061205565 | FZ2: 0.090356351 | GA2: 0.059421931 | GB2: 0.1174577 | GC2: 0.053258109 | GD2: 0.043133151 | GE2: 0.059986404 | GF2: 0.072900637 | GG2: 0.067820581 | GH2: 0.11055098 | GI2: 0.0671263 | GJ2: 0.029899051 | GK2: 0.031454982 | GL2: 0.0398942 | GM2: 0.055565564 | GN2: 0.082043591 | GO2: 0.047500245 | GP2: 0.046314632 | GQ2: 0.11258025 | GR2: 0.01845632 | GS2: 0.088990649 | GT2: 0.087261334 | GU2: 0.10199762 | GV2: 0.026980569 | GW2: 0.092485494 | GX2: 0.065666629 | GY2: 0.078304885 | GZ2: 0.015179094 | HA2: 0.095950371 | HB2: 0.0512256 | HC2: 0.049587302 | HD2: 0.041708518 | HE2: 0.0014192836 | HF2: 0.061143683 | HG2: 0.06859531 | HH2: 0.078166682 | HI2: 0.055294658 | HJ2: 0.027738509 | HK2: 0.091180528 | HL2: 0.074500946 | HM2: 0.075924318 | HN2: 0.12303395 | HO2: 0.062593671 | HP2: 0.09672848 | HQ2: 0.033880414 | HR2: 0.10114353 | HS2: 0.025517861 | HT2: 0.074599069 | HU2: 0.041382233 | HV2: 0.015226537 | HW2: 0.070455839 | HX2: 0.049428672 | HY2: 0.052860947 | HZ2: 0.048499239 | IA2: 0.075405827 | IB2: 0.091580355 | IC2: 0.05653098 | ID2: 0.044678654 | IE2: 0.02142299 | IF2: 0.059256139 | IG2: 0.084735888 | IH2: 0.058910344 | II2: 0.094155105 | IJ2: 0.057767217 | IK2: 0.089761023 | IL2: 0.092706264 | IM2: 0.035130087 | IN2: 0.085228853 | IO2: 0.076388577 | IP2: 0.027597899 | IQ2: 0.090133461 | IR2: 0.024757973 | IS2: 0.059916414 | IT2: 0.095489407 | IU2: 0.055736943 | IV2: 0.10429906 | IW2: 0.032030657 | IX2: 0.090494554 | IY2: 0.014322601 | IZ2: 0.057445144 | JA2: 0.074188442 | JB2: 0.0071688108 | JC2: 0.02570557 | JD2: 0.082497965 | JE2: 0.030323573 | JF2: 0.027836832 | JG2: 0.11352108 | JH2: 0.045985024 | JI2: 0.064912184 | JJ2: 0.15748803 | JK2: 0.056441108 | JL2: 0.013419124 | JM2: 0.059464818 | JN2: 0.065337565 | JO2: 0.10142739 | JP2: 0.02405183 | JQ2: 0.02965284 | JR2: 0.030565829 | JS2: 0.051741112 | JT2: 0.081711233 | JU2: 0.11453824 | JV2: 0.061145632 | JW2: 0.0955816 | JX2: 0.071901185 | JY2: 0.072674739 | JZ2: 0.064441021 | KA2: 0.01193831 | KB2: 0.034234058 | KC2: 0.068095326 | KD2: 0.073591509 | KE2: 0.056827986 | KF2: 0.084390724 | KG2: 0.06180648 | KH2: 0.03077428 | KI2: 0.096826804 | KJ2: 0.018860845 | KK2: 0.078640767 | KL2: 0.071507317 | KM2: 0.091406569 | KN2: 0.049005926 | KO2: 0.048781719 | KP2: 0.023844296 | KQ2: 0.054833637 | KR2: 0.043252045 | KS2: 0.083047913 | KT2: 0.10871996 | KU2: 0.072946303 | KV2: 0.077930499 | KW2: 0.042717481 | KX2: 0.096588902 | KY2: 0.023461201 | KZ2: 0.038410922 | LA2: 0.08317437 | LB2: 0.082998006 | LC2: 0.071631568 | LD2: 0.078834263 | LE2: 0.063411086 | LF2: 0.060347583 | LG2: 0.088095652 | LH2: 0.055565564 | LI2: 0.10496945 | LJ2: 0.051106764 | LK2: 0.062464463 | LL2: 0.041775012 | LM2: 0.085607021 | LN2: 0.10775849 | LO2: 0.054148093 | LP2: 0.072998273 | LQ2: 0.081522407 | LR2: 0.069944911 | LS2: 0.067857825 | LT2: 0.069498386 | LU2: 0.028380707 | LV2: 0.057108231 | LW2: 0.045368811 | LX2: 0.061089537 | LY2: 0.077085638 | LZ2: 0.053416281 | MA2: 0.057662591 | MB2: 0.064103363 | MC2: 0.030712455 | MD2: 0.092069108 | ME2: 0.093319526 | MF2: 0.068412013 | MG2: 0.069387056 | MH2: 0.089078659 | MI2: 0.088268922 | MJ2: 0.044754345 | MK2: 0.072229303 | ML2: 0.02970418 | MM2: 0.099997455 | MN2: 0.075675301 | MO2: 0.066954663 | MP2: 0.029806514 | MQ2: 0.07989044 | MR2: 0.062389231 | MS2: 0.047884659 | MT2: 0.023273033 | MU2: 0.050119631 | MV2: 0.043814054 | MW2: 0.07190935 | MX2: 0.11041644 | MY2: 0.060727527 | MZ2: 0.051781679 | NA2: 0.080295882 | NB2: 0.085546972 | NC2: 0.099209491 | ND2: 0.047798769 | NE2: 0.13128489 | NF2: 0.069089478 | NG2: 0.080705822 | NH2: 0.029568498 | NI2: 0.024856411 | NJ2: 0.053109965 | NK2: 0.0074841799 | NL2: 0.072832166 | NM2: 0.083973565 | NN2: 0.080981684 | NO2: 0.061632695 | NP2: 0.065817781 | NQ2: 0.028445683 | NR2: 0.069434785 | NS2: 0.018390886 | NT2: 0.023266272 | NU2: 0.071927771 | NV2: 0.06552917 | NW2: 0.083084756 | NX2: 0.028415716 | NY2: 0.090212074 | NZ2: 0.071022346 | OA2: 0.047963386 | OB2: 0.055897922 | OC2: 0.074462585 | OD2: 0.10809369 | OE2: 0.023367461 | OF2: 0.035905446 | OG2: 0.064303992 | OH2: 0.088341748 | OI2: 0.13543603 | OJ2: 0.036739592 | OK2: 0.052416829 | OL2: 0.093037905 | OM2: 0.054851972 | ON2: 0.071670331 | OO2: 0.085475636 | OP2: 0.059832816 | OQ2: 0.050816147 | OR2: 0.0097371438 | OS2: 0.07427118 | OT2: 0.095798531 | OU2: 0.072243685 | OV2: 0.069518269 | OW2: 0.047691736 | OX2: 0.098760388 | OY2: 0.067799037 | OZ2: 0.064327141 | PA2: 0.051475363 | PB2: 0.061673233 | PC2: 0.055020801 | PD2: 0.10113757 | PE2: 0.11646346 | PF2: 0.074723062 | PG2: 0.061041177 | PH2: 0.085865837 | PI2: 0.033697518 | PJ2: 0.031943507 | PK2: 0.020026978 | PL2: 0.045843555 | PM2: 0.011003433 | PN2: 0.087115796 | PO2: 0.076097645 | PP2: 0.07274513 | PQ2: 0.0511781 | PR2: 0.075347326 | PS2: 0.030971844 | PT2: 0.089127707 | PU2: 0.060343686 | PV2: 0.0295167 | PW2: 0.04997163 | PX2: 0.05490695 | PY2: 0.057883561 | PZ2: 0.10196611 | QA2: 0.069256015 | QB2: 0.092188346 | QC2: 0.017748803 | QD2: 0.083620895 | QE2: 0.069117239 | QF2: 0.036112464 | QG2: 0.073772285 | QH2: 0.01049898 | QI2: 0.058984631 | QJ2: 0.06417086 | QK2: 0.060801155 | QL2: 0.011280069 | QM2: 0.078736226 | QN2: 0.042942004 | QO2: 0.034681098 | QP2: 0.042709431 | QQ2: 0.046844181 | QR2: 0.055446412 | QS2: 0.049953925 | QT2: 0.095004722 | QU2: 0.096298916 | QV2: 0.053888532 | QW2: 0.059626514 | QX2: 0.080325018 | QY2: 0.10451186 | QZ2: 0.1174577 | RA2: 0.064060905 | RB2: 0.10940662 | RC2: 0.037748728 | RD2: 0.05857747 | RE2: 0.035633508 | RF2: 0.085521303 | RG2: 0.080666601 | RH2: 0.054870308 | RI2: 0.071552096 | RJ2: 0.077848219 | RK2: 0.085880276 | RL2: 0.014054217 | RM2: 0.070498067 | RN2: 0.066619726 | RO2: 0.021184974 | RP2: 0.087976587 | RQ2: 0.064412057 | RR2: 0.044875072 | RS2: 0.067953972 | RT2: 0.050165928 | RU2: 0.080315306 | RV2: 0.05346613 | RW2: 0.07611303 | RX2: 0.085062688 | RY2: 0.085152704 | RZ2: 0.10368459 | SA2: 0.039416964 | SB2: 0.093620972 | SC2: 0.033812 | SD2: 0.032529896 | SE2: 0.027002227 | SF2: 0.085744766 | SG2: 0.097598496
A3: 2 | B3: 0.066147504 | C3: 0.077525286 | D3: 0.10092935 | E3: 0.088208931 | F3: 0.0802183 | G3: 0.076084467 | H3: 0.07076989 | I3: 0.07672357 | J3: 0.13629779 | K3: 0.070572469 | L3: 0.050060041 | M3: 0.017391262 | N3: 0.080524674 | O3: 0.060147669 | P3: 0.059379043 | Q3: 0.082927243 | R3: 0.075012762 | S3: 0.038039229 | T3: 0.089757643 | U3: 0.10462314 | V3: 0.095301928 | W3: 0.063636669 | X3: 0.051954461 | Y3: 0.056853856 | Z3: 0.073574721 | AA3: 0.076315665 | AB3: 0.093402379 | AC3: 0.073860754 | AD3: 0.027355642 | AE3: 0.083808833 | AF3: 0.07255278 | AG3: 0.11998661 | AH3: 0.028400761 | AI3: 0.061105007 | AJ3: 0.07403176 | AK3: 0.059279545 | AL3: 0.046951128 | AM3: 0.036235769 | AN3: 0.075083812 | AO3: 0.051251499 | AP3: 0.076457163 | AQ3: 0.011312385 | AR3: 0.034692042 | AS3: 0.075721082 | AT3: 0.067712804 | AU3: 0.018659958 | AV3: 0.056453084 | AW3: 0.049206527 | AX3: 0.063447729 | AY3: 0.050165928 | AZ3: 0.073560024 | BA3: 0.069032037 | BB3: 0.063372525 | BC3: 0.1375501 | BD3: 0.047761582 | BE3: 0.052728674 | BF3: 0.063326285 | BG3: 0.052873524 | BH3: 0.014976259 | BI3: 0.049172779 | BJ3: 0.045531881 | BK3: 0.067889225 | BL3: 0.050855282 | BM3: 0.06156895 | BN3: 0.070397595 | BO3: 0.066892294 | BP3: 0.059244421 | BQ3: 0.080488089 | BR3: 0.03460048 | BS3: 0.11584968 | BT3: 0.037658712 | BU3: 0.10142131 | BV3: 0.075096761 | BW3: 0.077575193 | BX3: 0.076561302 | BY3: 0.046471141 | BZ3: 0.045277076 | CA3: 0.053977201 | CB3: 0.050282587 | CC3: 0.061902999 | CD3: 0.07151342 | CE3: 0.06193775 | CF3: 0.06600973 | CG3: 0.060033044 | CH3: 0.029554402 | CI3: 0.071786675 | CJ3: 0.062875177 | CK3: 0.049341293 | CL3: 0.077750182 | CM3: 0.070481967 | CN3: 0.013446398 | CO3: 0.033846264 | CP3: 0.061843179 | CQ3: 0.020283903 | CR3: 0.040614954 | CS3: 0.064311699 | CT3: 0.10426995 | CU3: 0.083717385 | CV3: 0.029063873 | CW3: 0.064001114 | CX3: 0.058493128 | CY3: 0.046564738 | CZ3: 0.038792757 | DA3: 0.058655854 | DB3: 0.068099251 | DC3: 0.020528451 | DD3: 0.045726065 | DE3: 0.050137279 | DF3: 0.04785217 | DG3: 0.032678986 | DH3: 0.050187959 | DI3: 0.042116166 | DJ3: 0.081217408 | DK3: 0.086535366 | DL3: 0.05452543 | DM3: 0.042467002 | DN3: 0.09199124 | DO3: 0.016226734 | DP3: 0.0564171 | DQ3: 0.05225393 | DR3: 0.052448515 | DS3: 0.075475215 | DT3: 0.070447817 | DU3: 0.041527714 | DV3: 0.10319481 | DW3: 0.12023322 | DX3: 0.038476529 | DY3: 0.074222391 | DZ3: 0.075599094 | EA3: 0.071432028 | EB3: 0.062508812 | EC3: 0.053378865 | ED3: 0.063420713 | EE3: 0.038004277 | EF3: 0.054957802 | EG3: 0.026861045 | EH3: 0.084802612 | EI3: 0.00035353776 | EJ3: 0.0047288257 | EK3: 0.051486135 | EL3: 0.06102181 | EM3: 0.038891138 | EN3: 0.023096211 | EO3: 0.07709237 | EP3: 0.056275087 | EQ3: 0.033338831 | ER3: 0.0048700084 | ES3: 0.059632358 | ET3: 0.052913346 | EU3: 0.1097103 | EV3: 0.09415098 | EW3: 0.10283211 | EX3: 0.038121567 | EY3: 0.05596625 | EZ3: 0.06736062 | FA3: 0.059725783 | FB3: 0.026735218 | FC3: 0.053158009 | FD3: 0.074821615 | FE3: 0.093577081 | FF3: 0.042984577 | FG3: 0.040243776 | FH3: 0.066050469 | FI3: 0.084409948 | FJ3: 0.12509852 | FK3: 0.021184974 | FL3: 0.10742181 | FM3: 0.06686502 | FN3: 0.067122403 | FO3: 0.046490365 | FP3: 0.049017214 | FQ3: 0.076497014 | FR3: 0.095314935 | FS3: 0.065625976 | FT3: 0.08096438 | FU3: 0.073837576 | FV3: 0.08310842 | FW3: 0.085271254 | FX3: 0.05671846 | FY3: 0.073421735 | FZ3: 0.047617133 | GA3: 0.055120328 | GB3: 0.059297135 | GC3: 0.0028361527 | GD3: 0.082853959 | GE3: 0.041694623 | GF3: 0.075219723 | GG3: 0.077652374 | GH3: 0.068755172 | GI3: 0.042973919 | GJ3: 0.075718904 | GK3: 0.065207957 | GL3: 0.074680289 | GM3: 0.044020728 | GN3: 0.041125939 | GO3: 0.050926962 | GP3: 0.085113283 | GQ3: 0.058863388 | GR3: 0.073044054 | GS3: 0.10987004 | GT3: 0.087179397 | GU3: 0.030610407 | GV3: 0.056261077 | GW3: 0.079368282 | GX3: 0.10028544 | GY3: 0.056808103 | GZ3: 0.036194744 | HA3: 0.034906681 | HB3: 0.12541847 | HC3: 0.13205681 | HD3: 0.061958979 | HE3: 0.04583622 | HF3: 0.076940014 | HG3: 0.052770702 | HH3: 0.01332378 | HI3: 0.086651051 | HJ3: 0.067808835 | HK3: 0.046593502 | HL3: 0.084385252 | HM3: 0.081011364 | HN3: 0.062117237 | HO3: 0.088086198 | HP3: 0.07603393 | HQ3: 0.055250109 | HR3: 0.012693271 | HS3: 0.040371895 | HT3: 0.056269071 | HU3: 0.045366347 | HV3: 0.036235769 | HW3: 0.11342253 | HX3: 0.076267133 | HY3: 0.084542077 | HZ3: 0.054688873 | IA3: 0.063600027 | IB3: 0.074511603 | IC3: 0.072190254 | ID3: 0.041772233 | IE3: 0.028184346 | IF3: 0.060795339 | IG3: 0.068544028 | IH3: 0.088997181 | II3: 0.059162427 | IJ3: 0.04520001 | IK3: 0.063983753 | IL3: 0.12626465 | IM3: 0.031976739 | IN3: 0.038498359 | IO3: 0.029169702 | IP3: 0.075146324 | IQ3: 0.053952477 | IR3: 0.082598924 | IS3: 0.044711486 | IT3: 0.0194556 | IU3: 0.071911384 | IV3: 0.07755024 | IW3: 0.069283805 | IX3: 0.11210261 | IY3: 0.036304012 | IZ3: 0.036605343 | JA3: 0.087992229 | JB3: 0.06146461 | JC3: 0.063559546 | JD3: 0.092898442 | JE3: 0.10758465 | JF3: 0.077848219 | JG3: 0.031197599 | JH3: 0.063962553 | JI3: 0.0638642 | JJ3: 0.071182322 | JK3: 0.026436121 | JL3: 0.063829478 | JM3: 0.095811824 | JN3: 0.10705796 | JO3: 0.06574994 | JP3: 0.075198121 | JQ3: 0.074258431 | JR3: 0.07976341 | JS3: 0.027686597 | JT3: 0.096280638 | JU3: 0.09661205 | JV3: 0.020275766 | JW3: 0.10560706 | JX3: 0.064321354 | JY3: 0.075976918 | JZ3: 0.086692707 | KA3: 0.038795852 | KB3: 0.050598128 | KC3: 0.081946871 | KD3: 0.016753075 | KE3: 0.088792914 | KF3: 0.062007224 | KG3: 0.047821974 | KH3: 0.066720915 | KI3: 0.13246936 | KJ3: 0.064082134 | KK3: 0.080605349 | KL3: 0.042685251 | KM3: 0.038616508 | KN3: 0.05137002 | KO3: 0.054754164 | KP3: 0.05759346 | KQ3: 0.0067736827 | KR3: 0.070066899 | KS3: 0.054894745 | KT3: 0.078136801 | KU3: 0.055322992 | KV3: 0.090532715 | KW3: 0.0876968 | KX3: 0.090075533 | KY3: 0.085467099 | KZ3: 0.087127886 | LA3: 0.083800753 | LB3: 0.055014728 | LC3: 0.037451637 | LD3: 0.10283211 | LE3: 0.070642917 | LF3: 0.074639665 | LG3: 0.037402819 | LH3: 0.067067769 | LI3: 0.09453992 | LJ3: 0.062159694 | LK3: 0.075386317 | LL3: 0.060533744 | LM3: 0.070275178 | LN3: 0.058732233 | LO3: 0.068660401 | LP3: 0.059570047 | LQ3: 0.095380197 | LR3: 0.10188451 | LS3: 0.071558198 | LT3: 0.065593058 | LU3: 0.035542175 | LV3: 0.020275766 | LW3: 0.076576859 | LX3: 0.070044896 | LY3: 0.075105356 | LZ3: 0.051041845 | MA3: 0.074443419 | MB3: 0.088974377 | MC3: 0.016061486 | MD3: 0.063833317 | ME3: 0.0099186644 | MF3: 0.020324928 | MG3: 0.073837576 | MH3: 0.038426565 | MI3: 0.077875636 | MJ3: 0.0051198284 | MK3: 0.055067557 | ML3: 0.077713769 | MM3: 0.061435618 | MN3: 0.029615367 | MO3: 0.053834844 | MP3: 0.056297089 | MQ3: 0.077716032 | MR3: 0.038851202 | MS3: 0.087576473 | MT3: 0.057749455 | MU3: 0.067214138 | MV3: 0.019993516 | MW3: 0.064112989 | MX3: 0.083943827 | MY3: 0.029398608 | MZ3: 0.072319805 | NA3: 0.072319805 | NB3: 0.048960718 | NC3: 0.030409176 | ND3: 0.094510698 | NE3: 0.10086438 | NF3: 0.075668769 | NG3: 0.084972902 | NH3: 0.07997696 | NI3: 0.040912961 | NJ3: 0.038557491 | NK3: 0.067382136 | NL3: 0.041455059 | NM3: 0.088583947 | NN3: 0.075793106 | NO3: 0.026564126 | NP3: 0.077348923 | NQ3: 0.045994736 | NR3: 0.054010176 | NS3: 0.037838456 | NT3: 0.021544348 | NU3: 0.10684046 | NV3: 0.069924943 | NW3: 0.072935933 | NX3: 0.078698953 | NY3: 0.086473312 | NZ3: 0.032371638 | OA3: 0.055302766 | OB3: 0.043984659 | OC3: 0.034637151 | OD3: 0.059819179 | OE3: 0.083779209 | OF3: 0.035383173 | OG3: 0.070804154 | OH3: 0.040461853 | OI3: 0.050506308 | OJ3: 0.055531242 | OK3: 0.071393409 | OL3: 0.068646592 | OM3: 0.08593236 | ON3: 0.076430605 | OO3: 0.036338104 | OP3: 0.067036571 | OQ3: 0.062136517 | OR3: 0.060093265 | OS3: 0.024559263 | OT3: 0.0092324616 | OU3: 0.049215523 | OV3: 0.025879642 | OW3: 0.058479376 | OX3: 0.048649818 | OY3: 0.056672622 | OZ3: 0.033005528 | PA3: 0.097010846 | PB3: 0.080288605 | PC3: 0.089232677 | PD3: 0.050181341 | PE3: 0.054594933 | PF3: 0.056841909 | PG3: 0.071613204 | PH3: 0.058139541 | PI3: 0.074650351 | PJ3: 0.052915438 | PK3: 0.07246815 | PL3: 0.066678085 | PM3: 0.07706544 | PN3: 0.024825699 | PO3: 0.069713426 | PP3: 0.06421137 | PQ3: 0.074776607 | PR3: 0.064547194 | PS3: 0.056604809 | PT3: 0.092177172 | PU3: 0.072106083 | PV3: 0.078038105 | PW3: 0.10487078 | PX3: 0.064413976 | PY3: 0.060605482 | PZ3: 0.11314475 | QA3: 0.031163048 | QB3: 0.035083389 | QC3: -0.007934069 | QD3: 0.060557007 | QE3: 0.065738309 | QF3: 0.063343618 | QG3: 0.086662969 | QH3: 0.045339073 | QI3: 0.052522372 | QJ3: 0.025582608 | QK3: 0.038301254 | QL3: 0.059848372 | QM3: 0.028535297 | QN3: 0.069966913 | QO3: 0.062859735 | QP3: 0.077105835 | QQ3: 0.042200852 | QR3: 0.06124619 | QS3: 0.060634532 | QT3: 0.065480754 | QU3: 0.057134044 | QV3: 0.048320612 | QW3: 0.056668639 | QX3: 0.08413377 | QY3: 0.095051821 | QZ3: 0.061416308 | RA3: 0.051522634 | RB3: 0.10529261 | RC3: 0.050504102 | RD3: 0.071870473 | RE3: 0.067999123 | RF3: 0.041267035 | RG3: 0.095354069 | RH3: 0.11783586 | RI3: 0.11379313 | RJ3: 0.03552808 | RK3: 0.028816173 | RL3: 0.10542543 | RM3: 0.077877899 | RN3: 0.047003298 | RO3: 0.083386201 | RP3: 0.045554056 | RQ3: 0.085279734 | RR3: 0.076073465 | RS3: 0.073216951 | RT3: 0.04854035 | RU3: 0.052328045 | RV3: 0.067079487 | RW3: 0.075453528 | RX3: 0.061700278 | RY3: 0.051664103 | RZ3: 0.062553161 | SA3: 0.049716481 | SB3: 0.039531044 | SC3: 0.063997247 | SD3: 0.06280384 | SE3: 0.051616947 | SF3: 0.078077096 | SG3: 0.080080555
A4: 3 | B4: 0.087985926 | C4: 0.02087224 | D4: 0.067253186 | E4: 0.054271341 | F4: 0.025081822 | G4: 0.078351068 | H4: 0.079546307 | I4: 0.046832263 | J4: 0.088883502 | K4: 0.076022986 | L4: 0.079610596 | M4: 0.013186493 | N4: 0.083171734 | O4: 0.065798415 | P4: 0.026463968 | Q4: 0.086103739 | R4: 0.091678736 | S4: 0.057678405 | T4: 0.061711852 | U4: 0.053022184 | V4: 0.075623045 | W4: 0.11043867 | X4: 0.042580395 | Y4: 0.073654509 | Z4: 0.030346148 | AA4: 0.0069148654 | AB4: 0.045831321 | AC4: 0.037160734 | AD4: 0.061572789 | AE4: 0.052612989 | AF4: 0.094114137 | AG4: 0.05551305 | AH4: 0.045625392 | AI4: 0.08621759 | AJ4: 0.069922966 | AK4: 0.039444008 | AL4: 0.082536756 | AM4: 0.048865632 | AN4: 0.066265939 | AO4: 0.073333897 | AP4: 0.05678421 | AQ4: 0.040120929 | AR4: 0.074742343 | AS4: 0.067483783 | AT4: 0.067626627 | AU4: 0.068559785 | AV4: 0.088054856 | AW4: 0.069727378 | AX4: 0.11529824 | AY4: 0.068907356 | AZ4: 0.080823799 | BA4: 0.028415716 | BB4: 0.07403176 | BC4: 0.06833128 | BD4: 0.051516159 | BE4: 0.079198106 | BF4: 0.085110475 | BG4: 0.059850321 | BH4: 0.024764161 | BI4: 0.089055798 | BJ4: 0.055654319 | BK4: 0.046863204 | BL4: 0.047645095 | BM4: 0.068542051 | BN4: 0.051175951 | BO4: 0.058941629 | BP4: 0.068794708 | BQ4: 0.081944293 | BR4: 0.049705365 | BS4: 0.10084673 | BT4: 0.068417915 | BU4: 0.094274285 | BV4: 0.094093681 | BW4: 0.064026182 | BX4: 0.029755404 | BY4: 0.06894099 | BZ4: 0.036625569 | CA4: 0.067302004 | CB4: 0.089140828 | CC4: 0.062047763 | CD4: 0.050933437 | CE4: 0.06754641 | CF4: 0.043692037 | CG4: 0.064456463 | CH4: 0.089108111 | CI4: 0.076839485 | CJ4: 0.064047411 | CK4: 0.078244951 | CL4: 0.054028741 | CM4: 0.072805207 | CN4: 0.078747915 | CO4: 0.066027206 | CP4: 0.072431021 | CQ4: 0.024301192 | CR4: 0.040464775 | CS4: 0.071798936 | CT4: 0.062433608 | CU4: 0.08931828 | CV4: 0.09188415 | CW4: 0.051803051 | CX4: 0.054398486 | CY4: 0.075200299 | CZ4: 0.021947154 | DA4: 0.068826307 | DB4: 0.075788751 | DC4: 0.086399569 | DD4: 0.090208694 | DE4: 0.079118004 | DF4: 0.087249186 | DG4: 0.083121598 | DH4: 0.059684929 | DI4: 0.075256451 | DJ4: 0.059275649 | DK4: 0.094261909 | DL4: 0.062412379 | DM4: 0.012878917 | DN4: 0.054839739 | DO4: 0.040798709 | DP4: 0.063603895 | DQ4: 0.076545774 | DR4: 0.081150255 | DS4: 0.08646741 | DT4: 0.093150897 | DU4: 0.068933083 | DV4: 0.060822441 | DW4: 0.055310845 | DX4: 0.12339562 | DY4: 0.077060942 | DZ4: 0.061089537 | EA4: 0.041089096 | EB4: 0.053551247 | EC4: 0.057433283 | ED4: 0.063640508 | EE4: 0.042599247 | EF4: 0.04146904 | EG4: 0.048437471 | EH4: 0.060620981 | EI4: 0.056042542 | EJ4: 0.055081767 | EK4: 0.023320247 | EL4: 0.077827706 | EM4: 0.042485911 | EN4: 0.14057911 | EO4: 0.052904952 | EP4: 0.04253725 | EQ4: 0.046605477 | ER4: 0.077857387 | ES4: 0.054868274 | ET4: 0.03703548 | EU4: 0.064624404 | EV4: 0.02304132 | EW4: 0.07311688 | EX4: 0.051098112 | EY4: 0.052082093 | EZ4: 0.075183023 | FA4: 0.079231167 | FB4: 0.087079526 | FC4: 0.062765279 | FD4: 0.0278986 | FE4: 0.09494072 | FF4: 0.045757923 | FG4: 0.078559461 | FH4: 0.059793911 | FI4: -0.0035079003 | FJ4: 0.017421516 | FK4: 0.087267407 | FL4: 0.048747626 | FM4: 0.056881731 | FN4: 0.034874079 | FO4: 0.073131491 | FP4: 0.06764035 | FQ4: 0.003746506 | FR4: 0.075806227 | FS4: 0.059441441 | FT4: 0.097790445 | FU4: 0.062815415 | FV4: 0.080148167 | FW4: 0.064095628 | FX4: 0.069865037 | FY4: 0.079909635 | FZ4: 0.093473658 | GA4: 0.091223387 | GB4: 0.10397452 | GC4: 0.061257793 | GD4: 0.069351302 | GE4: 0.075603449 | GF4: 0.087073453 | GG4: 0.036876306 | GH4: 0.063796703 | GI4: 0.053685926 | GJ4: 0.091584022 | GK4: 0.040858729 | GL4: 0.030009464 | GM4: 0.095245604 | GN4: 0.032662885 | GO4: 0.062961926 | GP4: 0.017709611 | GQ4: 0.065465283 | GR4: 0.070862713 | GS4: 0.049860872 | GT4: 0.099145317 | GU4: 0.043096079 | GV4: 0.096845598 | GW4: 0.060467852 | GX4: 0.057235204 | GY4: 0.081209902 | GZ4: 0.071411687 | HA4: 0.028903953 | HB4: 0.062007224 | HC4: 0.074866652 | HD4: 0.054275467 | HE4: 0.079460761 | HF4: 0.023259511 | HG4: 0.016160727 | HH4: 0.14079547 | HI4: 0.10409622 | HJ4: 0.060865042 | HK4: 0.067875473 | HL4: 0.066166928 | HM4: 0.056028504 | HN4: 0.023109848 | HO4: 0.06676959 | HP4: 0.085325057 | HQ4: 0.062080566 | HR4: 0.067587492 | HS4: 0.048978796 | HT4: 0.087873622 | HU4: 0.074931055 | HV4: 0.055504971 | HW4: 0.10809369 | HX4: 0.065503988 | HY4: 0.043839981 | HZ4: 0.052554001 | IA4: 0.086089185 | IB4: 0.055793324 | IC4: 0.074260552 | ID4: 0.050319945 | IE4: 0.03077428 | IF4: 0.06978121 | IG4: 0.11131602 | IH4: 0.030323573 | II4: 0.097588755 | IJ4: 0.079632025 | IK4: 0.05346613 | IL4: 0.099403159 | IM4: 0.062047763 | IN4: 0.023961414 | IO4: 0.083663754 | IP4: 0.023034444 | IQ4: 0.085750495 | IR4: 0.069430774 | IS4: 0.058767471 | IT4: 0.084300279 | IU4: 0.054131648 | IV4: 0.055660364 | IW4: 0.068601212 | IX4: 0.063526771 | IY4: 0.072054801 | IZ4: 0.07178464 | JA4: 0.080395523 | JB4: 0.077871081 | JC4: 0.057185641 | JD4: 0.056722442 | JE4: 0.051839349 | JF4: 0.037154202 | JG4: 0.055407965 | JH4: 0.064508576 | JI4: 0.051659806 | JJ4: 0.070108898 | JK4: 0.017381178 | JL4: 0.052686646 | JM4: 0.096565696 | JN4: 0.067636425 | JO4: 0.065930229 | JP4: 0.015927638 | JQ4: 0.11306247 | JR4: 0.065200222 | JS4: 0.052978265 | JT4: 0.0042635646 | JU4: 0.070283199 | JV4: 0.083938384 | JW4: 0.056696544 | JX4: 0.047824324 | JY4: 0.073171084 | JZ4: 0.08941414 | KA4: 0.074620441 | KB4: 0.030919359 | KC4: 0.042577702 | KD4: 0.010652539 | KE4: 0.089550281 | KF4: 0.022274899 | KG4: 0.051533348 | KH4: 0.062414328 | KI4: 0.085935225 | KJ4: 0.069693487 | KK4: 0.074686707 | KL4: 0.058622535 | KM4: 0.10690968 | KN4: 0.05508784 | KO4: 0.063249162 | KP4: 0.051395833 | KQ4: 0.085262773 | KR4: 0.054300076 | KS4: 0.066824109 | KT4: 0.038112113 | KU4: 0.020496135 | KV4: 0.01845632 | KW4: 0.0586676 | KX4: 0.076501454 | KY4: 0.056347139 | KZ4: 0.081011364 | LA4: 0.09873426 | LB4: 0.055714797 | LC4: 0.061130161 | LD4: 0.056036526 | LE4: 0.08871877 | LF4: 0.031726003 | LG4: 0.026154444 | LH4: 0.063663657 | LI4: 0.10882882 | LJ4: 0.063640508 | LK4: 0.11969737 | LL4: 0.039374792 | LM4: 0.056742382 | LN4: 0.095146306 | LO4: 0.08465547 | LP4: 0.067816656 | LQ4: 0.045336609 | LR4: 0.063898894 | LS4: 0.082578183 | LT4: 0.065149943 | LU4: 0.075692748 | LV4: 0.044100458 | LW4: 0.051432389 | LX4: 0.044915238 | LY4: 0.062709356 | LZ4: 0.057074482 | MA4: 0.022847996 | MB4: 0.032359377 | MC4: 0.0990337 | MD4: 0.01845632 | ME4: 0.025717259 | MF4: 0.046499991 | MG4: 0.036416201 | MH4: 0.084824901 | MI4: 0.051475363 | MJ4: 0.050137279 | MK4: 0.041390656 | ML4: 0.04530435 | MM4: 0.082015572 | MN4: 0.040082768 | MO4: 0.055728892 | MP4: 0.072869495 | MQ4: 0.046722623 | MR4: 0.069843092 | MS4: 0.056959256 | MT4: 0.10348955 | MU4: 0.0714483 | MV4: 0.081809843 | MW4: 0.094344533 | MX4: 0.013540596 | MY4: 0.043496364 | MZ4: 0.032326717 | NA4: 0.083161134 | NB4: 0.093741126 | NC4: 0.03362091 | ND4: 0.066079577 | NE4: 0.041006845 | NF4: 0.033853827 | NG4: 0.054378002 | NH4: 0.034129317 | NI4: 0.027603056 | NJ4: 0.099997455 | NK4: 0.060762421 | NL4: 0.060950216 | NM4: 0.07014895 | NN4: 0.051676938 | NO4: 0.057749455 | NP4: 0.095056119 | NQ4: 0.049902986 | NR4: 0.076852892 | NS4: 0.0736356 | NT4: 0.078134509 | NU4: 0.094402519 | NV4: 0.057207443 | NW4: 0.015355573 | NX4: 0.062522306 | NY4: 0.037739101 | NZ4: 0.057253052 | OA4: 0.043164894 | OB4: 0.075180875 | OC4: 0.057773119 | OD4: 0.091998631 | OE4: 0.084989748 | OF4: 0.081140285 | OG4: 0.029322631 | OH4: 0.073290035 | OI4: 0.058019501 | OJ4: 0.098373282 | OK4: 0.016259509 | OL4: 0.057792858 | OM4: 0.098271405 | ON4: 0.06237187 | OO4: 0.099577116 | OP4: 0.065618212 | OQ4: 0.051423794 | OR4: 0.056634719 | OS4: 0.066330027 | OT4: 0.062368031 | OU4: 0.054119272 | OV4: 0.068790754 | OW4: 0.038638224 | OX4: 0.079806498 | OY4: 0.04797496 | OZ4: 0.082374144 | PA4: 0.08697702 | PB4: 0.01051617 | PC4: 0.087221855 | PD4: 0.063278069 | PE4: 0.094307289 | PF4: 0.088303759 | PG4: 0.035315733 | PH4: 0.087453626 | PI4: 0.062950352 | PJ4: 0.045797114 | PK4: 0.04511286 | PL4: 0.074021217 | PM4: 0.050560999 | PN4: 0.073419644 | PO4: 0.027908913 | PP4: 0.0012226363 | PQ4: 0.050532579 | PR4: 0.073930371 | PS4: 0.086556108 | PT4: 0.03561947 | PU4: 0.094962035 | PV4: 0.08603097 | PW4: 0.021498968 | PX4: 0.029184141 | PY4: 0.031914284 | PZ4: 0.033743414 | QA4: 0.099209491 | QB4: 0.051503296 | QC4: 0.042159884 | QD4: 0.055146685 | QE4: 0.084658221 | QF4: 0.0033009554 | QG4: 0.058832075 | QH4: 0.003494394 | QI4: 0.052896586 | QJ4: 0.088702669 | QK4: 0.045806855 | QL4: 0.068624876 | QM4: 0.071147886 | QN4: 0.081804772 | QO4: 0.078612863 | QP4: 0.070032864 | QQ4: 0.053710793 | QR4: 0.065457548 | QS4: 0.066689773 | QT4: 0.084619487 | QU4: 0.071452368 | QV4: 0.06291179 | QW4: 0.04320718 | QX4: 0.065403344 | QY4: 0.052680343 | QZ4: 0.066001995 | RA4: 0.087346651 | RB4: 0.062913738 | RC4: 0.077063205 | RD4: 0.069980894 | RE4: 0.052052355 | RF4: 0.052499166 | RG4: 0.016160727 | RH4: 0.067977521 | RI4: 0.04428748 | RJ4: 0.056485056 | RK4: 0.030923714 | RL4: 0.033594038 | RM4: 0.089603625 | RN4: 0.040310815 | RO4: 0.056923502 | RP4: 0.046502369 | RQ4: 0.046996193 | RR4: 0.081122924 | RS4: 0.067691259 | RT4: 0.02766574 | RU4: 0.070612721 | RV4: 0.077040773 | RW4: 0.038039229 | RX4: 0.070485978 | RY4: 0.053520105 | RZ4: 0.082731398 | SA4: 0.045356434 | SB4: 0.030906181 | SC4: 0.089497051 | SD4: 0.11043867 | SE4: 0.092782929 | SF4: 0.077166485 | SG4: 0.11314475
A5: 4 | B5: 0.028295332 | C5: 0.009626673 | D5: 0.021392508 | E5: 0.039001437 | F5: 0.064448728 | G5: 0.081175122 | H5: 0.054067847 | I5: 0.060772105 | J5: 0.055976306 | K5: 0.074362542 | L5: 0.088494447 | M5: 0.036692665 | N5: 0.071054719 | O5: -0.0014919216 | P5: 0.13205681 | Q5: 0.055909983 | R5: 0.047826616 | S5: 0.064487347 | T5: 0.055164964 | U5: 0.067052156 | V5: 0.06832343 | W5: 0.085532705 | X5: 0.074631127 | Y5: 0.070907119 | Z5: 0.025033348 | AA5: 0.080066059 | AB5: 0.067518993 | AC5: 0.044514094 | AD5: 0.041524906 | AE5: 0.011582374 | AF5: 0.038891138 | AG5: 0.11759567 | AH5: 0.09188415 | AI5: 0.053216425 | AJ5: 0.066130056 | AK5: 0.062246501 | AL5: 0.05314549 | AM5: 0.053729415 | AN5: 0.043016434 | AO5: 0.065505907 | AP5: 0.077437047 | AQ5: 0.074845222 | AR5: 0.10201653 | AS5: 0.048048932 | AT5: 0.076183421 | AU5: 0.05015931 | AV5: 0.091755515 | AW5: 0.061868276 | AX5: 0.084079366 | AY5: 0.074571337 | AZ5: 0.050165928 | BA5: 0.09250446 | BB5: 0.065385925 | BC5: 0.071397477 | BD5: 0.01391143 | BE5: 0.076154829 | BF5: 0.096649237 | BG5: 0.072598217 | BH5: 0.074853788 | BI5: 0.047050684 | BJ5: 0.077727434 | BK5: 0.06247409 | BL5: 0.11459966 | BM5: 0.097736126 | BN5: 0.10182194 | BO5: 0.078346426 | BP5: 0.047026991 | BQ5: 0.020292154 | BR5: 0.08128714 | BS5: 0.041805438 | BT5: 0.042518342 | BU5: 0.062335227 | BV5: 0.064400483 | BW5: 0.10226463 | BX5: 0.042195409 | BY5: 0.031227852 | BZ5: 0.022439804 | CA5: 0.069605849 | CB5: 0.042604633 | CC5: 0.084437451 | CD5: 0.084566945 | CE5: 0.094044692 | CF5: 0.065670525 | CG5: 0.08309527 | CH5: 0.038513945 | CI5: 0.027072475 | CJ5: 0.063312763 | CK5: 0.051257973 | CL5: 0.053066103 | CM5: 0.027350371 | CN5: 0.045398491 | CO5: 0.081572657 | CP5: 0.051894785 | CQ5: 0.039096037 | CR5: 0.079489238 | CS5: 0.044736697 | CT5: 0.035076226 | CU5: 0.088555126 | CV5: 0.055759088 | CW5: 0.064388908 | CX5: 0.003746506 | CY5: 0.088731662 | CZ5: 0.10331066 | DA5: 0.080429587 | DB5: 0.078443547 | DC5: 0.10044553 | DD5: 0.060655847 | DE5: 0.057169769 | DF5: 0.070876837 | DG5: 0.054306236 | DH5: 0.090868425 | DI5: 0.0106695 | DJ5: 0.065264052 | DK5: 0.075027831 | DL5: 0.083765802 | DM5: 0.057375871 | DN5: 0.052944774 | DO5: 0.083040034 | DP5: 0.061489736 | DQ5: 0.071501186 | DR5: 0.040952841 | DS5: 0.089036259 | DT5: 0.030137583 | DU5: 0.061594047 | DV5: 0.029629463 | DW5: 0.031514572 | DX5: 0.068203419 | DY5: 0.085079534 | DZ5: 0.029903692 | EA5: 0.018567708 | EB5: 0.036012593 | EC5: 0.062364163 | ED5: 0.069369179 | EE5: 0.13801215 | EF5: 0.067048259 | EG5: 0.040525511 | EH5: 0.020585062 | EI5: 0.082796546 | EJ5: 0.067479887 | EK5: 0.090794568 | EL5: 0.070058877 | EM5: 0.042612712 | EN5: 0.044925266 | EO5: 0.042714817 | EP5: 0.0088639198 | EQ5: 0.043525128 | ER5: 0.084699819 | ES5: 0.082627459 | ET5: 0.044182567 | EU5: 0.065523355 | EV5: 0.088098746 | EW5: 0.040252543 | EX5: 0.018869784 | EY5: 0.057751431 | EZ5: 0.032918378 | FA5: 0.0095524146 | FB5: 0.054328811 | FC5: 0.062611032 | FD5: 0.037065218 | FE5: 0.09839368 | FF5: 0.04520001 | FG5: 0.050755182 | FH5: 0.083084756 | FI5: 0.05893186 | FJ5: 0.051574087 | FK5: 0.064558769 | FL5: 0.077921331 | FM5: 0.01724985 | FN5: 0.10753022 | FO5: 0.048570002 | FP5: 0.057670498 | FQ5: 0.02440238 | FR5: 0.063652083 | FS5: 0.097101148 | FT5: 0.045475127 | FU5: 0.089291923 | FV5: 0.023673662 | FW5: 0.05187559 | FX5: 0.052879798 | FY5: 0.087836263 | FZ5: 0.04620588 | GA5: 0.047940238 | GB5: 0.015472003 | GC5: 0.10070612 | GD5: 0.048051253 | GE5: 0.094669815 | GF5: 0.042304333 | GG5: 0.10085853 | GH5: 0.081974833 | GI5: 0.075144175 | GJ5: 0.072451648 | GK5: 0.046186513 | GL5: 0.08129711 | GM5: 0.051037519 | GN5: 0.069853062 | GO5: 0.080015465 | GP5: 0.047244294 | GQ5: 0.058841873 | GR5: 0.070905114 | GS5: 0.10831211 | GT5: 0.07956533 | GU5: 0.091755515 | GV5: 0.097969329 | GW5: 0.06280384 | GX5: 0.029722859 | GY5: 0.057149915 | GZ5: 0.052697132 | HA5: 0.087282648 | HB5: 0.046220405 | HC5: 0.062607165 | HD5: 0.042738939 | HE5: 0.058194604 | HF5: 0.035344153 | HG5: 0.02900583 | HH5: 0.0014967508 | HI5: 0.045704005 | HJ5: 0.02218815 | HK5: 0.02362748 | HL5: 0.049683133 | HM5: 0.074116389 | HN5: 0.044842412 | HO5: 0.040989798 | HP5: 0.082557441 | HQ5: 0.09420845 | HR5: 0.073000364 | HS5: 0.054232321 | HT5: 0.097849805 | HU5: 0.078545538 | HV5: 0.082531542 | HW5: 0.095798531 | HX5: 0.11962632 | HY5: 0.01855854 | HZ5: 0.059347844 | IA5: 0.073139799 | IB5: 0.014585485 | IC5: 0.066847487 | ID5: 0.057846117 | IE5: 0.082526385 | IF5: 0.063977966 | IG5: 0.059599269 | IH5: 0.10775849 | II5: 0.089150626 | IJ5: 0.045277076 | IK5: 0.048972006 | IL5: 0.092538609 | IM5: 0.044907732 | IN5: 0.047453404 | IO5: 0.093757227 | IP5: 0.050974691 | IQ5: 0.052429492 | IR5: 0.054022553 | IS5: 0.067889225 | IT5: 0.10256877 | IU5: 0.074802306 | IV5: 0.085113283 | IW5: 0.052655075 | IX5: 0.073700748 | IY5: 0.057895393 | IZ5: 0.025594411 | JA5: 0.068230951 | JB5: 0.063681018 | JC5: 0.04730079 | JD5: 0.028031875 | JE5: 0.078794555 | JF5: 0.093307665 | JG5: 0.055682538 | JH5: 0.078413465 | JI5: 0.066890346 | JJ5: 0.085687296 | JK5: 0.048129723 | JL5: 0.048469501 | JM5: 0.056008421 | JN5: 0.053059829 | JO5: 0.041558368 | JP5: 0.049674195 | JQ5: 0.028947729 | JR5: 0.081043566 | JS5: 0.033655461 | JT5: 0.087276575 | JU5: 0.018623173 | JV5: 0.082809581 | JW5: 0.085090764 | JX5: 0.055952183 | JY5: 0.096869147 | JZ5: 0.054888615 | KA5: 0.11050605 | KB5: 0.06399146 | KC5: 0.062799973 | KD5: 0.052564544 | KE5: 0.031603614 | KF5: 0.059484329 | KG5: 0.057373894 | KH5: 0.054963904 | KI5: -0.0040341266 | KJ5: 0.075871805 | KK5: 0.099225534 | KL5: 0.07558603 | KM5: 0.061420147 | KN5: 0.015587516 | KO5: 0.076922109 | KP5: 0.095856402 | KQ5: 0.049643025 | KR5: 0.075540392 | KS5: 0.081784546 | KT5: 0.052099082 | KU5: 0.11630257 | KV5: 0.0482057 | KW5: 0.055936111 | KX5: 0.053112085 | KY5: 0.050827005 | KZ5: 0.046670052 | LA5: 0.048464946 | LB5: 0.10698795 | LC5: 0.043522492 | LD5: 0.057551948 | LE5: 0.088067404 | LF5: 0.048512933 | LG5: 0.020431159 | LH5: 0.042604633 | LI5: 0.074082526 | LJ5: 0.15028588 | LK5: 0.076812698 | LL5: 0.05987367 | LM5: 0.044827343 | LN5: 0.067881375 | LO5: 0.081344553 | LP5: 0.036198182 | LQ5: 0.095271617 | LR5: 0.045938756 | LS5: 0.12125267 | LT5: 0.11417497 | LU5: 0.033731954 | LV5: 0.068250604 | LW5: 0.056580859 | LX5: 0.051195404 | LY5: 0.031015448 | LZ5: 0.071819363 | MA5: 0.051251499 | MB5: 0.031759579 | MC5: 0.073171084 | MD5: 0.061466559 | ME5: 0.065006898 | MF5: 0.071566363 | MG5: 0.069492427 | MH5: 0.034754096 | MI5: 0.10767587 | MJ5: 0.062641859 | MK5: 0.058824254 | ML5: 0.076917639 | MM5: 0.018400168 | MN5: 0.079089813 | MO5: 0.067848027 | MP5: 0.080671471 | MQ5: 0.037503549 | MR5: 0.06502042 | MS5: 0.11233272 | MT5: 0.069367202 | MU5: 0.053101628 | MV5: 0.048722644 | MW5: 0.053366374 | MX5: 0.078923161 | MY5: 0.073599904 | MZ5: 0.072869495 | NA5: 0.086707604 | NB5: 0.013200245 | NC5: 0.049354729 | ND5: 0.04830454 | NE5: 0.049956131 | NF5: 0.080293475 | NG5: 0.10884865 | NH5: 0.07976341 | NI5: 0.047298441 | NJ5: 0.047689386 | NK5: 0.072792773 | NL5: 0.067714752 | NM5: 0.056219021 | NN5: 0.05412546 | NO5: 0.029666821 | NP5: 0.077695577 | NQ5: 0.073930371 | NR5: 0.11097429 | NS5: 0.045371274 | NT5: 0.061652004 | NU5: 0.052342857 | NV5: 0.06263802 | NW5: 0.019782429 | NX5: 0.038048741 | NY5: 0.060744974 | NZ5: 0.042499433 | OA5: 0.076375312 | OB5: 0.063135425 | OC5: 0.054890677 | OD5: 0.031704917 | OE5: 0.091013275 | OF5: 0.036975947 | OG5: 0.079960115 | OH5: 0.076077877 | OI5: 0.089278745 | OJ5: 0.042936675 | OK5: 0.075725436 | OL5: 0.10689237 | OM5: 0.053101628 | ON5: 0.040191176 | OO5: 0.063112277 | OP5: 0.035936616 | OQ5: 0.076721336 | OR5: 0.04447347 | OS5: 0.06049885 | OT5: 0.06291179 | OU5: 0.051281695 | OV5: 0.043088114 | OW5: 0.058277171 | OX5: 0.074505215 | OY5: 0.030632639 | OZ5: 0.052353428 | PA5: 0.061619172 | PB5: 0.091887817 | PC5: 0.0708526 | PD5: 0.088648064 | PE5: 0.058630385 | PF5: 0.059836712 | PG5: 0.10262767 | PH5: 0.076835015 | PI5: 0.061327381 | PJ5: 0.030945602 | PK5: 0.07235894 | PL5: 0.07058453 | PM5: 0.078244951 | PN5: 0.052526584 | PO5: 0.030431637 | PP5: 0.049276202 | PQ5: -0.0037022556 | PR5: 0.050961656 | PS5: 0.065238898 | PT5: 0.059086278 | PU5: 0.066073761 | PV5: 0.081898569 | PW5: 0.093597021 | PX5: 0.048795298 | PY5: -0.0014919216 | PZ5: 0.038734141 | QA5: -8.83457e-05 | QB5: 0.034775984 | QC5: 0.062786479 | QD5: 0.076084467 | QE5: 0.043475393 | QF5: 0.080068466 | QG5: 0.10079974 | QH5: 0.053393419 | QI5: 0.083436738 | QJ5: 0.033435837 | QK5: 0.064195957 | QL5: 0.072757563 | QM5: 0.052617201 | QN5: 0.053468222 | QO5: 0.06683385 | QP5: 0.045100369 | QQ5: 0.075258628 | QR5: 0.043506792 | QS5: 0.063212548 | QT5: 0.10995599 | QU5: 0.043286309 | QV5: 0.043780334 | QW5: 0.055318952 | QX5: 0.073294189 | QY5: 0.047095606 | QZ5: 0.067019009 | RA5: 0.063094944 | RB5: 0.034932007 | RC5: 0.065728625 | RD5: 0.10429906 | RE5: 0.072767906 | RF5: 0.082655993 | RG5: 0.039852774 | RH5: 0.073185667 | RI5: 0.067846079 | RJ5: 0.042094278 | RK5: 0.053896783 | RL5: 0.075710195 | RM5: 0.020431159 | RN5: 0.03698586 | RO5: 0.03260255 | RP5: 0.066499114 | RQ5: 0.047870735 | RR5: 0.057907225 | RS5: 0.050837863 | RT5: 0.057371917 | RU5: 0.10424084 | RV5: 0.085675836 | RW5: 0.052873524 | RX5: 0.037668338 | RY5: 0.078042689 | RZ5: 0.09494072 | SA5: 0.065829413 | SB5: 0.045137784 | SC5: 0.053721136 | SD5: 0.069904974 | SE5: 0.098729103 | SF5: 0.072165616 | SG5: 0.054012239
A6: 5 | B6: 0.061244242 | C6: 0.038946374 | D6: 0.10929317 | E6: 0.05716381 | F6: 0.06500495 | G6: 0.063788968 | H6: -0.011300451 | I6: 0.047248993 | J6: 0.071892991 | K6: 0.058863388 | L6: 0.073606206 | M6: 0.066964432 | N6: 0.048890557 | O6: 0.084989748 | P6: 0.079603434 | Q6: 0.036929478 | R6: 0.072505279 | S6: 0.059733576 | T6: 0.056253056 | U6: 0.054582671 | V6: 0.097613221 | W6: 0.070858645 | X6: 0.073709171 | Y6: 0.10352416 | Z6: 0.076761445 | AA6: 0.067751996 | AB6: 0.031755397 | AC6: 0.093061169 | AD6: 0.067200443 | AE6: 0.06670533 | AF6: 0.083171734 | AG6: 0.015792643 | AH6: 0.051108941 | AI6: 0.058653906 | AJ6: 0.070355452 | AK6: 0.076670169 | AL6: 0.055730898 | AM6: 0.052596115 | AN6: 0.058086425 | AO6: 0.026424891 | AP6: 0.07808168 | AQ6: 0.064240306 | AR6: 0.075753799 | AS6: 0.071454402 | AT6: 0.066283415 | AU6: 0.079756248 | AV6: 0.051413022 | AW6: 0.063625095 | AX6: 0.0632318 | AY6: 0.061561215 | AZ6: 0.052701372 | BA6: 0.10242564 | BB6: 0.056776245 | BC6: 0.040264232 | BD6: 0.13901693 | BE6: 0.071621369 | BF6: 0.047038823 | BG6: 0.10613248 | BH6: 0.034386528 | BI6: 0.051316188 | BJ6: 0.077366972 | BK6: 0.091187633 | BL6: 0.036746239 | BM6: 0.051967239 | BN6: 0.062101795 | BO6: 0.035542175 | BP6: 0.075756005 | BQ6: 0.055146685 | BR6: 0.030601469 | BS6: 0.072942178 | BT6: 0.04076433 | BU6: 0.057729715 | BV6: 0.06137958 | BW6: 0.088167962 | BX6: 0.053199722 | BY6: 0.085384647 | BZ6: 0.064049331 | CA6: 0.060411585 | CB6: 0.10373364 | CC6: 0.070349436 | CD6: 0.059308824 | CE6: 0.049332297 | CF6: 0.086399569 | CG6: 0.042494047 | CH6: 0.097613221 | CI6: 0.053187203 | CJ6: 0.060715924 | CK6: 0.036699369 | CL6: 0.077258735 | CM6: 0.063243375 | CN6: 0.034482732 | CO6: 0.058455855 | CP6: 0.010770574 | CQ6: 0.043082786 | CR6: 0.095336708 | CS6: 0.11076665 | CT6: 0.024615415 | CU6: 0.047157029 | CV6: 0.065775151 | CW6: 0.073411278 | CX6: 0.042556101 | CY6: 0.03040018 | CZ6: 0.070409656 | DA6: 0.070199028 | DB6: 0.039062517 | DC6: 0.083050549 | DD6: 0.077891622 | DE6: 0.02625632 | DF6: 0.065353036 | DG6: 0.034430992 | DH6: 0.050950798 | DI6: 0.071942096 | DJ6: 0.041269872 | DK6: 0.103552 | DL6: 0.10298555 | DM6: 0.031501852 | DN6: 0.093146944 | DO6: 0.028903953 | DP6: 0.055057386 | DQ6: 0.081467171 | DR6: 0.062337147 | DS6: 0.039108241 | DT6: 0.061242322 | DU6: 0.05485604 | DV6: 0.044226113 | DW6: 0.070000891 | DX6: 0.04620588 | DY6: 0.068475041 | DZ6: 0.05880271 | EA6: 0.10107775 | EB6: 0.015701883 | EC6: 0.041655775 | ED6: 0.013527303 | EE6: 0.11405625 | EF6: 0.018614005 | EG6: 0.093453833 | EH6: 0.055887866 | EI6: 0.094673997 | EJ6: 0.059386836 | EK6: 0.082806974 | EL6: 0.079924046 | EM6: 0.069520274 | EN6: 0.036628892 | EO6: 0.073386181 | EP6: 0.082299542 | EQ6: 0.072381573 | ER6: 0.052587692 | ES6: 0.11714874 | ET6: 0.063943272 | EU6: 0.017914509 | EV6: 0.02987596 | EW6: 0.074182082 | EX6: 0.049638555 | EY6: 0.028082871 | EZ6: 0.020126906 | FA6: 0.078489844 | FB6: 0.090487679 | FC6: 0.07780261 | FD6: 0.059392709 | FE6: 0.076179009 | FF6: 0.045539273 | FG6: 0.059000274 | FH6: 0.066851383 | FI6: 0.01981635 | FJ6: 0.072840474 | FK6: 0.046569551 | FL6: 0.087904792 | FM6: 0.05510205 | FN6: 0.1114721 | FO6: 0.091041637 | FP6: 0.073778617 | FQ6: 0.077843664 | FR6: 0.025658814 | FS6: 0.054896751 | FT6: 0.041849615 | FU6: 0.073612509 | FV6: 0.062300505 | FW6: 0.07966543 | FX6: 0.03902894 | FY6: 0.06949641 | FZ6: 0.083423416 | GA6: 0.062003385 | GB6: 0.0023493475 | GC6: 0.1025949 | GD6: 0.034783261 | GE6: 0.064016556 | GF6: 0.048088182 | GG6: 0.06188177 | GH6: 0.04466857 | GI6: 0.092338295 | GJ6: 0.079363526 | GK6: 0.080174754 | GL6: 0.058920113 | GM6: 0.042222654 | GN6: 0.022965686 | GO6: 0.073148165 | GP6: 0.10682316 | GQ6: 0.065817781 | GR6: 0.057494592 | GS6: 0.033029249 | GT6: 0.024122536 | GU6: 0.066493298 | GV6: 0.027313242 | GW6: 0.025670503 | GX6: 0.041750088 | GY6: 0.069385079 | GZ6: 0.046803729 | HA6: 0.065502068 | HB6: 0.095423801 | HC6: 0.081512351 | HD6: 0.035411535 | HE6: 0.032154536 | HF6: 0.062109501 | HG6: 0.054507009 | HH6: 0.065542693 | HI6: 0.06800892 | HJ6: 0.047180636 | HK6: 0.094787906 | HL6: 0.032989714 | HM6: 0.0051748347 | HN6: 0.058520573 | HO6: 0.024256728 | HP6: 0.060046653 | HQ6: 0.028742602 | HR6: 0.043855509 | HS6: 0.087839415 | HT6: 0.11771485 | HU6: 0.094448243 | HV6: 0.070353447 | HW6: 0.032306319 | HX6: 0.041533271 | HY6: 0.023034444 | HZ6: 0.024801061 | IA6: 0.10854371 | IB6: 0.096004346 | IC6: 0.058001796 | ID6: 0.070492022 | IE6: 0.029092808 | IF6: 0.036088399 | IG6: 0.028204572 | IH6: 0.092263177 | II6: 0.055855693 | IJ6: 0.060897932 | IK6: 0.028057316 | IL6: 0.036365321 | IM6: 0.049109722 | IN6: 0.034924787 | IO6: 0.061375712 | IP6: 0.046004477 | IQ6: 0.085886063 | IR6: 0.02226768 | IS6: 0.03305681 | IT6: 0.051188929 | IU6: 0.09738443 | IV6: 0.096353808 | IW6: 0.10598511 | IX6: 0.03192265 | IY6: 0.028757385 | IZ6: 0.052772794 | JA6: 0.015575827 | JB6: 0.021754517 | JC6: 0.093955192 | JD6: 0.073331806 | JE6: 0.020568904 | JF6: 0.074761624 | JG6: 0.047577426 | JH6: 0.094468984 | JI6: 0.08148224 | JJ6: 0.068201442 | JK6: 0.050774778 | JL6: 0.076234072 | JM6: -0.0097694439 | JN6: 0.066621675 | JO6: 0.058808611 | JP6: 0.097520398 | JQ6: 0.062526174 | JR6: 0.03123215 | JS6: 0.063584585 | JT6: 0.04785217 | JU6: 0.058912292 | JV6: 0.098604537 | JW6: 0.011660529 | JX6: 0.031158751 | JY6: 0.12662403 | JZ6: 0.066625571 | KA6: 0.078304885 | KB6: 0.061346719 | KC6: 0.064118776 | KD6: 0.091697014 | KE6: 0.09053621 | KF6: 0.072525935 | KG6: 0.079429877 | KH6: 0.062888642 | KI6: 0.060781788 | KJ6: 0.049354729 | KK6: 0.088609559 | KL6: 0.092229486 | KM6: 0.083129505 | KN6: 0.051918249 | KO6: 0.064066692 | KP6: 0.035287256 | KQ6: 0.056118806 | KR6: 0.085059881 | KS6: 0.096121578 | KT6: 0.053882315 | KU6: 0.094012089 | KV6: 0.082209755 | KW6: 0.077245213 | KX6: 0.061418228 | KY6: 0.10068274 | KZ6: 0.061364109 | LA6: 0.039220603 | LB6: 0.056572894 | LC6: 0.057391714 | LD6: 0.085532705 | LE6: 0.046290509 | LF6: 0.067704954 | LG6: 0.060136009 | LH6: 0.065765468 | LI6: 0.086892906 | LJ6: 0.067900971 | LK6: 0.044241469 | LL6: 0.10592014 | LM6: 0.031918525 | LN6: 0.10465293 | LO6: 0.025896946 | LP6: 0.071505255 | LQ6: 0.032779028 | LR6: 0.098009324 | LS6: 0.13063948 | LT6: 0.011892472 | LU6: 0.061333168 | LV6: 0.03139098 | LW6: 0.031266586 | LX6: 0.055595846 | LY6: 0.05037922 | LZ6: 0.11688471 | MA6: 0.096004346 | MB6: 0.091467993 | MC6: 0.065289206 | MD6: 0.036625569 | ME6: 0.035169451 | MF6: 0.048078957 | MG6: 0.050223169 | MH6: 0.026784609 | MI6: 0.018539976 | MJ6: 0.047208941 | MK6: 0.095341063 | ML6: 0.068388378 | MM6: 0.076300223 | MN6: 0.065881755 | MO6: 0.090418462 | MP6: 0.066976121 | MQ6: 0.056925478 | MR6: 0.09027728 | MS6: 0.070834436 | MT6: 0.041926795 | MU6: 0.070138923 | MV6: 0.044519193 | MW6: 0.058563719 | MX6: 0.052697132 | MY6: 0.065409131 | MZ6: 0.051318337 | NA6: 0.089463875 | NB6: 0.029657539 | NC6: 0.0936369 | ND6: 0.054361615 | NE6: 0.07140355 | NF6: 0.058143494 | NG6: 0.08203087 | NH6: 0.066314499 | NI6: 0.036649061 | NJ6: 0.084349555 | NK6: 0.052486503 | NL6: 0.046715461 | NM6: 0.053760414 | NN6: 0.071745821 | NO6: 0.033785356 | NP6: 0.02489927 | NQ6: 0.053874065 | NR6: 0.068370644 | NS6: 0.078631485 | NT6: 0.10125171 | NU6: 0.062587884 | NV6: 0.060149589 | NW6: 0.081439611 | NX6: 0.061545745 | NY6: 0.039181182 | NZ6: 0.08519499 | OA6: 0.071690729 | OB6: 0.075187349 | OC6: 0.046993815 | OD6: 0.10760287 | OE6: 0.041337312 | OF6: 0.030422641 | OG6: 0.048334392 | OH6: 0.062223353 | OI6: 0.08754261 | OJ6: 0.078297952 | OK6: 0.041904793 | OL6: 0.10074703 | OM6: 0.1050994 | ON6: 0.076357636 | OO6: 0.036896303 | OP6: 0.093934908 | OQ6: 0.058094304 | OR6: 0.013580934 | OS6: 0.080412541 | OT6: 0.016519184 | OU6: 0.015167406 | OV6: 0.054055499 | OW6: 0.059768613 | OX6: 0.053266446 | OY6: 0.06105278 | OZ6: 0.042550715 | PA6: 0.063135425 | PB6: 0.037761562 | PC6: 0.089377756 | PD6: 0.060036941 | PE6: 0.0244465 | PF6: 0.034192975 | PG6: 0.053422526 | PH6: 0.070381523 | PI6: 0.12997207 | PJ6: 0.093426101 | PK6: 0.098180244 | PL6: 0.081204946 | PM6: 0.082397292 | PN6: 0.059998064 | PO6: 0.075727642 | PP6: 0.06157087 | PQ6: 0.046550356 | PR6: 0.024794987 | PS6: 0.022411269 | PT6: 0.078979399 | PU6: 0.065980651 | PV6: 0.073004518 | PW6: 0.099198719 | PX6: 0.04340463 | PY6: 0.087808302 | PZ6: 0.064051279 | QA6: 0.048824807 | QB6: 0.086089185 | QC6: 0.056827986 | QD6: 0.059123379 | QE6: 0.062155827 | QF6: 0.092637506 | QG6: 0.0678853 | QH6: 0.0904219 | QI6: 0.053274754 | QJ6: 0.10999908 | QK6: -0.011001584 | QL6: 0.048228734 | QM6: 0.071243173 | QN6: 0.074343405 | QO6: 0.099289938 | QP6: 0.06269973 | QQ6: 0.085555567 | QR6: 0.046583933 | QS6: 0.082919364 | QT6: 0.10133021 | QU6: 0.090822644 | QV6: 0.072612714 | QW6: 0.10127578 | QX6: 0.072472276 | QY6: 0.088609559 | QZ6: 0.069665582 | RA6: 0.079672593 | RB6: 0.031784791 | RC6: 0.019094507 | RD6: 0.0632318 | RE6: 0.088792914 | RF6: 0.069575997 | RG6: 0.067706931 | RH6: 0.072774122 | RI6: 0.089936356 | RJ6: 0.040838703 | RK6: 0.0083601543 | RL6: 0.063416874 | RM6: 0.050602511 | RN6: 0.016017023 | RO6: 0.030928068 | RP6: 0.079470244 | RQ6: 0.031262289 | RR6: 0.039368776 | RS6: 0.1161788 | RT6: 0.065961256 | RU6: 0.045368811 | RV6: 0.05978417 | RW6: 0.035748907 | RX6: 0.020102038 | RY6: 0.03552808 | RZ6: 0.074320027 | SA6: 0.057646776 | SB6: 0.050504102 | SC6: 0.049005926 | SD6: 0.082645622 | SE6: 0.04600694 | SF6: 0.082454017 | SG6: 0.067208265
A7: 6 | B7: 0.022553483 | C7: 0.070862713 | D7: 0.068169986 | E7: 0.10036531 | F7: 0.030192245 | G7: 0.078401891 | H7: 0.068514462 | I7: 0.089912692 | J7: 0.078054149 | K7: 0.10438672 | L7: 0.073871296 | M7: 0.042326049 | N7: 0.057952548 | O7: 0.032662885 | P7: 0.0052293825 | Q7: 0.093390518 | R7: 0.063407247 | S7: 0.069458621 | T7: 0.10384652 | U7: 0.02040675 | V7: 0.075799666 | W7: 0.050724699 | X7: 0.034826865 | Y7: 0.02819953 | Z7: 0.038881971 | AA7: 0.023034444 | AB7: 0.066870864 | AC7: 0.047298441 | AD7: 0.090713949 | AE7: 0.053197631 | AF7: 0.047940238 | AG7: 0.044274702 | AH7: 0.026740718 | AI7: 0.038931018 | AJ7: 0.04020871 | AK7: 0.036521114 | AL7: 0.028535297 | AM7: 0.079892847 | AN7: 0.094319665 | AO7: 0.089206377 | AP7: 0.10273287 | AQ7: 0.087343614 | AR7: 0.11254083 | AS7: 0.073989503 | AT7: 0.022057166 | AU7: 0.065932148 | AV7: 0.066555524 | AW7: 0.048035066 | AX7: 0.07953204 | AY7: 0.05048442 | AZ7: 0.071371062 | BA7: 0.05331641 | BB7: 0.060283552 | BC7: 0.09575848 | BD7: 0.020927361 | BE7: 0.048108952 | BF7: 0.077704687 | BG7: 0.038632036 | BH7: 0.064958595 | BI7: 0.078360293 | BJ7: 0.06718291 | BK7: 0.05513047 | BL7: 0.07129795 | BM7: 0.054302139 | BN7: 0.065140288 | BO7: 0.089032993 | BP7: 0.02625632 | BQ7: 0.060116585 | BR7: 0.10123968 | BS7: 0.082619666 | BT7: 0.054851972 | BU7: 0.075839001 | BV7: 0.065008817 | BW7: 0.090699968 | BX7: 0.028077714 | BY7: 0.0015737595 | BZ7: 0.045694178 | CA7: 0.076846189 | CB7: 0.074520112 | CC7: 0.069729384 | CD7: 0.035988471 | CE7: 0.069542162 | CF7: 0.054414873 | CG7: 0.024427591 | CH7: 0.045452896 | CI7: 0.072321868 | CJ7: 0.090116387 | CK7: 0.081946871 | CL7: 0.056471075 | CM7: 0.08184531 | CN7: 0.055391807 | CO7: 0.059351741 | CP7: 0.087545704 | CQ7: 0.078374159 | CR7: 0.096982426 | CS7: -0.0008382641 | CT7: 0.06746814 | CU7: 0.06173119 | CV7: 0.020185006 | CW7: 0.07763421 | CX7: 0.049439845 | CY7: 0.035276541 | CZ7: 0.053410035 | DA7: 0.072674739 | DB7: 0.10398163 | DC7: 0.095630074 | DD7: 0.073700748 | DE7: 0.059861981 | DF7: 0.068778893 | DG7: 0.026385699 | DH7: 0.042792513 | DI7: 0.070150955 | DJ7: 0.078904453 | DK7: 0.071030453 | DL7: 0.10925226 | DM7: 0.0034623071 | DN7: 0.088256316 | DO7: 0.057715907 | DP7: 0.037784023 | DQ7: 0.018549143 | DR7: 0.022595884 | DS7: 0.066861124 | DT7: 0.050137279 | DU7: 0.02696441 | DV7: 0.096496308 | DW7: 0.10488591 | DX7: 0.078413465 | DY7: 0.069494433 | DZ7: 0.032117464 | EA7: 0.06515381 | EB7: 0.099305981 | EC7: 0.077468676 | ED7: 0.029078369 | EE7: 0.047940238 | EF7: 0.07555125 | EG7: 0.055549406 | EH7: 0.059573943 | EI7: 0.06069269 | EJ7: 0.058285021 | EK7: 0.032448876 | EL7: 0.10659213 | EM7: 0.047659104 | EN7: 0.064995295 | EO7: 0.059256139 | EP7: 0.052606658 | EQ7: 0.039926688 | ER7: 0.048180374 | ES7: 0.097790445 | ET7: 0.051509742 | EU7: 0.047038823 | EV7: 0.026199824 | EW7: 0.10370556 | EX7: 0.052118191 | EY7: 0.091496929 | EZ7: 0.064651448 | FA7: 0.043088114 | FB7: 0.04991628 | FC7: 0.080451504 | FD7: 0.042976584 | FE7: 0.12103585 | FF7: 0.090584856 | FG7: 0.036067771 | FH7: 0.06753856 | FI7: 0.034163008 | FJ7: 0.065134472 | FK7: 0.085736114 | FL7: 0.082622245 | FM7: 0.11025027 | FN7: 0.019645601 | FO7: 0.077215962 | FP7: 0.031548608 | FQ7: 0.015927638 | FR7: 0.063748487 | FS7: 0.027691753 | FT7: 0.065169281 | FU7: 0.072282762 | FV7: 0.066250411 | FW7: 0.078355651 | FX7: 0.038579264 | FY7: 0.05768826 | FZ7: 0.017778139 | GA7: 0.055452457 | GB7: 0.046832263 | GC7: 0.08203087 | GD7: 0.07233009 | GE7: 0.076634586 | GF7: 0.049696484 | GG7: 0.052494955 | GH7: 0.084950556 | GI7: 0.12773699 | GJ7: 0.014915981 | GK7: 0.058834052 | GL7: 0.050907423 | GM7: 0.030009464 | GN7: 0.090977864 | GO7: 0.065320147 | GP7: 0.03257837 | GQ7: 0.065447864 | GR7: 0.066149452 | GS7: 0.094406644 | GT7: 0.066536071 | GU7: 0.061875983 | GV7: 0.06180648 | GW7: 0.036263101 | GX7: 0.074853788 | GY7: 0.059640151 | GZ7: 0.072786556 | HA7: 0.039608855 | HB7: 0.079782548 | HC7: 0.055664403 | HD7: 0.065465283 | HE7: 0.020043709 | HF7: 0.070582525 | HG7: 0.034012773 | HH7: 0.096413455 | HI7: 0.042132553 | HJ7: 0.040718434 | HK7: 0.077414414 | HL7: 0.096639897 | HM7: 0.087780398 | HN7: 0.06350941 | HO7: 0.075946235 | HP7: 0.055051284 | HQ7: 0.068628829 | HR7: 0.078785216 | HS7: 0.087628844 | HT7: 0.078843603 | HU7: 0.058976839 | HV7: 0.069932936 | HW7: 0.054682742 | HX7: 0.059618721 | HY7: 0.018221169 | HZ7: 0.067253186 | IA7: 0.045994736 | IB7: 0.053139216 | IC7: 0.049383865 | ID7: 0.040485001 | IE7: 0.060533744 | IF7: 0.088430732 | IG7: 0.057012944 | IH7: 0.028811245 | II7: 0.098342684 | IJ7: 0.051766724 | IK7: 0.046244584 | IL7: 0.11178976 | IM7: -0.0058199959 | IN7: 0.079078038 | IO7: 0.051644793 | IP7: 0.103256 | IQ7: 0.043043021 | IR7: 0.074682438 | IS7: 0.0035897382 | IT7: 0.08055401 | IU7: 0.013103297 | IV7: 0.11279225 | IW7: 0.064338744 | IX7: 0.039001437 | IY7: 0.060686845 | IZ7: 0.03386523 | JA7: 0.044007865 | JB7: 0.024844149 | JC7: 0.056750347 | JD7: 0.060403849 | JE7: 0.076209835 | JF7: 0.05978417 | JG7: 0.037597403 | JH7: 0.065637579 | JI7: 0.044435366 | JJ7: 0.013687509 | JK7: 0.05508784 | JL7: 0.06990698 | JM7: 0.030282891 | JN7: 0.064039705 | JO7: 0.081160167 | JP7: 0.063067956 | JQ7: 0.055934105 | JR7: 0.05026279 | JS7: 0.07531054 | JT7: 0.13423139 | JU7: 0.071827557 | JV7: 0.07470381 | JW7: 0.03863513 | JX7: 0.10434283 | JY7: 0.024000147 | JZ7: 0.04150256 | KA7: 0.051052674 | KB7: 0.029940535 | KC7: 0.076579065 | KD7: 0.060289368 | KE7: 0.078605873 | KF7: 0.0086851495 | KG7: 0.0426611 | KH7: 0.086594669 | KI7: 0.092046819 | KJ7: 0.030963078 | KK7: 0.067751996 | KL7: 0.053547093 | KM7: 0.13135915 | KN7: 0.099209491 | KO7: 0.070142933 | KP7: 0.062047763 | KQ7: 0.069583961 | KR7: 0.1081409 | KS7: 0.058679347 | KT7: 0.08003231 | KU7: 0.13373267 | KV7: 0.02218815 | KW7: 0.077114802 | KX7: 0.028365694 | KY7: 0.12222582 | KZ7: 0.061582473 | LA7: 0.017914509 | LB7: 0.099343683 | LC7: 0.041602946 | LD7: 0.031885177 | LE7: 0.030570299 | LF7: 0.079916855 | LG7: 0.022806283 | LH7: 0.06430786 | LI7: 0.009882452 | LJ7: 0.042080584 | LK7: 0.022652265 | LL7: 0.058416606 | LM7: 0.069440744 | LN7: 0.063197106 | LO7: 0.041337312 | LP7: 0.05845978 | LQ7: 0.081517364 | LR7: 0.042965955 | LS7: 0.044079888 | LT7: 0.056518977 | LU7: 0.12864826 | LV7: 0.033143387 | LW7: 0.076499248 | LX7: 0.06136219 | LY7: 0.11755602 | LZ7: 0.049491299 | MA7: 0.054517265 | MB7: 0.0087447396 | MC7: 0.055761094 | MD7: 0.025804352 | ME7: 0.095397616 | MF7: 0.061928095 | MG7: 0.0881396 | MH7: 0.0065591584 | MI7: 0.06855586 | MJ7: 0.067128248 | MK7: 0.035773316 | ML7: 0.07039559 | MM7: 0.093453833 | MN7: 0.067591389 | MO7: 0.080056433 | MP7: 0.084702569 | MQ7: 0.063312763 | MR7: 0.056473052 | MS7: 0.063916256 | MT7: 0.12326315 | MU7: 0.097442587 | MV7: 0.0046431077 | MW7: 0.083803447 | MX7: 0.079467866 | MY7: 0.10344119 | MZ7: 0.092995161 | NA7: 0.090150536 | NB7: 0.081987553 | NC7: 0.056704508 | ND7: 0.043457057 | NE7: 0.080298317 | NF7: 0.058990504 | NG7: 0.047149981 | NH7: 0.059924207 | NI7: 0.061941618 | NJ7: 0.049883047 | NK7: 0.066131976 | NL7: 0.090308164 | NM7: 0.080752491 | NN7: 0.020463704 | NO7: 0.047439337 | NP7: 0.080683733 | NQ7: 0.031408112 | NR7: 0.048212633 | NS7: 0.069946916 | NT7: 0.031072001 | NU7: 0.068737409 | NV7: 0.059127304 | NW7: 0.084256503 | NX7: -0.016111663 | NY7: 0.1113041 | NZ7: 0.061727323 | OA7: 0.079972147 | OB7: 0.10890835 | OC7: 0.067671663 | OD7: 0.059094071 | OE7: 0.099118731 | OF7: 0.052787491 | OG7: 0.06768341 | OH7: 0.067808835 | OI7: 0.067554202 | OJ7: 0.086118292 | OK7: 0.034084281 | OL7: 0.044985429 | OM7: 0.079491616 | ON7: 0.05950381 | OO7: 0.11256718 | OP7: 0.0297275 | OQ7: 0.04396661 | OR7: 0.1200109 | OS7: 0.097283127 | OT7: 0.096700519 | OU7: 0.087536479 | OV7: 0.038482774 | OW7: 0.086473312 | OX7: 0.063345537 | OY7: 0.039296294 | OZ7: 0.063046727 | PA7: 0.071654001 | PB7: 0.022910451 | PC7: 0.051726128 | PD7: 0.05346613 | PE7: 0.096878602 | PF7: 0.057855972 | PG7: 0.067321543 | PH7: 0.10082908 | PI7: 0.058273217 | PJ7: 0.0677324 | PK7: 0.068191616 | PL7: 0.080981684 | PM7: 0.05784414 | PN7: 0.099230863 | PO7: 0.045838656 | PP7: 0.058487226 | PQ7: 0.096017811 | PR7: 0.065976784 | PS7: 0.063910469 | PT7: 0.033323246 | PU7: 0.080315306 | PV7: 0.021776864 | PW7: 0.05522782 | PX7: 0.08216363 | PY7: 0.08737106 | PZ7: 0.047687066 | QA7: 0.065324014 | QB7: 0.049170544 | QC7: 0.015238226 | QD7: 0.052623503 | QE7: 0.075996657 | QF7: 0.074541456 | QG7: 0.055867754 | QH7: 0.056702503 | QI7: 0.033284284 | QJ7: 0.068230951 | QK7: 0.038115264 | QL7: 0.06642136 | QM7: 0.056293107 | QN7: 0.028579875 | QO7: 0.027805834 | QP7: 0.042596553 | QQ7: 0.12003566 | QR7: 0.038382789 | QS7: 0.06835884 | QT7: 0.063956766 | QU7: 0.070804154 | QV7: 0.077868789 | QW7: 0.049798704 | QX7: 0.12069206 | QY7: 0.10201023 | QZ7: 0.071592835 | RA7: 0.069524256 | RB7: 0.022896584 | RC7: 0.070221059 | RD7: 0.073344354 | RE7: 0.059961135 | RF7: 0.06804817 | RG7: 0.047940238 | RH7: 0.074218151 | RI7: 0.054410805 | RJ7: 0.032096836 | RK7: 0.05950381 | RL7: 0.027088633 | RM7: 0.080991596 | RN7: 0.11759567 | RO7: 0.091744571 | RP7: 0.090249777 | RQ7: 0.061039229 | RR7: 0.096062905 | RS7: 0.057474825 | RT7: 0.034427267 | RU7: 0.075004167 | RV7: 0.040199943 | RW7: 0.093307665 | RX7: 0.069552103 | RY7: 0.038172161 | RZ7: 0.050394576 | SA7: 0.017188656 | SB7: 0.09736025 | SC7: 0.098439747 | SD7: 0.11440072 | SE7: 0.020118655 | SF7: 0.038563737 | SG7: 0.04315693
A8: 7 | B8: 0.047731329 | C8: 0.075282407 | D8: 0.069885006 | E8: 0.031582471 | F8: 0.023909501 | G8: 0.070255123 | H8: 0.091755515 | I8: 0.055140612 | J8: 0.058404831 | K8: 0.088054856 | L8: 0.075144175 | M8: 0.026216784 | N8: 0.032791061 | O8: 0.10146406 | P8: 0.056032515 | Q8: 0.061686755 | R8: 0.082580761 | S8: 0.10660909 | T8: 0.049551577 | U8: 0.08149731 | V8: 0.032747056 | W8: 0.073273304 | X8: 0.037552138 | Y8: 0.037487333 | Z8: 0.066619726 | AA8: 0.12617664 | AB8: 0.079967334 | AC8: 0.083354343 | AD8: 0.076783734 | AE8: 0.063555678 | AF8: 0.10137273 | AG8: 0.041605754 | AH8: 0.035867285 | AI8: 0.064182434 | AJ8: 0.033597876 | AK8: 0.066077629 | AL8: 0.078619853 | AM8: 0.081329598 | AN8: 0.062880964 | AO8: 0.064126511 | AP8: 0.039671539 | AQ8: 0.060886329 | AR8: -0.011300451 | AS8: 0.019662791 | AT8: 0.091273523 | AU8: 0.051150024 | AV8: 0.056792174 | AW8: 0.079837669 | AX8: 0.081130372 | AY8: 0.065001111 | AZ8: 0.053716982 | BA8: 0.049044316 | BB8: 0.057247093 | BC8: 0.053310165 | BD8: 0.10271969 | BE8: 0.061174624 | BF8: 0.083293321 | BG8: 0.037764771 | BH8: 0.063110357 | BI8: 0.052160649 | BJ8: 0.035877713 | BK8: 0.073474077 | BL8: 0.041128746 | BM8: 0.022868852 | BN8: 0.056086719 | BO8: 0.03977565 | BP8: 0.045010439 | BQ8: 0.099188061 | BR8: 0.055442344 | BS8: 0.070052861 | BT8: 0.039126462 | BU8: 0.0363789 | BV8: 0.065209905 | BW8: 0.022813273 | BX8: 0.026779108 | BY8: 0.084580753 | BZ8: 0.031989173 | CA8: 0.074699541 | CB8: 0.037739101 | CC8: 0.079035723 | CD8: 0.077738808 | CE8: 0.082130397 | CF8: 0.069765281 | CG8: 0.069526233 | CH8: 0.0456549 | CI8: 0.073692326 | CJ8: 0.031855898 | CK8: 0.097879601 | CL8: 0.086042602 | CM8: 0.052577178 | CN8: 0.11165431 | CO8: 0.055440339 | CP8: 0.017320671 | CQ8: 0.06269973 | CR8: 0.042803171 | CS8: 0.04239389 | CT8: 0.014322601 | CU8: 0.094821712 | CV8: 0.06407056 | CW8: 0.084171874 | CX8: 0.068366719 | CY8: 0.074224511 | CZ8: 0.066822161 | DA8: 0.064918 | DB8: 0.10383242 | DC8: 0.063461222 | DD8: 0.061410492 | DE8: 0.093581035 | DF8: 0.061862489 | DG8: 0.052328045 | DH8: 0.1050994 | DI8: 0.085561297 | DJ8: 0.084041348 | DK8: 0.063204813 | DL8: 0.091788519 | DM8: 0.060917298 | DN8: 0.06874334 | DO8: 0.10597698 | DP8: 0.086955992 | DQ8: 0.04337048 | DR8: 0.079242971 | DS8: 0.063544133 | DT8: 0.063625095 | DU8: 0.0393356 | DV8: 0.099484522 | DW8: 0.073168993 | DX8: 0.050033512 | DY8: 0.10904896 | DZ8: 0.0527644 | EA8: 0.023441146 | EB8: 0.021917703 | EC8: 0.035112095 | ED8: 0.075751622 | EE8: 0.035482241 | EF8: 0.053478621 | EG8: 0.088010965 | EH8: 0.037425623 | EI8: 0.090577923 | EJ8: 0.049752063 | EK8: 0.045080429 | EL8: 0.057179682 | EM8: 0.047187741 | EN8: 0.032550065 | EO8: 0.046314632 | EP8: 0.058385178 | EQ8: 0.074334925 | ER8: 0.064508576 | ES8: 0.021702262 | ET8: 0.040490789 | EU8: 0.045610666 | EV8: 0.05074865 | EW8: 0.12579068 | EX8: 0.0989756 | EY8: 0.083516669 | EZ8: 0.11022827 | FA8: 0.053739729 | FB8: 0.034445775 | FC8: 0.059803623 | FD8: 0.084972902 | FE8: 0.067305929 | FF8: 0.095210996 | FG8: 0.042334242 | FH8: 0.061445301 | FI8: 0.050002571 | FJ8: 0.088654481 | FK8: 0.089203111 | FL8: 0.047882309 | FM8: 0.037419091 | FN8: 0.038814302 | FO8: 0.052215798 | FP8: 0.040473427 | FQ8: 0.041987302 | FR8: 0.030073638 | FS8: 0.030260258 | FT8: 0.12562291 | FU8: 0.044716528 | FV8: 0.050939969 | FW8: 0.057141979 | FX8: 0.059499914 | FY8: 0.10063037 | FZ8: 0.066993654 | GA8: 0.041421483 | GB8: 0.084139214 | GC8: 0.08270017 | GD8: 0.014284556 | GE8: 0.061530303 | GF8: 0.080927365 | GG8: 0.11288622 | GH8: 0.079174557 | GI8: 0.08715814 | GJ8: 0.030614877 | GK8: 0.035407983 | GL8: 0.066549679 | GM8: 0.016625988 | GN8: 0.10152514 | GO8: 0.027461415 | GP8: 0.10658365 | GQ8: 0.05049757 | GR8: 0.027398043 | GS8: 0.060574483 | GT8: 0.048729463 | GU8: 0.048217217 | GV8: 0.049787617 | GW8: 0.065215692 | GX8: 0.065264052 | GY8: 0.033513133 | GZ8: 0.11722529 | HA8: 0.088199476 | HB8: 0.060318475 | HC8: 0.11423479 | HD8: 0.023501309 | HE8: 0.029246367 | HF8: 0.01299145 | HG8: 0.035415088 | HH8: 0.066804628 | HI8: 0.0081107927 | HJ8: 0.11902767 | HK8: 0.13023335 | HL8: 0.085141416 | HM8: 0.062888642 | HN8: 0.07177851 | HO8: 0.057946618 | HP8: 0.068266361 | HQ8: 0.07757972 | HR8: 0.059142917 | HS8: 0.056584869 | HT8: 0.034841419 | HU8: 0.0729027 | HV8: 0.078659389 | HW8: 0.073928279 | HX8: 0.066648891 | HY8: 0.072538341 | HZ8: 0.027707339 | IA8: 0.043138422 | IB8: 0.05242528 | IC8: 0.056303106 | ID8: 0.062522306 | IE8: 0.048334392 | IF8: 0.063384099 | IG8: 0.025464803 | IH8: 0.033655461 | II8: 0.08658871 | IJ8: 0.051619124 | IK8: 0.096968216 | IL8: 0.073791222 | IM8: 0.021589613 | IN8: 0.094423261 | IO8: 0.018860845 | IP8: 0.012210133 | IQ8: 0.10551206 | IR8: 0.068154286 | IS8: 0.082271294 | IT8: 0.061634614 | IU8: 0.062128811 | IV8: 0.075412302 | IW8: 0.04641582 | IX8: 0.1075937 | IY8: 0.050440615 | IZ8: 0.048166566 | JA8: 0.069958892 | JB8: 0.072360974 | JC8: 0.078857641 | JD8: 0.064427499 | JE8: 0.063723419 | JF8: 0.057794835 | JG8: 0.085912076 | JH8: 0.0646495 | JI8: 0.053318502 | JJ8: 0.064103363 | JK8: 0.039169034 | JL8: -0.017607833 | JM8: 0.085655724 | JN8: 0.091041637 | JO8: 0.064931522 | JP8: 0.078129897 | JQ8: 0.040815841 | JR8: 0.053441206 | JS8: 0.067989296 | JT8: 0.035584347 | JU8: 0.03165014 | JV8: 0.071574499 | JW8: 0.030574768 | JX8: 0.024477899 | JY8: 0.028850322 | JZ8: 0.076676815 | KA8: 0.10565473 | KB8: 0.093209571 | KC8: 0.069414903 | KD8: 0.086464431 | KE8: 0.10005349 | KF8: 0.033906943 | KG8: 0.10279899 | KH8: 0.10551997 | KI8: 0.11402668 | KJ8: 0.086417274 | KK8: 0.080453968 | KL8: 0.058720487 | KM8: 0.097984284 | KN8: 0.071010198 | KO8: 0.05488658 | KP8: 0.10218155 | KQ8: 0.022475443 | KR8: 0.10702301 | KS8: 0.093260509 | KT8: 0.064728686 | KU8: 0.087761776 | KV8: 0.048159661 | KW8: 0.033643944 | KX8: 0.078953615 | KY8: 0.0028361527 | KZ8: 0.073191941 | LA8: 0.054772528 | LB8: 0.069135059 | LC8: 0.052634046 | LD8: 0.083134777 | LE8: 0.031501852 | LF8: 0.06574994 | LG8: 0.057751431 | LH8: 0.074167241 | LI8: 0.063702218 | LJ8: 0.12848141 | LK8: 0.068577547 | LL8: 0.10570263 | LM8: 0.024250311 | LN8: 0.076935545 | LO8: 0.064722899 | LP8: 0.052871433 | LQ8: 0.12084929 | LR8: 0.065974836 | LS8: 0.0631682 | LT8: 0.098786401 | LU8: 0.0883767 | LV8: 0.092311995 | LW8: 0.0881239 | LX8: 0.094200199 | LY8: 0.12033361 | LZ8: 0.043180766 | MA8: 0.072720262 | MB8: 0.064927654 | MC8: 0.051078659 | MD8: 0.046203473 | ME8: 0.049958336 | MF8: 0.088335445 | MG8: 0.094535737 | MH8: 0.11136369 | MI8: 0.079214608 | MJ8: 0.084749783 | MK8: 0.097144121 | ML8: 0.12048579 | MM8: 0.031590951 | MN8: 0.067650119 | MO8: 0.07282592 | MP8: 0.079221713 | MQ8: 0.080519803 | MR8: 0.068540074 | MS8: 0.081995174 | MT8: 0.078369518 | MU8: 0.037101487 | MV8: 0.12092905 | MW8: 0.078736226 | MX8: 0.060704292 | MY8: 0.077060942 | MZ8: 0.045600811 | NA8: 0.065982571 | NB8: 0.04365296 | NC8: 0.030269369 | ND8: 0.052804279 | NE8: 0.079823287 | NF8: 0.052179729 | NG8: 0.011691699 | NH8: 0.066915671 | NI8: 0.082974399 | NJ8: 0.032461024 | NK8: 0.023367461 | NL8: 0.034012773 | NM8: 0.072685081 | NN8: 0.032285863 | NO8: 0.064367679 | NP8: 0.076714661 | NQ8: 0.12876194 | NR8: 0.087502673 | NS8: 0.098964942 | NT8: 0.036896303 | NU8: 0.068952879 | NV8: 0.068763079 | NW8: 0.026352122 | NX8: 0.053952477 | NY8: 0.049253741 | NZ8: 0.070632833 | OA8: 0.049419705 | OB8: 0.077022839 | OC8: 0.056965215 | OD8: 0.038479623 | OE8: 0.088609559 | OF8: 0.10213697 | OG8: 0.074351913 | OH8: 0.072441335 | OI8: 0.021453473 | OJ8: 0.09311182 | OK8: 0.074851639 | OL8: 0.066718967 | OM8: 0.038967803 | ON8: 0.11481763 | OO8: 0.10322873 | OP8: 0.050933437 | OQ8: 0.066001995 | OR8: 0.10742181 | OS8: 0.06350941 | OT8: 0.071645836 | OU8: 0.023541303 | OV8: 0.069908956 | OW8: 0.046358035 | OX8: 0.072114277 | OY8: 0.058047061 | OZ8: 0.12657911 | PA8: 0.085268446 | PB8: 0.054451773 | PC8: 0.052056595 | PD8: 0.036982536 | PE8: 0.045082893 | PF8: 0.081155211 | PG8: 0.019739799 | PH8: 0.061482 | PI8: 0.052147929 | PJ8: 0.098104668 | PK8: 0.054055499 | PL8: 0.094665632 | PM8: 0.086267382 | PN8: 0.069881023 | PO8: 0.068240778 | PP8: 0.034151778 | PQ8: 0.043459693 | PR8: 0.089042791 | PS8: 0.060638428 | PT8: 0.10087618 | PU8: 0.070919266 | PV8: 0.071725394 | PW8: 0.075105356 | PX8: 0.088379851 | PY8: 0.046140502 | PZ8: 0.059478455 | QA8: 0.093955192 | QB8: 0.037716641 | QC8: 0.1160218 | QD8: 0.080388189 | QE8: 0.08484719 | QF8: 0.078610542 | QG8: 0.075633931 | QH8: 0.039056386 | QI8: 0.061524516 | QJ8: 0.054717465 | QK8: 0.072101958 | QL8: 0.052209438 | QM8: 0.036936125 | QN8: 0.049075887 | QO8: 0.080230447 | QP8: 0.047577426 | QQ8: 0.09104519 | QR8: 0.064690067 | QS8: 0.12853641 | QT8: 0.052871433 | QU8: 0.044108194 | QV8: 0.076732452 | QW8: 0.076225248 | QX8: 0.059912546 | QY8: 0.058127737 | QZ8: 0.029431784 | RA8: 0.020126906 | RB8: 0.071348716 | RC8: 0.020633192 | RD8: 0.048992347 | RE8: 0.067481835 | RF8: 0.078413465 | RG8: 0.076514747 | RH8: 0.065608528 | RI8: 0.094452368 | RJ8: 0.050218785 | RK8: 0.10349654 | RL8: 0.0030378422 | RM8: 0.064388908 | RN8: 0.055751038 | RO8: 0.07014895 | RP8: 0.10537844 | RQ8: 0.10032532 | RR8: 0.047977281 | RS8: 0.0090591919 | RT8: 0.040984126 | RU8: 0.084674837 | RV8: 0.019875596 | RW8: 0.035090608 | RX8: 0.082135497 | RY8: 0.070044896 | RZ8: 0.091715235 | SA8: 0.039911905 | SB8: 0.04933456 | SC8: 0.054330846 | SD8: 0.092844467 | SE8: 0.078813235 | SF8: 0.073379879 | SG8: 0.089430699
A9: 8 | B9: 0.071923674 | C9: 0.091435448 | D9: 0.089144094 | E9: 0.022595884 | F9: 0.10626473 | G9: 0.052892375 | H9: 0.060882461 | I9: 0.030507844 | J9: 0.042006554 | K9: 0.054267245 | L9: 0.064188221 | M9: 0.062819254 | N9: 0.074413595 | O9: 0.12733544 | P9: 0.055043176 | Q9: 0.10489347 | R9: 0.051145698 | S9: 0.076752506 | T9: 0.045779982 | U9: 0.065426549 | V9: 0.053559526 | W9: 0.028330513 | X9: 0.033906943 | Y9: 0.061437566 | Z9: 0.12815503 | AA9: 0.049193034 | AB9: 0.068618974 | AC9: 0.054209746 | AD9: 0.10413954 | AE9: 0.044877593 | AF9: 0.054725601 | AG9: 0.02869344 | AH9: 0.082541913 | AI9: 0.019067806 | AJ9: 0.03230225 | AK9: 0.042687944 | AL9: 0.092610805 | AM9: 0.085390319 | AN9: 0.039677498 | AO9: 0.033064717 | AP9: 0.035272988 | AQ9: 0.044749303 | AR9: 0.10954195 | AS9: 0.077620573 | AT9: 0.11385112 | AU9: 0.021115184 | AV9: 0.071566363 | AW9: 0.10426995 | AX9: 0.11145995 | AY9: 0.10078806 | AZ9: 0.066594429 | BA9: 0.0955816 | BB9: 0.068431695 | BC9: 0.084267447 | BD9: 0.068215223 | BE9: 0.08563567 | BF9: 0.049549342 | BG9: 0.025015127 | BH9: 0.051285992 | BI9: 0.079948082 | BJ9: 0.079110956 | BK9: 0.098398836 | BL9: 0.062655381 | BM9: 0.041675199 | BN9: 0.10676288 | BO9: 0.03153583 | BP9: 0.075418834 | BQ9: 0.059185862 | BR9: 0.064713245 | BS9: 0.047621775 | BT9: 0.059941682 | BU9: 0.092124916 | BV9: 0.068052123 | BW9: 0.056221026 | BX9: 0.032289931 | BY9: 0.041463425 | BZ9: 0.06493539 | CA9: 0.052802188 | CB9: 0.046691596 | CC9: 0.067934347 | CD9: 0.065306596 | CE9: 0.02628451 | CF9: 0.045860658 | CG9: 0.08089035 | CH9: 0.05730654 | CI9: 0.064111069 | CJ9: 0.075200299 | CK9: 0.04697485 | CL9: 0.034892185 | CM9: 0.074084646 | CN9: 0.046456731 | CO9: 0.062082514 | CP9: 0.070335369 | CQ9: 0.10202913 | CR9: 0.086662969 | CS9: 0.019040876 | CT9: 0.090044878 | CU9: 0.047270193 | CV9: 0.043930455 | CW9: 0.022454013 | CX9: 0.042404777 | CY9: 0.015214619 | CZ9: 0.068871774 | DA9: 0.076799319 | DB9: 0.082713177 | DC9: 0.05202044 | DD9: 0.078120729 | DE9: 0.088433883 | DF9: 0.08703724 | DG9: 0.06963573 | DH9: 0.051080808 | DI9: 0.093857957 | DJ9: 0.026536393 | DK9: 0.037337671 | DL9: 0.062096008 | DM9: 0.092229486 | DN9: 0.08260666 | DO9: 0.071170175 | DP9: 0.06361544 | DQ9: 0.08900039 | DR9: 0.072823857 | DS9: 0.097696705 | DT9: 0.040548602 | DU9: 0.059037403 | DV9: 0.043876193 | DW9: 0.069528239 | DX9: 0.07611303 | DY9: 0.092500678 | DZ9: 0.10203544 | EA9: 0.055183213 | EB9: 0.056514994 | EC9: 0.048178082 | ED9: 0.064053198 | EE9: 0.067155579 | EF9: 0.059002222 | EG9: 0.0532706 | EH9: 0.082765261 | EI9: 0.041255776 | EJ9: 0.070644923 | EK9: 0.061893373 | EL9: 0.074110058 | EM9: 0.077509443 | EN9: 0.05696722 | EO9: 0.053781098 | EP9: 0.059755005 | EQ9: 0.090491117 | ER9: 0.060454272 | ES9: 0.099070829 | ET9: 0.1006479 | EU9: 0.074742343 | EV9: 0.073064853 | EW9: 0.0095152853 | EX9: 0.082092065 | EY9: 0.048654345 | EZ9: 0.1017784 | FA9: 0.055292624 | FB9: 0.062915658 | FC9: 0.054464035 | FD9: 0.10959433 | FE9: 0.055343247 | FF9: 0.059947527 | FG9: 0.10540973 | FH9: 0.097603423 | FI9: 0.044562282 | FJ9: 0.051751769 | FK9: 0.06301974 | FL9: 0.053586514 | FM9: 0.10321521 | FN9: 0.056409107 | FO9: 0.082982249 | FP9: 0.071578596 | FQ9: 0.087647351 | FR9: 0.03304896 | FS9: 0.07816439 | FT9: 0.07246815 | FU9: 0.088725187 | FV9: 0.049078151 | FW9: 0.065610477 | FX9: 0.056285085 | FY9: 0.06187985 | FZ9: 0.055393812 | GA9: 0.055304771 | GB9: 0.046531161 | GC9: 0.070659018 | GD9: 0.042928654 | GE9: 0.095564067 | GF9: 0.054711334 | GG9: 0.12141815 | GH9: 0.072461962 | GI9: 0.089700631 | GJ9: 0.015792643 | GK9: 0.070546312 | GL9: 0.057731692 | GM9: 0.038881971 | GN9: 0.064288551 | GO9: 0.1039602 | GP9: 0.083884352 | GQ9: 0.070650968 | GR9: 0.04551707 | GS9: 0.021107392 | GT9: 0.043333694 | GU9: 0.067219982 | GV9: 0.072075314 | GW9: 0.065653106 | GX9: 0.064690067 | GY9: 0.086704625 | GZ9: 0.076141593 | HA9: 0.071970774 | HB9: 0.009174705 | HC9: 0.040438647 | HD9: 0.065951573 | HE9: 0.0155183 | HF9: 0.09804439 | HG9: 0.068751218 | HH9: 0.11373538 | HI9: 0.0955816 | HJ9: 0.05992031 | HK9: 0.06684359 | HL9: 0.054523396 | HM9: 0.09027728 | HN9: 0.037790441 | HO9: 0.088472101 | HP9: 0.085079534 | HQ9: 0.025891101 | HR9: 0.072410422 | HS9: 0.088721978 | HT9: 0.11310349 | HU9: 0.054519299 | HV9: 0.054039026 | HW9: 0.090356351 | HX9: 0.065401396 | HY9: 0.070556368 | HZ9: 0.071147886 | IA9: 0.072654054 | IB9: 0.065856544 | IC9: 0.035158736 | ID9: 0.064655316 | IE9: 0.054915086 | IF9: 0.08014089 | IG9: 0.057668521 | IH9: 0.087185413 | II9: 0.060064129 | IJ9: 0.041783321 | IK9: 0.10852422 | IL9: 0.071123563 | IM9: 0.051749649 | IN9: 0.010854229 | IO9: 0.065070671 | IP9: 0.080595551 | IQ9: 0.076168007 | IR9: 0.089098313 | IS9: 0.061729242 | IT9: 0.085147031 | IU9: 0.047131073 | IV9: 0.080485653 | IW9: 0.071478811 | IX9: 0.078134509 | IY9: 0.06111661 | IZ9: 0.029815796 | JA9: 0.051992765 | JB9: 0.079014609 | JC9: 0.05158698 | JD9: 0.04141306 | JE9: 0.0041443844 | JF9: 0.082557441 | JG9: 0.084774822 | JH9: 0.048361895 | JI9: 0.024433894 | JJ9: 0.014794509 | JK9: 0.092035703 | JL9: 0.064632139 | JM9: 0.047420601 | JN9: 0.076955685 | JO9: 0.072958794 | JP9: 0.074443419 | JQ9: 0.068309621 | JR9: 0.090133461 | JS9: 0.081317107 | JT9: 0.031755397 | JU9: 0.067646223 | JV9: 0.040220399 | JW9: 0.05795845 | JX9: 0.081519885 | JY9: 0.045588492 | JZ9: 0.073019072 | KA9: 0.042096999 | KB9: 0.089797981 | KC9: 0.068670285 | KD9: 0.014398235 | KE9: 0.039561011 | KF9: 0.076410694 | KG9: 0.068697931 | KH9: 0.099236192 | KI9: 0.046810834 | KJ9: 0.07724974 | KK9: -0.011934856 | KL9: 0.07096373 | KM9: 0.060973451 | KN9: 0.085489903 | KO9: 0.074834479 | KP9: 0.044688767 | KQ9: 0.1375501 | KR9: 0.047568086 | KS9: 0.075686187 | KT9: 0.05753811 | KU9: 0.080271645 | KV9: 0.051128422 | KW9: 0.028082871 | KX9: 0.046875122 | KY9: 0.044982908 | KZ9: 0.063077582 | LA9: 0.062871309 | LB9: 0.06683385 | LC9: 0.061725374 | LD9: 0.031240802 | LE9: 0.060694609 | LF9: 0.012606865 | LG9: 0.096130631 | LH9: 0.071328404 | LI9: 0.072260158 | LJ9: 0.076683519 | LK9: 0.081063391 | LL9: 0.073772285 | LM9: 0.084054928 | LN9: 0.042429128 | LO9: 0.02666921 | LP9: 0.032650795 | LQ9: 0.081524928 | LR9: 0.091854641 | LS9: 0.077351157 | LT9: 0.036053962 | LU9: 0.045277076 | LV9: 0.070277183 | LW9: 0.067499425 | LX9: 0.081522407 | LY9: 0.068836191 | LZ9: 0.062105662 | MA9: 0.05513047 | MB9: 0.063767768 | MC9: 0.068148384 | MD9: 0.080034717 | ME9: 0.044103037 | MF9: 0.11801922 | MG9: 0.040427073 | MH9: 0.06299662 | MI9: 0.048969771 | MJ9: 0.091446277 | MK9: 0.05295314 | ML9: 0.065533009 | MM9: 0.081987553 | MN9: 0.033338831 | MO9: 0.095198046 | MP9: 0.075549073 | MQ9: 0.074879544 | MR9: 0.092353364 | MS9: 0.064464169 | MT9: 0.036033335 | MU9: 0.052442183 | MV9: 0.10553578 | MW9: 0.093692938 | MX9: 0.017787995 | MY9: 0.049134503 | MZ9: 0.049491299 | NA9: 0.0967145 | NB9: 0.099001957 | NC9: 0.067032674 | ND9: 0.052319594 | NE9: 0.047782496 | NF9: 0.045853324 | NG9: 0.084475955 | NH9: 0.073778617 | NI9: 0.028535297 | NJ9: 0.06497017 | NK9: 0.055166969 | NL9: 0.093967396 | NM9: 0.098656334 | NN9: 0.056359115 | NO9: 0.097716415 | NP9: 0.032277669 | NQ9: -0.0017018621 | NR9: 0.029848227 | NS9: 0.054236447 | NT9: 0.09673782 | NU9: 0.09163135 | NV9: 0.075930908 | NW9: 0.017491648 | NX9: 0.047614784 | NY9: 0.044356409 | NZ9: 0.067863727 | OA9: 0.081175122 | OB9: 0.05147754 | OC9: 0.053571989 | OD9: 0.056554931 | OE9: 0.068830261 | OF9: 0.052062955 | OG9: 0.080806581 | OH9: 0.042415606 | OI9: 0.032497523 | OJ9: 0.08552984 | OK9: 0.060064129 | OL9: 0.084836074 | OM9: 0.10907933 | ON9: 0.043712836 | OO9: 0.064701642 | OP9: 0.028184346 | OQ9: 0.062310159 | OR9: 0.024459105 | OS9: 0.056684568 | OT9: 0.058186754 | OU9: 0.028923435 | OV9: 0.095656604 | OW9: 0.061472346 | OX9: 0.091493319 | OY9: 0.055801374 | OZ9: 0.032030657 | PA9: 0.061684836 | PB9: 0.04331788 | PC9: 0.069182645 | PD9: 0.084079366 | PE9: 0.04948683 | PF9: 0.071423891 | PG9: 0.044832385 | PH9: 0.087582604 | PI9: 0.066641099 | PJ9: 0.01068646 | PK9: 0.073993714 | PL9: 0.052793794 | PM9: 0.081284676 | PN9: 0.082454017 | PO9: 0.063977966 | PP9: 0.068309621 | PQ9: 0.04622284 | PR9: 0.020697366 | PS9: 0.060746894 | PT9: 0.073175267 | PU9: 0.0781943 | PV9: 0.039731072 | PW9: 0.063993408 | PX9: 0.093942987 | PY9: 0.077455125 | PZ9: 0.065567875 | QA9: 0.040528376 | QB9: 0.053428743 | QC9: 0.074639665 | QD9: 0.051847858 | QE9: 0.077290278 | QF9: 0.054100765 | QG9: 0.018878952 | QH9: 0.065091928 | QI9: 0.082286707 | QJ9: 0.060052468 | QK9: 0.1419836 | QL9: 0.077110333 | QM9: 0.082728791 | QN9: 0.072268352 | QO9: 0.049776529 | QP9: 0.08023526 | QQ9: 0.044559761 | QR9: 0.059856136 | QS9: 0.08522318 | QT9: 0.045526954 | QU9: 0.04290201 | QV9: 0.066038838 | QW9: 0.04174453 | QX9: 0.071989195 | QY9: 0.065459467 | QZ9: 0.061327381 | RA9: 0.058113986 | RB9: 0.089835053 | RC9: 0.067413392 | RD9: 0.04882028 | RE9: 0.05503504 | RF9: 0.061901079 | RG9: 0.045701541 | RH9: 0.069051862 | RI9: 0.059928103 | RJ9: 0.042456173 | RK9: 0.054762329 | RL9: 0.087675141 | RM9: 0.049327827 | RN9: 0.076104235 | RO9: 0.073354782 | RP9: 0.046273606 | RQ9: 0.065275655 | RR9: 0.063513249 | RS9: 0.069269939 | RT9: 0.05832235 | RU9: 0.083258942 | RV9: 0.043723207 | RW9: 0.07262509 | RX9: 0.084866729 | RY9: 0.075211071 | RZ9: 0.061860541 | SA9: 0.085245813 | SB9: 0.036473786 | SC9: 0.044192823 | SD9: 0.013674215 | SE9: 0.029981961 | SF9: 0.042488661 | SG9: 0.046401381
A10: 9 | B10: 0.059797807 | C10: 0.097825053 | D10: 0.076038342 | E10: 0.048865632 | F10: 0.081484762 | G10: 0.10709303 | H10: 0.084270197 | I10: 0.065411079 | J10: 0.065033942 | K10: 0.065556272 | L10: 0.04525473 | M10: 0.054703169 | N10: 0.066462185 | O10: 0.11033851 | P10: 0.046208286 | Q10: 0.12035882 | R10: 0.11623174 | S10: 0.012475996 | T10: 0.056409107 | U10: 0.072054801 | V10: 0.087851848 | W10: 0.10148847 | X10: 0.069460627 | Y10: 0.028098112 | Z10: 0.073089835 | AA10: 0.025816041 | AB10: 0.053428743 | AC10: 0.074605486 | AD10: 0.059431672 | AE10: 0.076128414 | AF10: 0.058567644 | AG10: 0.081706162 | AH10: 0.066956611 | AI10: 0.11679166 | AJ10: 0.030685869 | AK10: 0.081504816 | AL10: 0.076201011 | AM10: 0.075017059 | AN10: 0.039096037 | AO10: 0.068518416 | AP10: 0.069683517 | AQ10: 0.06669367 | AR10: 0.084989748 | AS10: 0.085655724 | AT10: 0.077716032 | AU10: 0.03130532 | AV10: 0.065167333 | AW10: 0.054562244 | AX10: 0.05621501 | AY10: 0.067243417 | AZ10: 0.049654169 | BA10: 0.091356147 | BB10: 0.083506012 | BC10: 0.082430812 | BD10: 0.019773834 | BE10: 0.070020888 | BF10: 0.04266915 | BG10: 0.096381311 | BH10: 0.073595721 | BI10: 0.049347996 | BJ10: 0.094792146 | BK10: 0.066980017 | BL10: 0.078932529 | BM10: 0.058224113 | BN10: 0.028365694 | BO10: 0.053536722 | BP10: -0.0030082603 | BQ10: 0.065742205 | BR10: 0.053760414 | BS10: 0.057694191 | BT10: 0.10164822 | BU10: 0.036989183 | BV10: 0.0024199388 | BW10: 0.098099625 | BX10: 0.050394576 | BY10: 0.068099251 | BZ10: 0.069319559 | CA10: 0.031227852 | CB10: 0.042746961 | CC10: 0.067771591 | CD10: 0.047064894 | CE10: 0.092629885 | CF10: 0.057008962 | CG10: 0.096244196 | CH10: 0.022475443 | CI10: 0.063513249 | CJ10: 0.055855693 | CK10: 0.081469692 | CL10: 0.091540418 | CM10: 0.056343128 | CN10: 0.03224902 | CO10: 0.044420068 | CP10: 0.04015313 | CQ10: 0.06686502 | CR10: 0.08065921 | CS10: 0.067738273 | CT10: 0.041080616 | CU10: 0.080524674 | CV10: 0.060192305 | CW10: 0.079092162 | CX10: 0.069542162 | CY10: 0.086349548 | CZ10: 0.054332908 | DA10: 0.075900253 | DB10: 0.070554363 | DC10: 0.048007334 | DD10: 0.017270019 | DE10: 0.0080475355 | DF10: 0.054770466 | DG10: 0.074224511 | DH10: 0.05862646 | DI10: 0.05806872 | DJ10: 0.057116195 | DK10: 0.082770475 | DL10: 0.064603175 | DM10: 0.068337182 | DN10: 0.05543226 | DO10: 0.032166855 | DP10: 0.0963035 | DQ10: 0.11193897 | DR10: 0.072616839 | DS10: 0.080838553 | DT10: 0.047131073 | DU10: 0.020151888 | DV10: 0.091551305 | DW10: 0.043754378 | DX10: 0.037561821 | DY10: 0.062169321 | DZ10: 0.052213678 | EA10: 0.028835654 | EB10: 0.0082153045 | EC10: 0.093926772 | ED10: 0.027254683 | EE10: 0.043824396 | EF10: 0.079541552 | EG10: 0.068425793 | EH10: 0.067624679 | EI10: 0.058828179 | EJ10: 0.086387823 | EK10: 0.093749205 | EL10: -0.014395469 | EM10: 0.038235189 | EN10: 0.054609229 | EO10: 0.071358858 | EP10: 0.097731141 | EQ10: 0.04563032 | ER10: 0.12216577 | ES10: 0.035237349 | ET10: 0.050126249 | EU10: 0.045110339 | EV10: 0.09739417 | EW10: 0.066380564 | EX10: 0.086671907 | EY10: 0.055944161 | EZ10: 0.043005834 | FA10: 0.076670169 | FB10: 0.051285992 | FC10: 0.078829593 | FD10: 0.071064861 | FE10: 0.052150049 | FF10: 0.045502258 | FG10: 0.056586875 | FH10: 0.083819605 | FI10: 0.10241922 | FJ10: 0.043027092 | FK10: 0.068857936 | FL10: 0.056778222 | FM10: 0.029507303 | FN10: 0.050101983 | FO10: 0.053729415 | FP10: 0.014806656 | FQ10: 0.054441517 | FR10: 0.045195054 | FS10: 0.069043926 | FT10: 0.044789612 | FU10: 0.086276149 | FV10: 0.038700164 | FW10: 0.056188939 | FX10: 0.074690975 | FY10: 0.042730889 | FZ10: 0.035710517 | GA10: 0.041074943 | GB10: 0.080020278 | GC10: 0.07810692 | GD10: 0.11243631 | GE10: 0.086282051 | GF10: 0.068591356 | GG10: 0.068195541 | GH10: 0.073709171 | GI10: 0.10170391 | GJ10: 0.093288069 | GK10: 0.041108921 | GL10: 0.10123968 | GM10: 0.094093681 | GN10: 0.058296824 | GO10: 0.045267164 | GP10: 0.042886024 | GQ10: 0.066711174 | GR10: 0.075878365 | GS10: 0.056704508 | GT10: 0.064516311 | GU10: 0.038127927 | GV10: 0.06602331 | GW10: 0.01105271 | GX10: 0.069898986 | GY10: 0.071666234 | GZ10: 0.047399458 | HA10: 0.065111295 | HB10: 0.085561297 | HC10: 0.063673283 | HD10: 0.11405625 | HE10: 0.089977037 | HF10: 0.11669953 | HG10: 0.10020018 | HH10: 0.082940307 | HI10: 0.071204611 | HJ10: 0.10415398 | HK10: 0.080664137 | HL10: 0.065674393 | HM10: 0.059813363 | HN10: 0.086016474 | HO10: 0.052200958 | HP10: 0.075933085 | HQ10: 0.021192652 | HR10: 0.076926607 | HS10: 0.10003115 | HT10: 0.02570557 | HU10: 0.065564008 | HV10: 0.0239354 | HW10: 0.057344185 | HX10: 0.0034302201 | HY10: 0.069022153 | HZ10: 0.043629525 | IA10: 0.034315994 | IB10: 0.084041348 | IC10: 0.087601112 | ID10: 0.057530203 | IE10: 0.070036874 | IF10: 0.079082737 | IG10: 0.041547252 | IH10: 0.083749644 | II10: 0.017106834 | IJ10: 0.087091616 | IK10: 0.065345301 | IL10: 0.077616047 | IM10: 0.025792778 | IN10: 0.058286997 | IO10: 0.049591743 | IP10: 0.092323283 | IQ10: 0.021138448 | IR10: 0.081272185 | IS10: 0.062651513 | IT10: 0.062175108 | IU10: 0.026120294 | IV10: 0.088010965 | IW10: 0.083843899 | IX10: 0.035577356 | IY10: 0.015367262 | IZ10: 0.058528423 | JA10: 0.13423139 | JB10: 0.065033942 | JC10: 0.029502605 | JD10: 0.081625486 | JE10: 0.073742805 | JF10: 0.07414819 | JG10: 0.0752219 | JH10: 0.079070962 | JI10: 0.041427098 | JJ10: 0.079811311 | JK10: 0.063227962 | JL10: 0.10364953 | JM10: 0.038010637 | JN10: 0.05167052 | JO10: 0.067329364 | JP10: 0.075605626 | JQ10: 0.031688071 | JR10: 0.13222 | JS10: 0.092983529 | JT10: 0.031032867 | JU10: 0.074875246 | JV10: 0.039401894 | JW10: 0.076801553 | JX10: 0.061771729 | JY10: 0.050194577 | JZ10: 0.036047087 | KA10: 0.10904896 | KB10: 0.035305075 | KC10: 0.04417231 | KD10: 0.028042074 | KE10: 0.091151936 | KF10: 0.078251856 | KG10: 0.040666751 | KH10: 0.038989233 | KI10: 0.042228126 | KJ10: 0.058064766 | KK10: 0.063796703 | KL10: 0.058283072 | KM10: 0.058137592 | KN10: 0.089245798 | KO10: 0.094560776 | KP10: 0.061775596 | KQ10: 0.10492384 | KR10: 0.044465849 | KS10: 0.0743838 | KT10: 0.096235086 | KU10: 0.089727447 | KV10: 0.066524411 | KW10: 0.088338596 | KX10: 0.047404156 | KY10: 0.049585068 | KZ10: 0.048804409 | LA10: 0.071423891 | LB10: 0.065206009 | LC10: 0.094834432 | LD10: 0.058918165 | LE10: 0.092523368 | LF10: 0.021483726 | LG10: 0.062136517 | LH10: 0.058881007 | LI10: 0.020617149 | LJ10: 0.075120454 | LK10: 0.047817333 | LL10: 0.07808168 | LM10: 0.026817383 | LN10: 0.050628725 | LO10: -0.021348257 | LP10: 0.059745264 | LQ10: 0.10199132 | LR10: 0.051264448 | LS10: 0.028042074 | LT10: 0.037503549 | LU10: 0.03500065 | LV10: 0.046967716 | LW10: 0.046516779 | LX10: 0.10437939 | LY10: 0.09404876 | LZ10: 0.051216977 | MA10: 0.085155511 | MB10: 0.10331754 | MC10: 0.057820476 | MD10: 0.079706055 | ME10: 0.09444406 | MF10: 0.061242322 | MG10: 0.095656604 | MH10: 0.10030813 | MI10: 0.1024128 | MJ10: 0.097168015 | MK10: 0.070786019 | ML10: 0.046276013 | MM10: 0.079938456 | MN10: 0.070311275 | MO10: 0.090946064 | MP10: 0.054086383 | MQ10: 0.04448619 | MR10: 0.077144024 | MS10: 0.019968304 | MT10: 0.024708467 | MU10: 0.056568883 | MV10: 0.054111078 | MW10: 0.07355375 | MX10: 0.061311911 | MY10: 0.067466192 | MZ10: 0.041766704 | NA10: 0.064097576 | NB10: 0.064767305 | NC10: 0.054203586 | ND10: 0.063341698 | NE10: 0.092296926 | NF10: 0.071030453 | NG10: 0.062763331 | NH10: 0.098630378 | NI10: 0.097307192 | NJ10: 0.059086278 | NK10: 0.097904468 | NL10: 0.040594785 | NM10: 0.038376486 | NN10: 0.071105342 | NO10: 0.051307565 | NP10: 0.078418106 | NQ10: 0.05235764 | NR10: 0.067648171 | NS10: 0.065459467 | NT10: 0.068477018 | NU10: 0.041808188 | NV10: 0.085762012 | NW10: 0.093236959 | NX10: 0.063738832 | NY10: 0.092455183 | NZ10: 0.051790245 | OA10: 0.10693569 | OB10: 0.076745831 | OC10: 0.049305367 | OD10: 0.048295372 | OE10: 0.10125171 | OF10: 0.023889905 | OG10: 0.022518073 | OH10: 0.062360295 | OI10: 0.092618483 | OJ10: 0.051111118 | OK10: 0.069548121 | OL10: 0.038379638 | OM10: 0.034743152 | ON10: 0.025458844 | OO10: 0.08616499 | OP10: 0.034088005 | OQ10: 0.047069592 | OR10: 0.12300187 | OS10: 0.11610867 | OT10: 0.037160734 | OU10: 0.073966268 | OV10: 0.044169789 | OW10: 0.045272091 | OX10: 0.07030927 | OY10: 0.048958455 | OZ10: 0.049262737 | PA10: 0.061176573 | PB10: 0.016899873 | PC10: 0.065304676 | PD10: 0.061369897 | PE10: 0.081663303 | PF10: 0.081819956 | PG10: 0.097398983 | PH10: 0.023387515 | PI10: 0.053874065 | PJ10: 0.057968305 | PK10: 0.056578882 | PL10: 0.053503517 | PM10: 0.03883894 | PN10: 0.036071209 | PO10: 0.026307086 | PP10: 0.089059121 | PQ10: 0.1014518 | PR10: 0.067169216 | PS10: 0.030069054 | PT10: 0.063432287 | PU10: 0.016138724 | PV10: 0.055237961 | PW10: 0.062026534 | PX10: 0.061875983 | PY10: 0.087976587 | PZ10: 0.05225181 | QA10: 0.081997752 | QB10: 0.048631597 | QC10: 0.10575879 | QD10: 0.080999016 | QE10: 0.02934641 | QF10: 0.076890824 | QG10: -0.0062398768 | QH10: 0.048437471 | QI10: 0.071833688 | QJ10: 0.062034269 | QK10: 0.050985521 | QL10: 0.089714039 | QM10: 0.035881151 | QN10: 0.013089316 | QO10: 0.048831625 | QP10: 0.089570278 | QQ10: 0.051576236 | QR10: 0.043032421 | QS10: 0.074954719 | QT10: 0.047284346 | QU10: 0.090449575 | QV10: 0.068759125 | QW10: 0.0739726 | QX10: 0.078506088 | QY10: 0.098828344 | QZ10: 0.092740757 | RA10: 0.089222822 | RB10: 0.065610477 | RC10: 0.083177006 | RD10: 0.047819682 | RE10: 0.032404184 | RF10: 0.047579746 | RG10: 0.068690024 | RH10: 0.050273792 | RI10: 0.063765848 | RJ10: 0.040513937 | RK10: 0.076038342 | RL10: 0.087979681 | RM10: 0.018306314 | RN10: 0.030690281 | RO10: 0.084155544 | RP10: 0.10601777 | RQ10: 0.064386989 | RR10: 0.085670049 | RS10: 0.039716232 | RT10: 0.045519534 | RU10: 0.057638898 | RV10: 0.086479214 | RW10: 0.045234848 | RX10: 0.051214828 | RY10: 0.086458529 | RZ10: 0.057694191 | SA10: 0.086328978 | SB10: 0.023068823 | SC10: 0.061758206 | SD10: 0.088886711 | SE10: 0.0499871 | SF10: 0.055193355 | SG10: 0.11533079
A11: 10 | B11: 0.079292562 | C11: 0.01918332 | D11: 0.011456089 | E11: 0.029746122 | F11: 0.052800096 | G11: 0.04299787 | H11: 0.044663528 | I11: 0.052528704 | J11: 0.087410767 | K11: 0.063584585 | L11: 0.077791207 | M11: 0.077317351 | N11: 0.051346327 | O11: 0.083564742 | P11: 0.088149054 | Q11: 0.083787288 | R11: 0.074224511 | S11: 0.043378358 | T11: 0.055535282 | U11: 0.11684759 | V11: 0.089331516 | W11: 0.086767251 | X11: 0.091682345 | Y11: 0.044678654 | Z11: 0.10021152 | AA11: 0.040660964 | AB11: 0.084830459 | AC11: 0.10872981 | AD11: 0.055757083 | AE11: 0.027179852 | AF11: 0.076674609 | AG11: 0.065684076 | AH11: 0.0936369 | AI11: 0.081502295 | AJ11: 0.057561832 | AK11: 0.11340855 | AL11: 0.043053621 | AM11: 0.096626031 | AN11: 0.065262104 | AO11: 0.048182695 | AP11: 0.058924038 | AQ11: 0.068569669 | AR11: 0.058017524 | AS11: 0.026882818 | AT11: 0.021544348 | AU11: 0.065608528 | AV11: 0.070245125 | AW11: 0.10548834 | AX11: 0.043728421 | AY11: 0.032195676 | AZ11: 0.036081523 | BA11: 0.036524495 | BB11: 0.079415668 | BC11: 0.098959671 | BD11: 0.070120931 | BE11: 0.10472765 | BF11: 0.1005262 | BG11: 0.088670525 | BH11: 0.057950571 | BI11: 0.071425925 | BJ11: 0.029601272 | BK11: 0.046420633 | BL11: 0.031947632 | BM11: 0.02034143 | BN11: 0.074477482 | BO11: 0.036133034 | BP11: 0.038269797 | BQ11: 0.091180528 | BR11: 0.087103706 | BS11: 0.029605971 | BT11: 0.042880695 | BU11: 0.067908821 | BV11: 0.063069876 | BW11: 0.072678864 | BX11: 0.017709611 | BY11: 0.027471958 | BZ11: 0.074907448 | CA11: 0.03362091 | CB11: 0.048355019 | CC11: 0.043958875 | CD11: 0.021060637 | CE11: 0.054322652 | CF11: 0.046550356 | CG11: 0.10523829 | CH11: 0.068105153 | CI11: 0.064655316 | CJ11: 0.084073951 | CK11: 0.058681323 | CL11: 0.051428092 | CM11: 0.052863038 | CN11: 0.063750406 | CO11: 0.092031979 | CP11: 0.13833486 | CQ11: 0.11964969 | CR11: 0.05428366 | CS11: 0.058277171 | CT11: 0.067601187 | CU11: -0.02316713 | CV11: 0.0095895438 | CW11: 0.081774404 | CX11: 0.057816551 | CY11: 0.052444275 | CZ11: 0.084027769 | DA11: 0.093335283 | DB11: 0.051397982 | DC11: 0.025256467 | DD11: 0.076410694 | DE11: 0.068419892 | DF11: 0.092717723 | DG11: 0.08211762 | DH11: 0.055674459 | DI11: 0.044574945 | DJ11: 0.064072479 | DK11: 0.035658032 | DL11: 0.062184762 | DM11: 0.054623553 | DN11: 0.078487552 | DO11: 0.082549705 | DP11: 0.044832385 | DQ11: 0.064622484 | DR11: 0.082687164 | DS11: 0.09253477 | DT11: 0.0781943 | DU11: 0.0082982723 | DV11: 0.057956473 | DW11: 0.069267933 | DX11: 0.082010472 | DY11: -0.00074108641 | DZ11: 0.087182377 | EA11: 0.087582604 | EB11: 0.080703387 | EC11: 0.069573991 | ED11: 0.061910734 | EE11: 0.054627621 | EF11: 0.053723198 | EG11: 0.047329038 | EH11: 0.11124451 | EI11: 0.091873034 | EJ11: 0.067840177 | EK11: 0.053648682 | EL11: 0.06976127 | EM11: 0.09422902 | EN11: 0.12953019 | EO11: 0.005283472 | EP11: 0.081274707 | EQ11: 0.0464086 | ER11: 0.07113975 | ES11: 0.046653321 | ET11: 0.088275282 | EU11: 0.13010226 | EV11: 0.046036105 | EW11: 0.062772985 | EX11: 0.082253302 | EY11: 0.050874821 | EZ11: 0.079458355 | FA11: 0.04774296 | FB11: 0.10267362 | FC11: 0.06616498 | FD11: 0.039769748 | FE11: 0.06523695 | FF11: 0.062393099 | FG11: 0.083285414 | FH11: 0.041074943 | FI11: 0.039962098 | FJ11: 0.085274061 | FK11: 0.02649743 | FL11: 0.061816135 | FM11: 0.040147286 | FN11: 0.050589418 | FO11: 0.080300752 | FP11: 0.089049323 | FQ11: 0.024256728 | FR11: 0.028275278 | FS11: 0.012074909 | FT11: 0.077898469 | FU11: 0.0010227803 | FV11: 0.077962529 | FW11: 0.040447357 | FX11: 0.063137344 | FY11: 0.056345134 | FZ11: 0.08853278 | GA11: 0.072101958 | GB11: 0.076519188 | GC11: 0.00387027 | GD11: 0.066380564 | GE11: 0.037991557 | GF11: 0.047486207 | GG11: 0.081357044 | GH11: 0.059661552 | GI11: 0.061284866 | GJ11: 0.10281893 | GK11: 0.036769674 | GL11: 0.054076069 | GM11: 0.073943034 | GN11: 0.038004277 | GO11: 0.044703923 | GP11: 0.061595995 | GQ11: 0.062776853 | GR11: 0.049692015 | GS11: 0.063366738 | GT11: 0.10915015 | GU11: 0.020423023 | GV11: 0.079974554 | GW11: 0.049019477 | GX11: 0.087715307 | GY11: 0.091587632 | GZ11: 0.075677478 | HA11: 0.025220484 | HB11: 0.029862093 | HC11: 0.024116119 | HD11: 0.10942747 | HE11: 0.060539589 | HF11: 0.10362156 | HG11: 0.051709025 | HH11: 0.11824749 | HI11: 0.036544721 | HJ11: 0.035043853 | HK11: 0.068709763 | HL11: 0.019438182 | HM11: 0.065088089 | HN11: 0.028036918 | HO11: 0.036779701 | HP11: 0.11034974 | HQ11: 0.056907573 | HR11: 0.019227668 | HS11: 0.099642837 | HT11: 0.065403344 | HU11: 0.056331096 | HV11: 0.086836009 | HW11: 0.08688689 | HX11: 0.060956032 | HY11: 0.063796703 | HZ11: 0.054256988 | IA11: 0.080300752 | IB11: 0.064921867 | IC11: 0.064086002 | ID11: 0.073196095 | IE11: 0.049891899 | IF11: 0.06764035 | IG11: 0.059536928 | IH11: 0.05462149 | II11: 0.0743838 | IJ11: 0.097721286 | IK11: 0.018287405 | IL11: 0.07227454 | IM11: 0.087258297 | IN11: 0.01299145 | IO11: 0.055591778 | IP11: 0.051994885 | IQ11: 0.058283072 | IR11: 0.087814547 | IS11: 0.063451568 | IT11: 0.049258239 | IU11: 0.06440627 | IV11: 0.075625222 | IW11: 0.046386942 | IX11: 0.097148934 | IY11: 0.07536463 | IZ11: 0.043904613 | JA11: 0.042072333 | JB11: 0.062902164 | JC11: 0.058473503 | JD11: 0.039395878 | JE11: 0.093374704 | JF11: 0.075933085 | JG11: 0.06479435 | JH11: 0.061557348 | JI11: 0.035237349 | JJ11: 0.070822318 | JK11: 0.051779559 | JL11: 0.066824109 | JM11: 0.084063064 | JN11: 0.085444351 | JO11: 0.060651979 | JP11: 0.047147604 | JQ11: 0.071129636 | JR11: 0.076437252 | JS11: 0.029049376 | JT11: 0.047668415 | JU11: 0.069916949 | JV11: 0.078517691 | JW11: 0.03703548 | JX11: 0.060141825 | JY11: 0.065146075 | JZ11: 0.083346379 | KA11: 0.075070891 | KB11: 0.024689902 | KC11: 0.024714655 | KD11: 0.03476143 | KE11: 0.077518525 | KF11: 0.037594194 | KG11: 0.031189004 | KH11: 0.056566906 | KI11: 0.084503515 | KJ11: 0.035940054 | KK11: 0.077713769 | KL11: 0.10271304 | KM11: 0.074804483 | KN11: 0.096253307 | KO11: 0.059564202 | KP11: 0.02899139 | KQ11: 0.034027842 | KR11: 0.055452457 | KS11: 0.041471848 | KT11: 0.061719587 | KU11: 0.064800166 | KV11: 0.10714586 | KW11: 0.070566424 | KX11: 0.039997451 | KY11: 0.040612032 | KZ11: 0.077000435 | LA11: 0.032216246 | LB11: 0.076592415 | LC11: 0.096422623 | LD11: 0.078088585 | LE11: 0.054197427 | LF11: 0.067930422 | LG11: 0.093557141 | LH11: 0.06864069 | LI11: 0.069871025 | LJ11: 0.072021998 | LK11: 0.059589528 | LL11: 0.049949484 | LM11: 0.059881433 | LN11: 0.078129897 | LO11: 0.070824352 | LP11: 0.070735597 | LQ11: 0.063547972 | LR11: 0.09122694 | LS11: 0.039635728 | LT11: 0.039108241 | LU11: 0.072542466 | LV11: 0.076375312 | LW11: 0.013364805 | LX11: 0.049638555 | LY11: 0.032236759 | LZ11: 0.041432656 | MA11: 0.071180288 | MB11: 0.12033361 | MC11: 0.051184575 | MD11: 0.057516366 | ME11: 0.05460516 | MF11: 0.090160793 | MG11: 0.069188575 | MH11: 0.056961261 | MI11: 0.062435528 | MJ11: 0.064022343 | MK11: 0.072877804 | ML11: 0.10039384 | MM11: 0.065815833 | MN11: 0.048533503 | MO11: 0.022064501 | MP11: 0.037594194 | MQ11: 0.10553578 | MR11: 0.073139799 | MS11: 0.062938778 | MT11: 0.10519188 | MU11: 0.076536922 | MV11: 0.056058614 | MW11: 0.037141023 | MX11: 0.0061667805 | MY11: 0.072299235 | MZ11: 0.072726479 | NA11: 0.0892097 | NB11: 0.05526429 | NC11: 0.064035837 | ND11: 0.030233042 | NE11: 0.058192656 | NF11: 0.068012845 | NG11: 0.039041145 | NH11: 0.05428366 | NI11: 0.10239332 | NJ11: 0.0072824904 | NK11: 0.016805675 | NL11: 0.081469692 | NM11: 0.038569925 | NN11: 0.08104603 | NO11: 0.053205997 | NP11: 0.07777525 | NQ11: 0.10753915 | NR11: 0.057883561 | NS11: 0.04309075 | NT11: 0.076681284 | NU11: 0.11893828 | NV11: 0.040755735 | NW11: 0.11927703 | NX11: 0.045799521 | NY11: 0.05753218 | NZ11: 0.088272073 | OA11: 0.015107816 | OB11: 0.08149731 | OC11: 0.10779528 | OD11: 0.076390783 | OE11: 0.053841032 | OF11: 0.080179595 | OG11: 0.026329547 | OH11: 0.051453876 | OI11: 0.044912746 | OJ11: 0.031085065 | OK11: 0.057763263 | OL11: 0.0091556821 | OM11: 0.044399727 | ON11: 0.034076717 | OO11: 0.069731361 | OP11: 0.093288069 | OQ11: 0.079474971 | OR11: 0.0060663941 | OS11: 0.052273011 | OT11: 0.062666955 | OU11: 0.068790754 | OV11: 0.047462772 | OW11: 0.081249782 | OX11: 0.092409918 | OY11: 0.070909153 | OZ11: 0.1029655 | PA11: 0.056712472 | PB11: 0.0095152853 | PC11: 0.10239985 | PD11: 0.035290808 | PE11: 0.047272542 | PF11: 0.058455855 | PG11: 0.078904453 | PH11: 0.069291769 | PI11: 0.073166901 | PJ11: 0.017581148 | PK11: 0.046463951 | PL11: 0.098547697 | PM11: 0.044990414 | PN11: 0.0089031117 | PO11: 0.1181847 | PP11: 0.038715577 | PQ11: 0.082770475 | PR11: 0.075673123 | PS11: 0.064838785 | PT11: 0.053505609 | PU11: 0.051907591 | PV11: 0.042096999 | PW11: 0.042312469 | PX11: 0.076861802 | PY11: 0.0093841871 | PZ11: 0.029497906 | QA11: 0.1137787 | QB11: 0.032842859 | QC11: 0.058869261 | QD11: 0.059090174 | QE11: 0.072344501 | QF11: 0.070624811 | QG11: 0.075120454 | QH11: 0.077184477 | QI11: 0.091105639 | QJ11: 0.057579623 | QK11: 0.016028024 | QL11: 0.014843327 | QM11: 0.032105087 | QN11: 0.046430259 | QO11: 0.053380928 | QP11: 0.096121578 | QQ11: 0.099913685 | QR11: 0.071613204 | QS11: 0.03885739 | QT11: 0.04427983 | QU11: 0.078100044 | QV11: 0.074460465 | QW11: 0.070850594 | QX11: 0.066565236 | QY11: 0.059669344 | QZ11: 0.036796375 | RA11: 0.020300405 | RB11: 0.058485278 | RC11: 0.049296428 | RD11: 0.062618739 | RE11: 0.065790651 | RF11: 0.087665859 | RG11: 0.10147013 | RH11: 0.046372503 | RI11: 0.046072547 | RJ11: 0.063033262 | RK11: 0.050726877 | RL11: 0.091920992 | RM11: 0.072093764 | RN11: 0.032989714 | RO11: 0.06153417 | RP11: 0.042022999 | RQ11: 0.069252062 | RR11: 0.0459972 | RS11: 0.069669593 | RT11: 0.072614776 | RU11: 0.067840177 | RV11: 0.11231988 | RW11: 0.071281706 | RX11: 0.056044548 | RY11: 0.0697513 | RZ11: 0.14148855 | SA11: 0.066859175 | SB11: 0.065552376 | SC11: 0.058925987 | SD11: 0.053066103 | SE11: 0.01156656 | SF11: 0.073139799 | SG11: 0.068960786
A12: 11 | B12: 0.049914045 | C12: 0.014806656 | D12: 0.065658894 | E12: 0.072009708 | F12: 0.082684585 | G12: 0.065602741 | H12: 0.07646825 | I12: 0.056851879 | J12: 0.080191714 | K12: 0.085877411 | L12: 0.056447067 | M12: 0.061541906 | N12: 0.090325353 | O12: 0.034670097 | P12: 0.073146074 | Q12: 0.079866432 | R12: 0.10958378 | S12: 0.085816789 | T12: 0.043103986 | U12: 0.047109815 | V12: 0.075968151 | W12: 0.046435072 | X12: 0.078524624 | Y12: 0.040363186 | Z12: 0.073662932 | AA12: 0.080836089 | AB12: 0.042542636 | AC12: 0.035033024 | AD12: 0.068325378 | AE12: 0.10404603 | AF12: 0.0182591 | AG12: 0.076969093 | AH12: 0.088635229 | AI12: 0.069321536 | AJ12: 0.066664476 | AK12: 0.059429723 | AL12: 0.081653218 | AM12: 0.06430978 | AN12: 0.063958685 | AO12: 0.11624939 | AP12: 0.038235189 | AQ12: 0.063474716 | AR12: 0.056343128 | AS12: 0.084677645 | AT12: 0.05358236 | AU12: 0.089650438 | AV12: 0.10615712 | AW12: 0.040029825 | AX12: 0.053493146 | AY12: 0.063860333 | AZ12: 0.099241578 | BA12: 0.080524674 | BB12: 0.049426438 | BC12: 0.05481533 | BD12: 0.043658174 | BE12: 0.060269944 | BF12: 0.086352527 | BG12: 0.080013058 | BH12: 0.073411278 | BI12: 0.017044952 | BJ12: 0.067227803 | BK12: 0.068012845 | BL12: 0.063177826 | BM12: 0.02037409 | BN12: 0.054396452 | BO12: 0.052416829 | BP12: 0.082138075 | BQ12: 0.062931071 | BR12: 0.057960426 | BS12: 0.047237247 | BT12: 0.081751656 | BU12: 0.12653327 | BV12: 0.11478623 | BW12: 0.092542391 | BX12: 0.070331358 | BY12: 0.072592029 | BZ12: 0.082893208 | CA12: 0.051719711 | CB12: 0.051666223 | CC12: 0.062952271 | CD12: 0.088329085 | CE12: 0.06979118 | CF12: 0.048517517 | CG12: 0.08413102 | CH12: 0.08274704 | CI12: 0.041359773 | CJ12: 0.060599666 | CK12: 0.091565858 | CL12: 0.054741931 | CM12: 0.031897668 | CN12: 0.056792174 | CO12: 0.090487679 | CP12: 0.055089874 | CQ12: 0.09717277 | CR12: 0.047917089 | CS12: 0.037764771 | CT12: 0.059634306 | CU12: 0.079181605 | CV12: 0.10825481 | CW12: 0.0803396 | CX12: 0.034921178 | CY12: 0.086279071 | CZ12: 0.068723601 | DA12: 0.052940591 | DB12: 0.079151007 | DC12: 0.069248108 | DD12: 0.051760335 | DE12: 0.058549996 | DF12: 0.034230334 | DG12: 0.092440114 | DH12: -0.0036362482 | DI12: 0.042464309 | DJ12: 0.038632036 | DK12: 0.038743424 | DL12: 0.051009357 | DM12: 0.065895306 | DN12: 0.10516105 | DO12: 0.069347348 | DP12: 0.027477229 | DQ12: 0.083554028 | DR12: 0.061634614 | DS12: 0.067826483 | DT12: 0.06151678 | DU12: 0.079574842 | DV12: 0.092080281 | DW12: 0.070644923 | DX12: 0.070739636 | DY12: 0.063461222 | DZ12: 0.10490103 | EA12: 0.060322371 | EB12: 0.058155298 | EC12: 0.067282494 | ED12: 0.029497906 | EE12: 0.094069158 | EF12: 0.032359377 | EG12: 0.088164811 | EH12: 0.045689279 | EI12: 0.061306124 | EJ12: 0.052753885 | EK12: 0.11481763 | EL12: 0.035025861 | EM12: 0.063293511 | EN12: 0.048185016 | EO12: 0.077953361 | EP12: 0.052086333 | EQ12: 0.058589217 | ER12: 0.068937036 | ES12: 0.066366956 | ET12: 0.055428191 | EU12: 0.032166855 | EV12: 0.079268927 | EW12: 0.062013011 | EX12: 0.069144971 | EY12: 0.018390886 | EZ12: 0.060036941 | FA12: 0.043186037 | FB12: 0.077011666 | FC12: 0.00387027 | FD12: 0.087279612 | FE12: 0.060365059 | FF12: 0.016847617 | FG12: 0.049533728 | FH12: 0.11296735 | FI12: 0.076082261 | FJ12: 0.047045928 | FK12: 0.087203634 | FL12: 0.064300125 | FM12: 0.042366788 | FN12: 0.069164796 | FO12: 0.061580525 | FP12: 0.12339562 | FQ12: 0.065897254 | FR12: 0.052602446 | FS12: 0.088731662 | FT12: 0.059928103 | FU12: 0.054394418 | FV12: 0.071123563 | FW12: 0.08204869 | FX12: 0.042195409 | FY12: 0.083024249 | FZ12: 0.057873706 | GA12: 0.098124722 | GB12: 0.03499704 | GC12: 0.032882681 | GD12: 0.060431009 | GE12: 0.066417464 | GF12: 0.058918165 | GG12: 0.043443936 | GH12: 0.050062247 | GI12: 0.025124223 | GJ12: 0.045055447 | GK12: 0.048763526 | GL12: 0.033393207 | GM12: 0.043566927 | GN12: 0.12114357 | GO12: 0.050929111 | GP12: 0.055956194 | GQ12: 0.073162747 | GR12: 0.0089812664 | GS12: 0.024578056 | GT12: 0.038222583 | GU12: 0.079031025 | GV12: 0.037098221 | GW12: 0.081018813 | GX12: 0.023293317 | GY12: 0.04278982 | GZ12: 0.090784025 | HA12: 0.054143968 | HB12: 0.070614726 | HC12: 0.07965589 | HD12: 0.082428233 | HE12: 0.070677153 | HF12: 0.042014748 | HG12: 0.090699968 | HH12: 0.11616138 | HI12: 0.081701119 | HJ12: 0.027644884 | HK12: 0.051232075 | HL12: 0.022868852 | HM12: 0.030765456 | HN12: 0.090321915 | HO12: 0.057828354 | HP12: 0.041125939 | HQ12: 0.039004474 | HR12: 0.09824098 | HS12: 0.053247681 | HT12: 0.053671458 | HU12: 0.12401536 | HV12: 0.1290498 | HW12: 0.016604673 | HX12: 0.08878323 | HY12: 0.10370556 | HZ12: 0.069641689 | IA12: 0.065447864 | IB12: 0.043299487 | IC12: 0.075241324 | ID12: 0.055994355 | IE12: 0.066635283 | IF12: 0.094431626 | IG12: 0.088542349 | IH12: 0.037870429 | II12: 0.017875775 | IJ12: 0.061456875 | IK12: 0.08673144 | IL12: 0.072776185 | IM12: 0.059605113 | IN12: 0.020536588 | IO12: 0.058628409 | IP12: 0.080845944 | IQ12: 0.07635543 | IR12: 0.062068991 | IS12: 0.070576509 | IT12: 0.054821404 | IU12: 0.053303919 | IV12: 0.028229898 | IW12: 0.041700181 | IX12: 0.058265367 | IY12: 0.10587957 | IZ12: 0.062522306 | JA12: 0.077357947 | JB12: 0.056457095 | JC12: 0.049372663 | JD12: 0.0482057 | JE12: 0.049390569 | JF12: 0.089374433 | JG12: 0.051093814 | JH12: 0.033135538 | JI12: 0.081822506 | JJ12: 0.042677229 | JK12: 0.062927203 | JL12: 0.10230313 | JM12: 0.089520314 | JN12: 0.055539321 | JO12: 0.063536398 | JP12: 0.11326897 | JQ12: 0.069095437 | JR12: 0.060545376 | JS12: 0.085724654 | JT12: 0.031889302 | JU12: 0.11712949 | JV12: 0.026091874 | JW12: 0.043212451 | JX12: 0.05753218 | JY12: 0.099522568 | JZ12: 0.069709444 | KA12: 0.084769236 | KB12: 0.052196718 | KC12: 0.054213871 | KD12: 0.096221449 | KE12: 0.061617253 | KF12: 0.053716982 | KG12: 0.090713949 | KH12: 0.074496677 | KI12: 0.057753408 | KJ12: 0.070273172 | KK12: 0.059669344 | KL12: 0.034545359 | KM12: 0.074347645 | KN12: 0.051210502 | KO12: 0.093193871 | KP12: 0.03982315 | KQ12: 0.050352892 | KR12: 0.059373199 | KS12: 0.052300514 | KT12: 0.076309076 | KU12: 0.038232038 | KV12: 0.063800542 | KW12: 0.063823691 | KX12: 0.03230225 | KY12: 0.08319282 | KZ12: 0.11803985 | LA12: 0.044824822 | LB12: 0.092173391 | LC12: 0.065445916 | LD12: 0.025879642 | LE12: 0.069325518 | LF12: 0.031688071 | LG12: 0.055869788 | LH12: 0.055944161 | LI12: 0.066933233 | LJ12: 0.098511599 | LK12: 0.062888642 | LL12: 0.058789015 | LM12: 0.044930308 | LN12: 0.076512541 | LO12: 0.018996069 | LP12: 0.040325369 | LQ12: 0.073150228 | LR12: 0.10074119 | LS12: 0.053754225 | LT12: 0.085353419 | LU12: 0.049424174 | LV12: 0.079054517 | LW12: 0.09705359 | LX12: 0.09026009 | LY12: 0.035626518 | LZ12: 0.084939325 | MA12: 0.039065554 | MB12: 0.086517661 | MC12: 0.067853929 | MD12: 0.091013275 | ME12: 0.08685996 | MF12: 0.065014633 | MG12: 0.092671885 | MH12: 0.050794374 | MI12: 0.062852028 | MJ12: 0.043401994 | MK12: 0.069607826 | ML12: 0.04305895 | MM12: 0.053364283 | MN12: 0.078705944 | MO12: 0.069341389 | MP12: 0.050060041 | MQ12: 0.080956988 | MR12: 0.07922879 | MS12: 0.014818804 | MT12: 0.034950113 | MU12: 0.060830176 | MV12: 0.053826564 | MW12: 0.027104734 | MX12: 0.020018498 | MY12: 0.047984243 | MZ12: 0.03367076 | NA12: 0.074564919 | NB12: 0.031662803 | NC12: 0.094915165 | ND12: 0.075955002 | NE12: 0.012793657 | NF12: 0.074870949 | NG12: 0.089580305 | NH12: 0.041833055 | NI12: 0.040629336 | NJ12: 0.081442132 | NK12: 0.023414445 | NL12: 0.070737631 | NM12: 0.065173148 | NN12: 0.084475955 | NO12: 0.027339713 | NP12: 0.036143348 | NQ12: 0.051232075 | NR12: 0.017178342 | NS12: 0.069855067 | NT12: 0.09237594 | NU12: 0.040516802 | NV12: 0.038777344 | NW12: 0.039038108 | NX12: 0.086535366 | NY12: 0.089094989 | NZ12: 0.056507001 | OA12: 0.071854114 | OB12: 0.064786644 | OC12: 0.082204598 | OD12: 0.064711296 | OE12: 0.062749837 | OF12: 0.050278175 | OG12: 0.032330842 | OH12: 0.049255976 | OI12: 0.063326285 | OJ12: 0.061522568 | OK12: 0.073208614 | OL12: 0.067848027 | OM12: 0.075664414 | ON12: 0.060046653 | OO12: 0.037578036 | OP12: 0.071858211 | OQ12: 0.046920273 | OR12: 0.038467132 | OS12: 0.076835015 | OT12: 0.020665279 | OU12: 0.058561771 | OV12: 0.074088886 | OW12: 0.065262104 | OX12: 0.060981186 | OY12: 0.078042689 | OZ12: 0.054701135 | PA12: 0.10230955 | PB12: 0.09741835 | PC12: 0.082663786 | PD12: 0.081432105 | PE12: 0.076966859 | PF12: 0.076987027 | PG12: 0.038426565 | PH12: 0.033513133 | PI12: 0.077754766 | PJ12: 0.077641029 | PK12: 0.044950362 | PL12: 0.10410356 | PM12: 0.029374887 | PN12: 0.026685712 | PO12: 0.071261394 | PP12: 0.080826262 | PQ12: 0.069741331 | PR12: 0.015261833 | PS12: 0.051102466 | PT12: 0.099204105 | PU12: 0.076168007 | PV12: 0.027249297 | PW12: 0.091305839 | PX12: 0.032051342 | PY12: 0.086725481 | PZ12: 0.015747263 | QA12: 0.088507225 | QB12: 0.036628892 | QC12: 0.059238577 | QD12: 0.040147286 | QE12: 0.099802642 | QF12: 0.082710599 | QG12: 0.055950178 | QH12: 0.043694616 | QI12: 0.08497571 | QJ12: 0.03972517 | QK12: 0.013634336 | QL12: 0.024880935 | QM12: 0.050835686 | QN12: 0.069333454 | QO12: 0.082838316 | QP12: 0.045872863 | QQ12: 0.092188346 | QR12: 0.039150814 | QS12: 0.063652083 | QT12: 0.012461328 | QU12: 0.086197135 | QV12: 0.035734983 | QW12: 0.053053555 | QX12: 0.090903663 | QY12: 0.06457613 | QZ12: 0.062830828 | RA12: 0.058908367 | RB12: 0.061858593 | RC12: 0.11248857 | RD12: 0.058532348 | RE12: 0.043430872 | RF12: 0.010343588 | RG12: 0.082565233 | RH12: 0.060770157 | RI12: 0.071574499 | RJ12: 0.07195642 | RK12: 0.030827166 | RL12: 0.077969376 | RM12: 0.10601777 | RN12: 0.020903754 | RO12: 0.070685203 | RP12: 0.041636351 | RQ12: 0.071131671 | RR12: 0.045477591 | RS12: -0.0111501 | RT12: 0.059702463 | RU12: 0.080020278 | RV12: 0.0097733563 | RW12: 0.10413954 | RX12: 0.070931356 | RY12: 0.073837576 | RZ12: 0.062065124 | SA12: 0.049446549 | SB12: 0.045065417 | SC12: 0.047069592 | SD12: 0.04020871 | SE12: 0.046641374 | SF12: 0.067634477 | SG12: 0.05613485
A13: 12 | B13: 0.0017259434 | C13: 0.052028949 | D13: 0.033993864 | E13: 0.033009482 | F13: 0.06676959 | G13: 0.089111377 | H13: 0.015678964 | I13: 0.032898552 | J13: 0.025948743 | K13: 0.082441125 | L13: 0.086992089 | M13: 0.11578138 | N13: 0.071946193 | O13: 0.079202833 | P13: 0.063158545 | Q13: 0.079028676 | R13: 0.084049485 | S13: 0.085189317 | T13: 0.040718434 | U13: 0.050196754 | V13: 0.043472757 | W13: 0.036293813 | X13: 0.061951272 | Y13: 0.047460423 | Z13: 0.068406111 | AA13: 0.097153633 | AB13: 0.076806023 | AC13: 0.072509405 | AD13: 0.054201524 | AE13: 0.070951582 | AF13: 0.029289284 | AG13: -0.0089186807 | AH13: 0.070311275 | AI13: 0.052408406 | AJ13: 0.04497288 | AK13: 0.073782799 | AL13: 0.061443353 | AM13: 0.086054233 | AN13: 0.084106554 | AO13: 0.050075511 | AP13: 0.063222174 | AQ13: 0.037535979 | AR13: 0.081716303 | AS13: 0.076980295 | AT13: 0.063794755 | AU13: 0.089285334 | AV13: 0.049240276 | AW13: 0.13023335 | AX13: 0.025699725 | AY13: 0.10895854 | AZ13: 0.054984245 | BA13: 0.019542235 | BB13: 0.050950798 | BC13: 0.050403343 | BD13: 0.060754658 | BE13: 0.058659751 | BF13: 0.044650865 | BG13: 0.041650217 | BH13: 0.044676133 | BI13: 0.075566491 | BJ13: 0.025369803 | BK13: 0.092489276 | BL13: 0.064605094 | BM13: 0.032289931 | BN13: 0.011312385 | BO13: 0.022224362 | BP13: 0.087112759 | BQ13: 0.096285222 | BR13: 0.092106295 | BS13: 0.070373501 | BT13: 0.045418316 | BU13: 0.00098152566 | BV13: 0.078482911 | BW13: 0.027754094 | BX13: 0.045848454 | BY13: 0.048713534 | BZ13: 0.061408573 | CA13: 0.08370667 | CB13: 0.050214402 | CC13: 0.060027229 | CD13: 0.039988627 | CE13: 0.054215905 | CF13: 0.068688047 | CG13: 0.060926982 | CH13: 0.023157635 | CI13: 0.059328334 | CJ13: 0.085065496 | CK13: 0.074315787 | CL13: 0.033563211 | CM13: 0.051845738 | CN13: 0.065057148 | CO13: 0.062898297 | CP13: 0.045708875 | CQ13: 0.059505758 | CR13: 0.091598576 | CS13: 0.10720774 | CT13: 0.079749057 | CU13: 0.041899235 | CV13: -0.0039672024 | CW13: 0.08411744 | CX13: 0.037350677 | CY13: 0.050792197 | CZ13: 0.054805131 | DA13: 0.060293264 | DB13: 0.05236824 | DC13: 0.02405183 | DD13: 0.12136268 | DE13: 0.081108026 | DF13: 0.070086896 | DG13: 0.066935182 | DH13: 0.08497571 | DI13: 0.066106736 | DJ13: 0.015048225 | DK13: 0.065738309 | DL13: 0.059564202 | DM13: 0.11336638 | DN13: 0.061628827 | DO13: 0.076472662 | DP13: 0.049437611 | DQ13: 0.098256164 | DR13: 0.077928207 | DS13: 0.035411535 | DT13: 0.053301856 | DU13: 0.026608474 | DV13: 0.033311558 | DW13: 0.093604928 | DX13: 0.073964148 | DY13: 0.042304333 | DZ13: 0.02726534 | EA13: 0.036926155 | EB13: 0.094171492 | EC13: 0.041669641 | ED13: 0.11393867 | EE13: 0.037282091 | EF13: 0.078247243 | EG13: 0.047930984 | EH13: 0.07499987 | EI13: 0.046810834 | EJ13: 0.081282155 | EK13: 0.031582471 | EL13: 0.048804409 | EM13: 0.050040158 | EN13: 0.069393015 | EO13: 0.035960796 | EP13: 0.049964983 | EQ13: 0.076765885 | ER13: 0.068757149 | ES13: 0.094439877 | ET13: 0.093131301 | EU13: 0.057203489 | EV13: 0.044005286 | EW13: 0.06340146 | EX13: 0.048978796 | EY13: 0.032747056 | EZ13: 0.060884409 | FA13: 0.052568755 | FB13: 0.041605754 | FC13: 0.10230313 | FD13: 0.11122091 | FE13: 0.095572834 | FF13: 0.029601272 | FG13: 0.10044553 | FH13: 0.072900637 | FI13: 0.09163135 | FJ13: 0.050203372 | FK13: 0.064894822 | FL13: 0.055337173 | FM13: 0.063000488 | FN13: 0.097187152 | FO13: 0.06263802 | FP13: 0.05428366 | FQ13: 0.040188254 | FR13: 0.036876306 | FS13: 0.051730397 | FT13: -0.0016486894 | FU13: 0.06280576 | FV13: 0.060526009 | FW13: 0.07732861 | FX13: 0.076205423 | FY13: 0.058761627 | FZ13: 0.091729903 | GA13: 0.013989585 | GB13: 0.059152687 | GC13: 0.038638224 | GD13: 0.089477111 | GE13: 0.057338254 | GF13: 0.075527357 | GG13: 0.031704917 | GH13: 0.047444036 | GI13: 0.062377657 | GJ13: 0.055765133 | GK13: 0.064197876 | GL13: 0.07235894 | GM13: 0.044572423 | GN13: 0.061599834 | GO13: 0.062607165 | GP13: 0.054259022 | GQ13: 0.11797796 | GR13: 0.10050305 | GS13: 0.067601187 | GT13: 0.1051379 | GU13: 0.045002933 | GV13: 0.070221059 | GW13: 0.081185035 | GX13: 0.034713987 | GY13: 0.029922142 | GZ13: 0.094216643 | HA13: 0.048189599 | HB13: 0.079998619 | HC13: 0.027281269 | HD13: 0.061958979 | HE13: 0.077516233 | HF13: 0.051091637 | HG13: 0.040741411 | HH13: 0.050000365 | HI13: 0.021169503 | HJ13: 0.044721571 | HK13: 0.086437902 | HL13: 0.090543143 | HM13: 0.031947632 | HN13: 0.056678609 | HO13: 0.067618806 | HP13: 0.015261833 | HQ13: 0.098708247 | HR13: 0.05449065 | HS13: 0.056124822 | HT13: 0.068855959 | HU13: 0.071933902 | HV13: 0.07413971 | HW13: 0.044756866 | HX13: 0.064332957 | HY13: 0.052648772 | HZ13: 0.063738832 | IA13: 0.070955622 | IB13: 0.054441517 | IC13: 0.065090009 | ID13: 0.059222963 | IE13: 0.044295158 | IF13: 0.072645775 | IG13: 0.067020957 | IH13: 0.041580657 | II13: 0.11011872 | IJ13: 0.074746612 | IK13: 0.082544491 | IL13: 0.054888615 | IM13: 0.074449807 | IN13: 0.077498127 | IO13: 0.076607943 | IP13: 0.013364805 | IQ13: 0.085687296 | IR13: 0.089963458 | IS13: 0.11258025 | IT13: 0.1029388 | IU13: 0.055825525 | IV13: 0.067188755 | IW13: 0.056329119 | IX13: 0.074800186 | IY13: 0.057286743 | IZ13: 0.045987459 | JA13: 0.083506012 | JB13: 0.010753843 | JC13: 0.034743152 | JD13: 0.084855555 | JE13: 0.023171272 | JF13: 0.025734677 | JG13: 0.059121431 | JH13: 0.064008821 | JI13: 0.025931439 | JJ13: 0.067261008 | JK13: 0.063193239 | JL13: 0.041455059 | JM13: 0.087058383 | JN13: 0.070217077 | JO13: 0.04320718 | JP13: 0.023259511 | JQ13: 0.066923493 | JR13: 0.06155348 | JS13: 0.058300749 | JT13: 0.032396047 | JU13: 0.028952542 | JV13: 0.070006879 | JW13: 0.063191319 | JX13: 0.068012845 | JY13: 0.045999606 | JZ13: 0.065223427 | KA13: 0.049008161 | KB13: 0.039710273 | KC13: 0.070600631 | KD13: 0.082485016 | KE13: 0.1019284 | KF13: 0.079153357 | KG13: 0.053097445 | KH13: 0.062649594 | KI13: 0.076038342 | KJ13: 0.12010946 | KK13: 0.055827531 | KL13: 0.095616896 | KM13: 0.033997646 | KN13: 0.1126066 | KO13: 0.092039428 | KP13: 0.048658929 | KQ13: 0.088802597 | KR13: 0.12103585 | KS13: 0.10925226 | KT13: 0.068230951 | KU13: 0.04962297 | KV13: 0.058249668 | KW13: 0.095397616 | KX13: 0.053013819 | KY13: 0.065354984 | KZ13: 0.060060232 | LA13: 0.067290287 | LB13: 0.035811648 | LC13: 0.073010764 | LD13: 0.1060423 | LE13: 0.054870308 | LF13: 0.02769691 | LG13: 0.083084756 | LH13: 0.068729502 | LI13: 0.074952541 | LJ13: 0.072662334 | LK13: 0.049399565 | LL13: 0.055128436 | LM13: 0.069323512 | LN13: 0.059661552 | LO13: 0.031227852 | LP13: 0.083965457 | LQ13: 0.05621501 | LR13: 0.023013817 | LS13: 0.082950792 | LT13: 0.07650366 | LU13: 0.052883981 | LV13: 0.072577561 | LW13: 0.053524288 | LX13: 0.009626673 | LY13: 0.047582067 | LZ13: 0.061567002 | MA13: 0.053580268 | MB13: 0.070022894 | MC13: 0.066403884 | MD13: 0.11359213 | ME13: 0.04683467 | MF13: 0.044338532 | MG13: 0.096166958 | MH13: 0.067065821 | MI13: 0.076172419 | MJ13: 0.10763014 | MK13: 0.076121825 | ML13: 0.082624823 | MM13: 0.06611258 | MN13: 0.021161711 | MO13: 0.027949996 | MP13: 0.020068691 | MQ13: 0.059187811 | MR13: 0.063796703 | MS13: 0.080073307 | MT13: 0.064294338 | MU13: 0.075146324 | MV13: 0.062252288 | MW13: 0.066155268 | MX13: 0.05440668 | MY13: 0.039371755 | MZ13: 0.074498797 | NA13: 0.082376694 | NB13: 0.12064027 | NC13: 0.047012781 | ND13: 0.08386275 | NE13: 0.05889665 | NF13: 0.059809467 | NG13: 0.039929668 | NH13: 0.06160373 | NI13: 0.03905948 | NJ13: 0.073394547 | NK13: -0.0054972926 | NL13: 0.061014075 | NM13: 0.048770345 | NN13: 0.069295723 | NO13: 0.07785965 | NP13: 0.068925175 | NQ13: 0.062047763 | NR13: 0.032047216 | NS13: 0.056311099 | NT13: 0.052844159 | NU13: 0.078065608 | NV13: 0.063937485 | NW13: 0.12893429 | NX13: 0.064583865 | NY13: 0.097168015 | NZ13: 0.071684598 | OA13: 0.0988335 | OB13: 0.089127707 | OC13: 0.078771235 | OD13: 0.059262012 | OE13: 0.076559125 | OF13: 0.096004346 | OG13: 0.056255061 | OH13: 0.10022287 | OI13: 0.11272578 | OJ13: 0.054739868 | OK13: 0.06734303 | OL13: 0.058685248 | OM13: 0.044254247 | ON13: 0.0989544 | OO13: 0.051236401 | OP13: 0.10333118 | OQ13: 0.052412617 | OR13: 0.077992266 | OS13: 0.04876579 | OT13: 0.079844831 | OU13: 0.060725607 | OV13: 0.091642237 | OW13: 0.094431626 | OX13: 0.086493996 | OY13: 0.050172517 | OZ13: 0.082604081 | PA13: 0.097403797 | PB13: 0.055128436 | PC13: 0.04600694 | PD13: 0.08657685 | PE13: 0.030906181 | PF13: 0.1219595 | PG13: 0.060810838 | PH13: 0.042542636 | PI13: 0.044678654 | PJ13: 0.07443703 | PK13: 0.059486277 | PL13: 0.059185862 | PM13: 0.050198989 | PN13: 0.054441517 | PO13: 0.022282119 | PP13: 0.051423794 | PQ13: 0.040035727 | PR13: 0.035464593 | PS13: 0.069817136 | PT13: 0.092248222 | PU13: 0.06097729 | PV13: 0.075133403 | PW13: 0.11148402 | PX13: 0.028138736 | PY13: 0.094506515 | PZ13: 0.049645259 | QA13: 0.051214828 | QB13: 0.090727987 | QC13: 0.13683135 | QD13: 0.10743991 | QE13: 0.057591484 | QF13: 0.042781798 | QG13: 0.054625587 | QH13: 0.07912508 | QI13: 0.034681098 | QJ13: 0.089966838 | QK13: 0.04517265 | QL13: 0.027067089 | QM13: 0.031480537 | QN13: 0.057577646 | QO13: 0.07916983 | QP13: 0.04551707 | QQ13: 0.032989714 | QR13: 0.053364283 | QS13: 0.065407211 | QT13: 0.061466559 | QU13: 0.042372231 | QV13: 0.08093722 | QW13: 0.041216298 | QX13: 0.024383472 | QY13: 0.026795496 | QZ13: 0.049504707 | RA13: 0.11887136 | RB13: 0.12733544 | RC13: 0.083908646 | RD13: 0.038746461 | RE13: 0.063627015 | RF13: 0.05074865 | RG13: 0.052904952 | RH13: 0.073423826 | RI13: 0.082340682 | RJ13: 0.088462532 | RK13: 0.0059394214 | RL13: -0.00093544179 | RM13: 0.042550715 | RN13: 0.062153907 | RO13: 0.044706444 | RP13: 0.030009464 | RQ13: 0.0371903 | RR13: 0.073173147 | RS13: 0.084611179 | RT13: 0.089193256 | RU13: 0.053260201 | RV13: 0.03118465 | RW13: 0.031578288 | RX13: 0.07976341 | RY13: 0.009882452 | RZ13: 0.077502654 | SA13: 0.050046776 | SB13: 0.051952313 | SC13: 0.099896954 | SD13: 0.062198256 | SE13: 0.023673662 | SF13: 0.038681599 | SG13: 0.038513945
... A101: 100 | B101: 0.03931142 | C101: 0.075053673 | D101: 0.060283552 | E101: 0.041653025 | F101: 0.05631511 | G101: 0.043217723 | H101: 0.1161788 | I101: 0.029601272 | J101: 0.075258628 | K101: 0.038357692 | L101: 0.057696167 | M101: 0.079167481 | N101: 0.071263456 | O101: 0.07024713 | P101: 0.064850359 | Q101: 0.042290753 | R101: 0.049401799 | S101: 0.11340855 | T101: 0.07182346 | U101: 0.052545578 | V101: 0.048831625 | W101: 0.066232935 | X101: 0.032930296 | Y101: 0.084155544 | Z101: 0.078722245 | AA101: 0.03031452 | AB101: 0.074637516 | AC101: 0.094970573 | AD101: 0.098144891 | AE101: 0.070897035 | AF101: 0.046629428 | AG101: 0.062979287 | AH101: 0.076124002 | AI101: 0.079035723 | AJ101: 0.11988943 | AK101: 0.081946871 | AL101: 0.052774885 | AM101: 0.079722757 | AN101: 0.031633237 | AO101: 0.03069475 | AP101: 0.11893828 | AQ101: 0.098786401 | AR101: 0.043259952 | AS101: 0.09122694 | AT101: 0.052823188 | AU101: 0.019403344 | AV101: 0.087786586 | AW101: 0.062204043 | AX101: 0.082356095 | AY101: 0.075206773 | AZ101: 0.070548318 | BA101: 0.05420562 | BB101: 0.064091789 | BC101: 0.052835764 | BD101: 0.033501558 | BE101: 0.037415883 | BF101: 0.0027673949 | BG101: 0.091536808 | BH101: 0.070659018 | BI101: 0.022035164 | BJ101: 0.043629525 | BK101: 0.050519457 | BL101: 0.079854457 | BM101: 0.055757083 | BN101: 0.097413537 | BO101: 0.068879681 | BP101: 0.062632232 | BQ101: 0.052181849 | BR101: 0.073354782 | BS101: 0.041808188 | BT101: 0.053942163 | BU101: 0.010920695 | BV101: 0.073125246 | BW101: 0.048309123 | BX101: 0.037610295 | BY101: 0.082921972 | BZ101: 0.028093012 | CA101: 0.045195054 | CB101: 0.050818296 | CC101: 0.092263177 | CD101: 0.030228572 | CE101: 0.056006416 | CF101: 0.030155804 | CG101: 0.057100324 | CH101: 0.035151574 | CI101: 0.071192464 | CJ101: 0.074622561 | CK101: 0.082642987 | CL101: 0.07655245 | CM101: 0.077029571 | CN101: 0.058029356 | CO101: 0.06023502 | CP101: 0.049168281 | CQ101: 0.038105752 | CR101: 0.052060835 | CS101: 0.044374229 | CT101: 0.066462185 | CU101: 0.050267174 | CV101: 0.016314057 | CW101: 0.098896528 | CX101: 0.060151537 | CY101: 0.063200974 | CZ101: 0.043270495 | DA101: 0.074239351 | DB101: 0.062184762 | DC101: 0.027908913 | DD101: 0.10148239 | DE101: 0.071819363 | DF101: 0.073189849 | DG101: 0.018249589 | DH101: 0.075721082 | DI101: 0.058153321 | DJ101: 0.054790864 | DK101: 0.11461525 | DL101: 0.073434312 | DM101: 0.10983796 | DN101: 0.09408142 | DO101: 0.05695132 | DP101: 0.013700802 | DQ101: 0.041714047 | DR101: 0.063364818 | DS101: 0.083562049 | DT101: 0.084242866 | DU101: 0.042347794 | DV101: 0.026402545 | DW101: 0.069133082 | DX101: 0.001763531 | DY101: 0.048048932 | DZ101: 0.034012773 | EA101: 0.069347348 | EB101: 0.076980295 | EC101: 0.063015901 | ED101: 0.033013435 | EE101: 0.078671021 | EF101: 0.075536037 | EG101: 0.047933305 | EH101: 0.024038881 | EI101: 0.087995323 | EJ101: 0.049116483 | EK101: 0.06157087 | EL101: 0.036242645 | EM101: 0.059064791 | EN101: 0.04527954 | EO101: 0.067571821 | EP101: 0.063183613 | EQ101: -0.0051104154 | ER101: 0.098210555 | ES101: 0.060514378 | ET101: 0.085831171 | EU101: 0.08742916 | EV101: 0.10321521 | EW101: 0.052154289 | EX101: 0.09311182 | EY101: 0.10462314 | EZ101: 0.063324337 | FA101: 0.050829183 | FB101: 0.083914089 | FC101: 0.040138462 | FD101: 0.050887856 | FE101: 0.039683457 | FF101: 0.098713403 | FG101: 0.088243653 | FH101: 0.072925562 | FI101: 0.098064444 | FJ101: 0.051311862 | FK101: 0.034289981 | FL101: 0.051175951 | FM101: 0.060489166 | FN101: 0.079741866 | FO101: 0.077126033 | FP101: 0.11277896 | FQ101: 0.047404156 | FR101: 0.097466825 | FS101: 0.068347037 | FT101: 0.080529573 | FU101: 0.039740011 | FV101: 0.039111278 | FW101: 0.073673417 | FX101: 0.064491214 | FY101: 0.040718434 | FZ101: 0.043868458 | GA101: 0.044442987 | GB101: 0.079252396 | GC101: 0.064020395 | GD101: 0.03006447 | GE101: 0.074791591 | GF101: 0.050613426 | GG101: 0.07574509 | GH101: 0.10818823 | GI101: 0.072871587 | GJ101: 0.050598128 | GK101: 0.12284235 | GL101: 0.0095340791 | GM101: 0.024813437 | GN101: 0.011519346 | GO101: 0.10383242 | GP101: 0.0074172557 | GQ101: 0.027561228 | GR101: 0.039419943 | GS101: 0.046932134 | GT101: 0.074991275 | GU101: 0.064226812 | GV101: 0.083666447 | GW101: 0.092162218 | GX101: 0.070490017 | GY101: 0.082861808 | GZ101: 0.067429034 | HA101: 0.063443861 | HB101: 0.088567904 | HC101: 0.085359092 | HD101: 0.036327848 | HE101: 0.055016762 | HF101: 0.076494808 | HG101: 0.024559263 | HH101: 0.045735863 | HI101: 0.062107582 | HJ101: 0.039435013 | HK101: 0.033486088 | HL101: 0.01514357 | HM101: 0.038285497 | HN101: 0.054554051 | HO101: 0.093608939 | HP101: 0.068944943 | HQ101: 0.040681133 | HR101: 0.047462772 | HS101: 0.10571868 | HT101: 0.0047288257 | HU101: 0.046879878 | HV101: 0.058998325 | HW101: 0.03580122 | HX101: 0.090284098 | HY101: 0.033624749 | HZ101: 0.083760416 | IA101: 0.078787565 | IB101: 0.067149706 | IC101: 0.027110062 | ID101: 0.039519069 | IE101: 0.063343618 | IF101: 0.065509804 | IG101: 0.043811447 | IH101: 0.081419614 | II101: 0.10883868 | IJ101: 0.062819254 | IK101: 0.036246026 | IL101: 0.034626149 | IM101: 0.10786002 | IN101: 0.087346651 | IO101: 0.055799369 | IP101: 0.10108979 | IQ101: 0.027576928 | IR101: 0.063303137 | IS101: 0.060081605 | IT101: 0.02649743 | IU101: 0.10070027 | IV101: 0.048793064 | IW101: 0.071633602 | IX101: 0.050361658 | IY101: 0.089643734 | IZ101: 0.08869946 | JA101: 0.058839896 | JB101: 0.0300965 | JC101: 0.0049538929 | JD101: 0.063754274 | JE101: 0.093862025 | JF101: 0.083386201 | JG101: 0.062422034 | JH101: 0.036419582 | JI101: 0.066314499 | JJ101: 0.084663778 | JK101: 0.054170697 | JL101: 0.02308246 | JM101: 0.056901614 | JN101: 0.10818823 | JO101: 0.049618501 | JP101: 0.050879175 | JQ101: 0.064892874 | JR101: 0.073528567 | JS101: 0.077101337 | JT101: 0.056690556 | JU101: 0.081769362 | JV101: 0.11203958 | JW101: 0.0086047029 | JX101: 0.069659623 | JY101: 0.041233258 | JZ101: 0.059037403 | KA101: 0.11675499 | KB101: 0.020943061 | KC101: 0.069873002 | KD101: 0.06643302 | KE101: 0.080870583 | KF101: 0.08243339 | KG101: 0.1044823 | KH101: 0.083671775 | KI101: 0.066754005 | KJ101: 0.083359615 | KK101: 0.085972927 | KL101: 0.037594194 | KM101: 0.067712804 | KN101: 0.058412681 | KO101: 0.092852145 | KP101: 0.12475015 | KQ101: 0.034975382 | KR101: 0.021052844 | KS101: 0.064844572 | KT101: 0.045716267 | KU101: 0.071356824 | KV101: 0.054790864 | KW101: 0.060896012 | KX101: 0.078622145 | KY101: 0.045809319 | KZ101: 0.055258188 | LA101: 0.069238167 | LB101: 0.074360422 | LC101: 0.02016839 | LD101: 0.044612933 | LE101: 0.099230863 | LF101: 0.028300375 | LG101: 0.05646907 | LH101: 0.025617904 | LI101: 0.08349799 | LJ101: 0.042179022 | LK101: 0.051768873 | LL101: 0.03031005 | LM101: 0.042293446 | LN101: 0.069769263 | LO101: 0.08380614 | LP101: 0.094556651 | LQ101: 0.067456394 | LR101: 0.038200524 | LS101: 0.058469578 | LT101: 0.051668343 | LU101: 0.067124351 | LV101: 0.06420945 | LW101: 0.080044372 | LX101: 0.10902891 | LY101: 0.062057417 | LZ101: 0.041758396 | MA101: 0.059616773 | MB101: 0.061085669 | MC101: 0.08411744 | MD101: 0.023680309 | ME101: 0.073921919 | MF101: 0.07848059 | MG101: 0.044067054 | MH101: 0.040635123 | MI101: 0.10167916 | MJ101: 0.051704727 | MK101: 0.029722859 | ML101: 0.10077041 | MM101: 0.074712376 | MN101: 0.025470647 | MO101: 0.048286175 | MP101: 0.045249745 | MQ101: 0.090850834 | MR101: 0.03328818 | MS101: 0.062614871 | MT101: 0.093640911 | MU101: 0.094932183 | MV101: 0.066497166 | MW101: 0.042456173 | MX101: 0.089963458 | MY101: 0.037193623 | MZ101: 0.083628916 | NA101: 0.12459888 | NB101: 0.058542175 | NC101: 0.049858638 | ND101: 0.084054928 | NE101: 0.06714581 | NF101: 0.04142429 | NG101: 0.093256613 | NH101: 0.05923468 | NI101: 0.048254003 | NJ101: 0.072534186 | NK101: 0.043795919 | NL101: 0.10373364 | NM101: 0.058544123 | NN101: 0.060477535 | NO101: 0.033758655 | NP101: 0.089157215 | NQ101: 0.021430554 | NR101: 0.039719211 | NS101: 0.06280384 | NT101: 0.04967643 | NU101: 0.067173141 | NV101: 0.058121835 | NW101: 0.052904952 | NX101: 0.041202203 | NY101: 0.008277645 | NZ101: 0.04870216 | OA101: 0.041508175 | OB101: 0.013117277 | OC101: 0.042372231 | OD101: 0.026368853 | OE101: 0.063428448 | OF101: 0.085242948 | OG101: 0.061765941 | OH101: 0.024013097 | OI101: 0.014398235 | OJ101: 0.023096211 | OK101: 0.061072118 | OL101: 0.055801374 | OM101: 0.079584382 | ON101: 0.03670275 | OO101: 0.066976121 | OP101: 0.081683472 | OQ101: 0.051501147 | OR101: 0.023089336 | OS101: 0.055452457 | OT101: 0.042706738 | OU101: 0.075154976 | OV101: 0.084475955 | OW101: 0.02218093 | OX101: 0.049267206 | OY101: 0.074288169 | OZ101: 0.065486569 | PA101: 0.066318395 | PB101: 0.049282934 | PC101: 0.055601891 | PD101: 0.076212041 | PE101: 0.093430054 | PF101: 0.077306064 | PG101: 0.039731072 | PH101: 0.030583706 | PI101: 0.059612906 | PJ101: 0.058200506 | PK101: 0.094885428 | PL101: 0.056182923 | PM101: 0.044356409 | PN101: 0.016625988 | PO101: 0.052328045 | PP101: 0.083763109 | PQ101: 0.049991512 | PR101: 0.076601296 | PS101: 0.061366058 | PT101: 0.06253388 | PU101: 0.042736246 | PV101: 0.12373528 | PW101: 0.065173148 | PX101: 0.070413667 | PY101: 0.073856542 | PZ101: 0.10275269 | QA101: 0.05417276 | QB101: 0.042827236 | QC101: 0.047415902 | QD101: 0.016647303 | QE101: 0.040493711 | QF101: 0.031193302 | QG101: 0.066087341 | QH101: 0.039380809 | QI101: 0.047253748 | QJ101: 0.020864219 | QK101: 0.033225725 | QL101: 0.055355394 | QM101: 0.062084433 | QN101: 0.030404707 | QO101: 0.04270138 | QP101: 0.049832023 | QQ101: 0.056538974 | QR101: 0.068223101 | QS101: 0.054164538 | QT101: 0.045514606 | QU101: 0.082253302 | QV101: 0.068693977 | QW101: 0.067987319 | QX101: 0.090654531 | QY101: 0.0398942 | QZ101: 0.056379112 | RA101: 0.075847768 | RB101: 0.037927899 | RC101: 0.067740249 | RD101: 0.076705751 | RE101: 0.047670765 | RF101: 0.10289869 | RG101: 0.066448577 | RH101: 0.035337048 | RI101: 0.081043566 | RJ101: 0.059435568 | RK101: 0.039156887 | RL101: 0.088098746 | RM101: 0.047514283 | RN101: 0.039214587 | RO101: 0.09913466 | RP101: 0.075122602 | RQ101: 0.071805067 | RR101: 0.081242276 | RS101: 0.097491176 | RT101: 0.091898875 | RU101: 0.041049446 | RV101: 0.092391009 | RW101: 0.078550179 | RX101: 0.060071921 | RY101: 0.095349715 | RZ101: 0.091141222 | SA101: 0.025214524 | SB101: 0.066178559 | SC101: 0.042910032 | SD101: 0.054047248 | SE101: 0.071279672 | SF101: 0.085914999 | SG101: 0.055897922

Sheet DivVal
A1: Dividend | B1: =DivGrth!M22 -> 3.22 | D1: Discount | E1: 0.0785
B2: 1 | C2: 2 | D2: 3 | E2: 4 | F2: 5 | G2: 6 | H2: 7 | I2: 8 | J2: 9 | K2: 10 | L2: 11 | M2: 12 | N2: 13 | O2: 14 | P2: 15 | Q2: 16 | R2: 17 | S2: 18 | T2: 19 | U2: 20 | V2: 21 | W2: 22 | X2: 23 | Y2: 24 | Z2: 25 | AA2: 26 | AB2: 27 | AC2: 28 | AD2: 29 | AE2: 30 | AF2: 31 | AG2: 32 | AH2: 33 | AI2: 34 | AJ2: 35 | AK2: 36 | AL2: 37 | AM2: 38 | AN2: 39 | AO2: 40 | AP2: 41 | AQ2: 42 | AR2: 43 | AS2: 44 | AT2: 45 | AU2: 46 | AV2: 47 | AW2: 48 | AX2: 49 | AY2: 50 | AZ2: 51 | BA2: 52 | BB2: 53 | BC2: 54 | BD2: 55 | BE2: 56 | BF2: 57 | BG2: 58 | BH2: 59 | BI2: 60 | BJ2: 61 | BK2: 62 | BL2: 63 | BM2: 64 | BN2: 65 | BO2: 66 | BP2: 67 | BQ2: 68 | BR2: 69 | BS2: 70 | BT2: 71 | BU2: 72 | BV2: 73 | BW2: 74 | BX2: 75 | BY2: 76 | BZ2: 77 | CA2: 78 | CB2: 79 | CC2: 80 | CD2: 81 | CE2: 82 | CF2: 83 | CG2: 84 | CH2: 85 | CI2: 86 | CJ2: 87 | CK2: 88 | CL2: 89 | CM2: 90 | CN2: 91 | CO2: 92 | CP2: 93 | CQ2: 94 | CR2: 95 | CS2: 96 | CT2: 97 | CU2: 98 | CV2: 99 | CW2: 100 | CX2: 101 | CY2: 102 | CZ2: 103 | DA2: 104 | DB2: 105 | DC2: 106 | DD2: 107 | DE2: 108 | DF2: 109 | DG2: 110 | DH2: 111 | DI2: 112 | DJ2: 113 | DK2: 114 | DL2: 115 | DM2: 116 | DN2: 117 | DO2: 118 | DP2: 119 | DQ2: 120 | DR2: 121 | DS2: 122 | DT2: 123 | DU2: 124 | DV2: 125 | DW2: 126 | DX2: 127 | DY2: 128 | DZ2: 129 | EA2: 130 | EB2: 131 | EC2: 132 | ED2: 133 | EE2: 134 | EF2: 135 | EG2: 136 | EH2: 137 | EI2: 138 | EJ2: 139 | EK2: 140 | EL2: 141 | EM2: 142 | EN2: 143 | EO2: 144 | EP2: 145 | EQ2: 146 | ER2: 147 | ES2: 148 | ET2: 149 | EU2: 150 | EV2: 151 | EW2: 152 | EX2: 153 | EY2: 154 | EZ2: 155 | FA2: 156 | FB2: 157 | FC2: 158 | FD2: 159 | FE2: 160 | FF2: 161 | FG2: 162 | FH2: 163 | FI2: 164 | FJ2: 165 | FK2: 166 | FL2: 167 | FM2: 168 | FN2: 169 | FO2: 170 | FP2: 171 | FQ2: 172 | FR2: 173 | FS2: 174 | FT2: 175 | FU2: 176 | FV2: 177 | FW2: 178 | FX2: 179 | FY2: 180 | FZ2: 181 | GA2: 182 | GB2: 183 | GC2: 184 | GD2: 185 | GE2: 186 | GF2: 187 | GG2: 188 | GH2: 189 | GI2: 190 | GJ2: 191 | GK2: 192 | GL2: 193 | GM2: 194 | GN2: 195 | GO2: 196 | GP2: 197 | GQ2: 198 | GR2: 199 | GS2: 200 | GT2: 201 | GU2: 202 | GV2: 203 | GW2: 204 | GX2: 205 | GY2: 206 | GZ2: 207 | HA2: 208 | HB2: 209 | HC2: 210 | HD2: 211 | HE2: 212 | HF2: 213 | HG2: 214 | HH2: 215 | HI2: 216 | HJ2: 217 | HK2: 218 | HL2: 219 | HM2: 220 | HN2: 221 | HO2: 222 | HP2: 223 | HQ2: 224 | HR2: 225 | HS2: 226 | HT2: 227 | HU2: 228 | HV2: 229 | HW2: 230 | HX2: 231 | HY2: 232 | HZ2: 233 | IA2: 234 | IB2: 235 | IC2: 236 | ID2: 237 | IE2: 238 | IF2: 239 | IG2: 240 | IH2: 241 | II2: 242 | IJ2: 243 | IK2: 244 | IL2: 245 | IM2: 246 | IN2: 247 | IO2: 248 | IP2: 249 | IQ2: 250 | IR2: 251 | IS2: 252 | IT2: 253 | IU2: 254 | IV2: 255 | IW2: 256 | IX2: 257 | IY2: 258 | IZ2: 259 | JA2: 260 | JB2: 261 | JC2: 262 | JD2: 263 | JE2: 264 | JF2: 265 | JG2: 266 | JH2: 267 | JI2: 268 | JJ2: 269 | JK2: 270 | JL2: 271 | JM2: 272 | JN2: 273 | JO2: 274 | JP2: 275 | JQ2: 276 | JR2: 277 | JS2: 278 | JT2: 279 | JU2: 280 | JV2: 281 | JW2: 282 | JX2: 283 | JY2: 284 | JZ2: 285 | KA2: 286 | KB2: 287 | KC2: 288 | KD2: 289 | KE2: 290 | KF2: 291 | KG2: 292 | KH2: 293 | KI2: 294 | KJ2: 295 | KK2: 296 | KL2: 297 | KM2: 298 | KN2: 299 | KO2: 300 | KP2: 301 | KQ2: 302 | KR2: 303 | KS2: 304 | KT2: 305 | KU2: 306 | KV2: 307 | KW2: 308 | KX2: 309 | KY2: 310 | KZ2: 311 | LA2: 312 | LB2: 313 | LC2: 314 | LD2: 315 | LE2: 316 | LF2: 317 | LG2: 318 | LH2: 319 | LI2: 320 | LJ2: 321 | LK2: 322 | LL2: 323 | LM2: 324 | LN2: 325 | LO2: 326 | LP2: 327 | LQ2: 328 | LR2: 329 | LS2: 330 | LT2: 331 | LU2: 332 | LV2: 333 | LW2: 334 | LX2: 335 | LY2: 336 | LZ2: 337 | MA2: 338 | MB2: 339 | MC2: 340 | MD2: 341 | ME2: 342 | MF2: 343 | MG2: 344 | MH2: 345 | MI2: 346 | MJ2: 347 | MK2: 348 | ML2: 349 | MM2: 350 | MN2: 351 | MO2: 352 | MP2: 353 | MQ2: 354 | MR2: 355 | MS2: 356 | MT2: 357 | MU2: 358 | MV2: 359 | MW2: 360 | MX2: 361 | MY2: 362 | MZ2: 363 | NA2: 364 | NB2: 365 | NC2: 366 | ND2: 367 | NE2: 368 | NF2: 369 | NG2: 370 | NH2: 371 | NI2: 372 | NJ2: 373 | NK2: 374 | NL2: 375 | NM2: 376 | NN2: 377 | NO2: 378 | NP2: 379 | NQ2: 380 | NR2: 381 | NS2: 382 | NT2: 383 | NU2: 384 | NV2: 385 | NW2: 386 | NX2: 387 | NY2: 388 | NZ2: 389 | OA2: 390 | OB2: 391 | OC2: 392 | OD2: 393 | OE2: 394 | OF2: 395 | OG2: 396 | OH2: 397 | OI2: 398 | OJ2: 399 | OK2: 400 | OL2: 401 | OM2: 402 | ON2: 403 | OO2: 404 | OP2: 405 | OQ2: 406 | OR2: 407 | OS2: 408 | OT2: 409 | OU2: 410 | OV2: 411 | OW2: 412 | OX2: 413 | OY2: 414 | OZ2: 415 | PA2: 416 | PB2: 417 | PC2: 418 | PD2: 419 | PE2: 420 | PF2: 421 | PG2: 422 | PH2: 423 | PI2: 424 | PJ2: 425 | PK2: 426 | PL2: 427 | PM2: 428 | PN2: 429 | PO2: 430 | PP2: 431 | PQ2: 432 | PR2: 433 | PS2: 434 | PT2: 435 | PU2: 436 | PV2: 437 | PW2: 438 | PX2: 439 | PY2: 440 | PZ2: 441 | QA2: 442 | QB2: 443 | QC2: 444 | QD2: 445 | QE2: 446 | QF2: 447 | QG2: 448 | QH2: 449 | QI2: 450 | QJ2: 451 | QK2: 452 | QL2: 453 | QM2: 454 | QN2: 455 | QO2: 456 | QP2: 457 | QQ2: 458 | QR2: 459 | QS2: 460 | QT2: 461 | QU2: 462 | QV2: 463 | QW2: 464 | QX2: 465 | QY2: 466 | QZ2: 467 | RA2: 468 | RB2: 469 | RC2: 470 | RD2: 471 | RE2: 472 | RF2: 473 | RG2: 474 | RH2: 475 | RI2: 476 | RJ2: 477 | RK2: 478 | RL2: 479 | RM2: 480 | RN2: 481 | RO2: 482 | RP2: 483 | RQ2: 484 | RR2: 485 | RS2: 486 | RT2: 487 | RU2: 488 | RV2: 489 | RW2: 490 | RX2: 491 | RY2: 492 | RZ2: 493 | SA2: 494 | SB2: 495 | SC2: 496 | SD2: 497 | SE2: 498 | SF2: 499 | SG2: 500
A3: 1 | B3: =$B$1*(1+RndGrth!B2) -> 3.3852728 | C3: =$B$1*(1+RndGrth!C2) -> 3.4593379 | D3: =$B$1*(1+RndGrth!D2) -> 3.4902991 | E3: =$B$1*(1+RndGrth!E2) -> 3.4099305 | F3: =$B$1*(1+RndGrth!F2) -> 3.3883191 | G3: =$B$1*(1+RndGrth!G2) -> 3.3370853 | H3: =$B$1*(1+RndGrth!H2) -> 3.5010011 | I3: =$B$1*(1+RndGrth!I2) -> 3.5955378 | ... SG3: =$B$1*(1+RndGrth!SG2) -> 3.5342672
A4: 2 | B4: =B3*(1+RndGrth!B3) -> 3.6092002 | C4: =C3*(1+RndGrth!C3) -> 3.727524 | D4: =D3*(1+RndGrth!D3) -> 3.8425728 | E4: =E3*(1+RndGrth!E3) -> 3.7107168 | F4: =F3*(1+RndGrth!F3) -> 3.6601243 | G4: =G3*(1+RndGrth!G3) -> 3.5909856 | H4: =H3*(1+RndGrth!H3) -> 3.7487665 | I4: =I3*(1+RndGrth!I3) -> 3.8714003 | ... SG4: =SG3*(1+RndGrth!SG3) -> 3.8172932
A5: 3 | B5: =B4*(1+RndGrth!B4) -> 3.926759 | C5: =C4*(1+RndGrth!C4) -> 3.8053258 | D5: =D4*(1+RndGrth!D4) -> 4.100998 | E5: =E4*(1+RndGrth!E4) -> 3.9121024 | F5: =F4*(1+RndGrth!F4) -> 3.7519269 | G5: =G4*(1+RndGrth!G4) -> 3.8723432 | H5: =H4*(1+RndGrth!H4) -> 4.046967 | I5: =I4*(1+RndGrth!I4) -> 4.0527067 | ... SG5: =SG4*(1+RndGrth!SG4) -> 4.2491999
A6: 4 | B6: =B5*(1+RndGrth!B5) -> 4.0378679 | C6: =C5*(1+RndGrth!C5) -> 3.8419585 | D6: =D5*(1+RndGrth!D5) -> 4.1887286 | E6: =E5*(1+RndGrth!E5) -> 4.06468 | F6: =F5*(1+RndGrth!F5) -> 3.9937338 | G6: =G5*(1+RndGrth!G5) -> 4.1866811 | H6: =H5*(1+RndGrth!H5) -> 4.2657778 | I6: =I5*(1+RndGrth!I5) -> 4.2989982 | ... SG6: =SG5*(1+RndGrth!SG5) -> 4.4787087
A7: 5 | B7: =B6*(1+RndGrth!B6) -> 4.2851641 | C7: =C6*(1+RndGrth!C6) -> 3.9915888 | D7: =D6*(1+RndGrth!D6) -> 4.6465281 | E7: =E6*(1+RndGrth!E6) -> 4.2970326 | F7: =F6*(1+RndGrth!F6) -> 4.2533463 | G7: =G6*(1+RndGrth!G6) -> 4.4537452 | H7: =H6*(1+RndGrth!H6) -> 4.2175726 | I7: =I6*(1+RndGrth!I6) -> 4.5021216 | ... SG7: =SG6*(1+RndGrth!SG6) -> 4.779715
A8: 6 | B8: =B7*(1+RndGrth!B7) -> 4.3818095 | C8: =C7*(1+RndGrth!C7) -> 4.2744436 | D8: =D7*(1+RndGrth!D7) -> 4.9632818 | E8: =E7*(1+RndGrth!E7) -> 4.7283056 | F8: =F7*(1+RndGrth!F7) -> 4.3817643 | G8: =G7*(1+RndGrth!G7) -> 4.8029272 | H8: =H7*(1+RndGrth!H7) -> 4.5065373 | I8: =I7*(1+RndGrth!I7) -> 4.9069195 | ... SG8: =SG7*(1+RndGrth!SG7) -> 4.9859928
A9: 7 | B9: =B8*(1+RndGrth!B8) -> 4.590959 | C9: =C8*(1+RndGrth!C8) -> 4.596234 | D9: =D8*(1+RndGrth!D8) -> 5.3101408 | E9: =E8*(1+RndGrth!E8) -> 4.8776372 | F9: =F8*(1+RndGrth!F8) -> 4.4865301 | G9: =G8*(1+RndGrth!G8) -> 5.1403575 | H9: =H8*(1+RndGrth!H8) -> 4.920037 | I9: =I8*(1+RndGrth!I8) -> 5.17749 | ... SG9: =SG8*(1+RndGrth!SG8) -> 5.4318936
A10: 8 | B10: =B9*(1+RndGrth!B9) -> 4.9211577 | C10: =C9*(1+RndGrth!C9) -> 5.0164927 | D10: =D9*(1+RndGrth!D9) -> 5.7835085 | E10: =E9*(1+RndGrth!E9) -> 4.9878517 | F10: =F9*(1+RndGrth!F9) -> 4.96329 | G10: =G9*(1+RndGrth!G9) -> 5.4122432 | H10: =H9*(1+RndGrth!H9) -> 5.219581 | I10: =I9*(1+RndGrth!I9) -> 5.335444 | ... SG10: =SG9*(1+RndGrth!SG9) -> 5.683941
A11: 9 | B11: =B10*(1+RndGrth!B10) -> 5.2154321 | C11: =C10*(1+RndGrth!C10) -> 5.5072314 | D11: =D10*(1+RndGrth!D10) -> 6.2232769 | E11: =E10*(1+RndGrth!E10) -> 5.2315863 | F11: =F10*(1+RndGrth!F10) -> 5.3677225 | G11: =G10*(1+RndGrth!G10) -> 5.9918567 | H11: =H10*(1+RndGrth!H10) -> 5.6594361 | I11: =I10*(1+RndGrth!I10) -> 5.6844412 | ... SG11: =SG10*(1+RndGrth!SG10) -> 6.3394744
A12: 10 | B12: =B11*(1+RndGrth!B11) -> 5.6289771 | C12: =C11*(1+RndGrth!C11) -> 5.6128784 | D12: =D11*(1+RndGrth!D11) -> 6.2945713 | E12: =E11*(1+RndGrth!E11) -> 5.3872057 | F12: =F11*(1+RndGrth!F11) -> 5.6511388 | G12: =G11*(1+RndGrth!G11) -> 6.2494938 | H12: =H11*(1+RndGrth!H11) -> 5.9122065 | I12: =I11*(1+RndGrth!I11) -> 5.9830375 | ... SG12: =SG11*(1+RndGrth!SG11) -> 6.7766495
A13: 11 | B13: =B12*(1+RndGrth!B12) -> 5.9099421 | C13: =C12*(1+RndGrth!C12) -> 5.6959863 | D13: =D12*(1+RndGrth!D12) -> 6.7078659 | E13: =E12*(1+RndGrth!E12) -> 5.7751368 | F13: =F12*(1+RndGrth!F12) -> 6.1184009 | G13: =G12*(1+RndGrth!G12) -> 6.6594777 | H13: =H12*(1+RndGrth!H12) -> 6.3643025 | I13: =I12*(1+RndGrth!I12) -> 6.3231845 | ... SG13: =SG12*(1+RndGrth!SG12) -> 7.1570557
A14: 12 | B14: =B13*(1+RndGrth!B13) -> 5.9201424 | C14: =C13*(1+RndGrth!C13) -> 5.9923425 | D14: =D13*(1+RndGrth!D13) -> 6.9358922 | E14: =E13*(1+RndGrth!E13) -> 5.965771 | F14: =F13*(1+RndGrth!F13) -> 6.526924 | G14: =G13*(1+RndGrth!G13) -> 7.2529129 | H14: =H13*(1+RndGrth!H13) -> 6.4640882 | I14: =I13*(1+RndGrth!I13) -> 6.5312081 | ... SG14: =SG13*(1+RndGrth!SG13) -> 7.4327021
A15: 13 | B15: =B14*(1+RndGrth!B14) -> 6.2104917 | C15: =C14*(1+RndGrth!C14) -> 6.5175369 | D15: =D14*(1+RndGrth!D14) -> 7.1711457 | E15: =E14*(1+RndGrth!E14) -> 6.5602827 | F15: =F14*(1+RndGrth!F14) -> 6.9976486 | G15: =G14*(1+RndGrth!G14) -> 7.5839371 | H15: =H14*(1+RndGrth!H14) -> 6.8217141 | I15: =I14*(1+RndGrth!I14) -> 6.7415382 | ... SG15: =SG14*(1+RndGrth!SG14) -> 8.0400187
... A102: 100 | B102: =B101*(1+RndGrth!B101) -> 1609.6031 | C102: =C101*(1+RndGrth!C101) -> 1613.7576 | D102: =D101*(1+RndGrth!D101) -> 1277.2483 | E102: =E101*(1+RndGrth!E101) -> 1227.8156 | F102: =F101*(1+RndGrth!F101) -> 1254.7673 | G102: =G101*(1+RndGrth!G101) -> 2075.3257 | H102: =H101*(1+RndGrth!H101) -> 1176.3059 | I102: =I101*(1+RndGrth!I101) -> 1014.1152 | ... SG102: =SG101*(1+RndGrth!SG101) -> 2052.5791
A104: Npv 100 | B104: =NPV($E$1,B3:B102) -> 160.26888 | C104: =NPV($E$1,C3:C102) -> 164.82718 | D104: =NPV($E$1,D3:D102) -> 159.66142 | E104: =NPV($E$1,E3:E102) -> 154.96184 | F104: =NPV($E$1,F3:F102) -> 154.84011 | G104: =NPV($E$1,G3:G102) -> 194.18608 | H104: =NPV($E$1,H3:H102) -> 171.97251 | I104: =NPV($E$1,I3:I102) -> 147.70794 | ... SG104: =NPV($E$1,SG3:SG102) -> 190.59752
A105: Npv 75 | B105: =NPV($E$1,B3:B77) -> 136.42393 | C105: =NPV($E$1,C3:C77) -> 142.7564 | D105: =NPV($E$1,D3:D77) -> 139.46382 | E105: =NPV($E$1,E3:E77) -> 134.50803 | F105: =NPV($E$1,F3:F77) -> 136.13777 | G105: =NPV($E$1,G3:G77) -> 163.30883 | H105: =NPV($E$1,H3:H77) -> 152.95278 | I105: =NPV($E$1,I3:I77) -> 130.75006 | ... SG105: =NPV($E$1,SG3:SG77) -> 160.81266
A106: Npv 50 | B106: =NPV($E$1,B3:B52) -> 106.18541 | C106: =NPV($E$1,C3:C52) -> 110.91287 | D106: =NPV($E$1,D3:D52) -> 112.57602 | E106: =NPV($E$1,E3:E52) -> 104.09195 | F106: =NPV($E$1,F3:F52) -> 108.69521 | G106: =NPV($E$1,G3:G52) -> 121.92978 | H106: =NPV($E$1,H3:H52) -> 118.6485 | I106: =NPV($E$1,I3:I52) -> 105.25849 | ... SG106: =NPV($E$1,SG3:SG52) -> 123.58063
A107: Npv 35 | B107: =NPV($E$1,B3:B37) -> 81.494604 | C107: =NPV($E$1,C3:C37) -> 83.851035 | D107: =NPV($E$1,D3:D37) -> 89.095691 | E107: =NPV($E$1,E3:E37) -> 80.781541 | F107: =NPV($E$1,F3:F37) -> 84.897253 | G107: =NPV($E$1,G3:G37) -> 91.464455 | H107: =NPV($E$1,H3:H37) -> 91.566145 | I107: =NPV($E$1,I3:I37) -> 82.09284 | ... SG107: =NPV($E$1,SG3:SG37) -> 93.859949
A109: Pv 100 | B109: =-PV($E$1,100,0,B102,0) -> 0.84082157 | C109: =-PV($E$1,100,0,C102,0) -> 0.84299179 | D109: =-PV($E$1,100,0,D102,0) -> 0.66720669 | E109: =-PV($E$1,100,0,E102,0) -> 0.64138411 | F109: =-PV($E$1,100,0,F102,0) -> 0.6554631 | G109: =-PV($E$1,100,0,G102,0) -> 1.084105 | H109: =-PV($E$1,100,0,H102,0) -> 0.61447657 | I109: =-PV($E$1,100,0,I102,0) -> 0.52975168 | ... SG109: =-PV($E$1,100,0,SG102,0) -> 1.0722226

Sheet StkVal
B1: 100 | E1: 75 | H1: 50 | K1: 35
A2: Average | B2: =AVERAGE(DivVal!B104:SG104) -> 170.34684 | D2: Average | E2: =AVERAGE(DivVal!B105:SG105) -> 147.172 | G2: Average | H2: =AVERAGE(DivVal!B106:SG106) -> 114.19364 | J2: Average | K2: =AVERAGE(DivVal!B107:SG107) -> 87.924763
A3: Std | B3: =_xlfn.STDEV.S(DivVal!B104:SG104) -> 19.342007 | D3: Std | E3: =_xlfn.STDEV.S(DivVal!B105:SG105) -> 15.171021 | G3: Std | H3: =_xlfn.STDEV.S(DivVal!B106:SG106) -> 10.057001 | J3: Std | K3: =_xlfn.STDEV.S(DivVal!B107:SG107) -> 6.6187172
A4: Median | B4: =MEDIAN(DivVal!B104:SG104) -> 168.42133 | D4: Median | E4: =MEDIAN(DivVal!B105:SG105) -> 146.06466 | G4: Median | H4: =MEDIAN(DivVal!B106:SG106) -> 113.54671 | J4: Median | K4: =MEDIAN(DivVal!B107:SG107) -> 87.620357
A5: Max | B5: =MAX(DivVal!B104:SG104) -> 256.8135 | D5: Max | E5: =MAX(DivVal!B105:SG105) -> 212.4163 | G5: Max | H5: =MAX(DivVal!B106:SG106) -> 159.12772 | J5: Max | K5: =MAX(DivVal!B107:SG107) -> 115.00938
A6: Min | B6: =MIN(DivVal!B104:SG104) -> 126.70238 | D6: Min | E6: =MIN(DivVal!B105:SG105) -> 113.94199 | G6: Min | H6: =MIN(DivVal!B106:SG106) -> 89.578997 | J6: Min | K6: =MIN(DivVal!B107:SG107) -> 70.620907
A7: High Range | B7: =B2+B3 -> 189.68885 | D7: High Range | E7: =E2+E3 -> 162.34302 | G7: High Range | H7: =H2+H3 -> 124.25064 | J7: High Range | K7: =K2+K3 -> 94.54348
A8: Low Range | B8: =B2-B3 -> 151.00483 | D8: Low Range | E8: =E2-E3 -> 132.00098 | G8: Low Range | H8: =H2-H3 -> 104.13664 | J8: Low Range | K8: =K2-K3 -> 81.306046

Sheet Sheet1
B10: Dividend Discount Model Estimates with Goal Seek for Different Time Horizons
B11: GOAL SEEK | C11: 75 | D11: 50 | E11: 35
B12: Stock Price | C12: 53.859963 | D12: 53.859999 | E12: 53.859887
B13: Standard Deviation | C13: 3.7168038 | D13: 3.6390249 | E13: 3.4995388
B14: Median | C14: 53.77782 | D14: 53.739708 | E14: 53.726352
B15: Max | C15: 69.152939 | D15: 68.763105 | E15: 67.276477
B16: Min | C16: 44.171297 | D16: 44.218038 | E16: 44.501086
B17: High Range | C17: 57.576767 | D17: 57.499024 | E17: 57.359426
B18: Low Range | C18: 50.143159 | D18: 50.220974 | E18: 50.360349
B19: Fitted Discount Rate | C19: 0.12580947 | D19: 0.12245514 | E19: 0.1144222

Sheet Sheet2
C2: Net present value calculations at dicount rate of 7.85%
C3: NPV | D3: 100 | E3: 75 | F3: 50 | G3: 35
C4: Average | D4: 170.20518 | E4: 147.07338 | F4: 114.13873 | G4: 87.89375
C5: Std | D5: 19.320323 | E5: 15.157538 | F5: 10.0507 | G5: 6.615749
C6: Median | D6: 168.28596 | E6: 145.96729 | F6: 113.49184 | G6: 87.589216
C7: Max | D7: 256.57558 | E7: 212.26115 | F7: 159.04346 | G7: 114.9653
C8: Min | D8: 126.61044 | E8: 113.87552 | F8: 89.538141 | G8: 70.597272
C9: High Range | D9: 189.52551 | E9: 162.23092 | F9: 124.18943 | G9: 94.509499
C10: Low Range | D10: 150.88486 | E10: 131.91584 | F10: 104.08803 | G10: 81.278001
